{"40": {"sim0": {"simulation_id": 0, "user_seed": 19698229, "Nearest": {"max_delay": 0.1480657226707115, "cost": 122.225, "target_value": 178.6219726707115, "running_time": 1.001119613647461, "local_count": 80, "common_count": 0}, "M-Greedy": {"max_delay": 0.2323292273321046, "cost": 102.5, "target_value": 257.95422733210455, "running_time": 236.19532585144043, "n_selected_site": 1, "local_count": 80, "common_count": 0}, "M-Greedy-V2(Tx+Tp+Tq)": {"max_delay": 0.13749862347770908, "cost": 104.475, "target_value": 163.6173734777091, "running_time": 1372.6437091827393, "n_selected_site": 6, "local_count": 4, "common_count": 76}, "Ours": {"max_delay": 0.1337803616804393, "cost": 97.575, "target_value": 158.17411168043932, "running_time": 17326.991081237793, "local_count": 46, "common_count": 34}}, "sim1": {"simulation_id": 1, "user_seed": 55030839, "Nearest": {"max_delay": 0.14432463640333087, "cost": 116.425, "target_value": 173.43088640333087, "running_time": 1.0004043579101562, "local_count": 80, "common_count": 0}, "M-Greedy": {"max_delay": 0.14266166522816456, "cost": 102.35, "target_value": 168.24916522816457, "running_time": 1118.6587810516357, "n_selected_site": 9, "local_count": 48, "common_count": 32}, "M-Greedy-V2(Tx+Tp+Tq)": {"max_delay": 0.13440306400477126, "cost": 95.6, "target_value": 158.30306400477127, "running_time": 1418.008804321289, "n_selected_site": 6, "local_count": 20, "common_count": 60}, "Ours": {"max_delay": 0.13168591042697425, "cost": 93.85, "target_value": 155.14841042697427, "running_time": 17764.17326927185, "local_count": 43, "common_count": 37}}, "sim2": {"simulation_id": 2, "user_seed": 56394148, "Nearest": {"max_delay": 0.14263837453384046, "cost": 119.175, "target_value": 172.43212453384044, "running_time": 1.0006427764892578, "local_count": 80, "common_count": 0}, "M-Greedy": {"max_delay": 0.14117445874790296, "cost": 99.6, "target_value": 166.07445874790298, "running_time": 1292.1414375305176, "n_selected_site": 11, "local_count": 22, "common_count": 58}, "M-Greedy-V2(Tx+Tp+Tq)": {"max_delay": 0.13461628003774623, "cost": 96.7, "target_value": 158.79128003774625, "running_time": 1935.8010292053223, "n_selected_site": 9, "local_count": 12, "common_count": 68}, "Ours": {"max_delay": 0.13315236425180876, "cost": 95.225, "target_value": 156.95861425180877, "running_time": 17826.871633529663, "local_count": 36, "common_count": 44}}}, "50": {"sim0": {"simulation_id": 0, "user_seed": 88700724, "Nearest": {"max_delay": 0.14717319768772724, "cost": 137.68, "target_value": 181.59319768772724, "running_time": 2.001523971557617, "local_count": 100, "common_count": 0}, "M-Greedy": {"max_delay": 0.14242901164121557, "cost": 123.6, "target_value": 173.32901164121557, "running_time": 2271.411180496216, "n_selected_site": 13, "local_count": 58, "common_count": 42}, "M-Greedy-V2(Tx+Tp+Tq)": {"max_delay": 0.13819396825835106, "cost": 113.28, "target_value": 166.51396825835104, "running_time": 2753.8375854492188, "n_selected_site": 8, "local_count": 24, "common_count": 76}, "Ours": {"max_delay": 0.1350569626039284, "cost": 108.48, "target_value": 162.17696260392842, "running_time": 26040.520191192627, "local_count": 50, "common_count": 50}}, "sim1": {"simulation_id": 1, "user_seed": 30949762, "Nearest": {"max_delay": 0.1513477943399311, "cost": 137.1, "target_value": 185.6227943399311, "running_time": 2.001523971557617, "local_count": 100, "common_count": 0}, "M-Greedy": {"max_delay": 0.13912274295525912, "cost": 117.9, "target_value": 168.59774295525912, "running_time": 1967.9474830627441, "n_selected_site": 11, "local_count": 42, "common_count": 58}, "M-Greedy-V2(Tx+Tp+Tq)": {"max_delay": 0.1373713304240613, "cost": 113.3, "target_value": 165.6963304240613, "running_time": 2708.3001136779785, "n_selected_site": 8, "local_count": 24, "common_count": 76}, "Ours": {"max_delay": 0.13340845240268034, "cost": 106.58, "target_value": 160.05345240268036, "running_time": 25720.160484313965, "local_count": 42, "common_count": 58}}, "sim2": {"simulation_id": 2, "user_seed": 21782465, "Nearest": {"max_delay": 0.1464556167500791, "cost": 133.56, "target_value": 179.8456167500791, "running_time": 2.0017623901367188, "local_count": 100, "common_count": 0}, "M-Greedy": {"max_delay": 0.1464556167500791, "cost": 123.0, "target_value": 177.2056167500791, "running_time": 2237.424612045288, "n_selected_site": 13, "local_count": 60, "common_count": 40}, "M-Greedy-V2(Tx+Tp+Tq)": {"max_delay": 0.1378763809291118, "cost": 112.82, "target_value": 166.0813809291118, "running_time": 2740.5600547790527, "n_selected_site": 8, "local_count": 24, "common_count": 76}, "Ours": {"max_delay": 0.1334568960225525, "cost": 105.84, "target_value": 159.91689602255252, "running_time": 25695.053577423096, "local_count": 45, "common_count": 55}}}, "60": {"sim0": {"simulation_id": 0, "user_seed": 20118035, "Nearest": {"max_delay": 0.1506246423063477, "cost": 175.21666666666667, "target_value": 194.42880897301438, "running_time": 2.0012855529785156, "local_count": 120, "common_count": 0}, "M-Greedy": {"max_delay": 0.14888045625983606, "cost": 145.75, "target_value": 185.31795625983605, "running_time": 2458.1027030944824, "n_selected_site": 9, "local_count": 32, "common_count": 88}, "M-Greedy-V2(Tx+Tp+Tq)": {"max_delay": 0.1378503599798799, "cost": 133.55, "target_value": 171.2378599798799, "running_time": 3211.789608001709, "n_selected_site": 6, "local_count": 24, "common_count": 96}, "Ours": {"max_delay": 0.1341947082553265, "cost": 127.86666666666666, "target_value": 166.16137492199317, "running_time": 34436.514377593994, "local_count": 48, "common_count": 72}}, "sim1": {"simulation_id": 1, "user_seed": 26217104, "Nearest": {"max_delay": 0.14981713304422767, "cost": 161.9, "target_value": 190.29213304422765, "running_time": 2.0020008087158203, "local_count": 120, "common_count": 0}, "M-Greedy": {"max_delay": 0.13922983145692608, "cost": 138.41666666666666, "target_value": 173.83399812359275, "running_time": 2906.416416168213, "n_selected_site": 11, "local_count": 72, "common_count": 48}, "M-Greedy-V2(Tx+Tp+Tq)": {"max_delay": 0.13753893571624337, "cost": 132.36666666666667, "target_value": 170.63060238291004, "running_time": 3189.9921894073486, "n_selected_site": 6, "local_count": 20, "common_count": 100}, "Ours": {"max_delay": 0.1330887728228411, "cost": 121.56666666666666, "target_value": 163.48043948950777, "running_time": 35014.570474624634, "local_count": 60, "common_count": 60}}, "sim2": {"simulation_id": 2, "user_seed": 96688416, "Nearest": {"max_delay": 0.1466656149376177, "cost": 153.2, "target_value": 184.96561493761772, "running_time": 2.001523971557617, "local_count": 120, "common_count": 0}, "M-Greedy": {"max_delay": 0.2326130814698752, "cost": 123.0, "target_value": 263.36308146987517, "running_time": 565.0539398193359, "n_selected_site": 1, "local_count": 120, "common_count": 0}, "M-Greedy-V2(Tx+Tp+Tq)": {"max_delay": 0.13887764945566938, "cost": 131.86666666666667, "target_value": 171.84431612233604, "running_time": 3176.630973815918, "n_selected_site": 6, "local_count": 22, "common_count": 98}, "Ours": {"max_delay": 0.13254815805994657, "cost": 118.53333333333333, "target_value": 162.1814913932799, "running_time": 34559.36694145203, "local_count": 64, "common_count": 56}}}, "70": {"sim0": {"simulation_id": 0, "user_seed": 66150656, "Nearest": {"max_delay": 0.15015599065899685, "cost": 177.12857142857143, "target_value": 194.43813351613971, "running_time": 3.0031204223632812, "local_count": 140, "common_count": 0}, "M-Greedy": {"max_delay": 0.13776503469419, "cost": 148.34285714285716, "target_value": 174.85074897990427, "running_time": 3671.9675064086914, "n_selected_site": 10, "local_count": 74, "common_count": 66}, "M-Greedy-V2(Tx+Tp+Tq)": {"max_delay": 0.13776503469419, "cost": 150.92857142857142, "target_value": 175.49717755133284, "running_time": 4267.294645309448, "n_selected_site": 6, "local_count": 38, "common_count": 102}, "Ours": {"max_delay": 0.13517935493145938, "cost": 141.67142857142858, "target_value": 170.59721207431653, "running_time": 25655.431032180786, "local_count": 95, "common_count": 45}}, "sim1": {"simulation_id": 1, "user_seed": 69002220, "Nearest": {"max_delay": 0.14322250638320816, "cost": 170.82857142857142, "target_value": 185.929649240351, "running_time": 3.002643585205078, "local_count": 140, "common_count": 0}, "M-Greedy": {"max_delay": 0.14322250638320816, "cost": 156.11428571428573, "target_value": 182.2510778117796, "running_time": 3662.555694580078, "n_selected_site": 10, "local_count": 78, "common_count": 62}, "M-Greedy-V2(Tx+Tp+Tq)": {"max_delay": 0.13257921375316453, "cost": 137.75714285714287, "target_value": 167.01849946745025, "running_time": 5905.686616897583, "n_selected_site": 9, "local_count": 24, "common_count": 116}, "Ours": {"max_delay": 0.12840197196922612, "cost": 131.75714285714287, "target_value": 161.34125768351183, "running_time": 46231.57262802124, "local_count": 79, "common_count": 61}}, "sim2": {"simulation_id": 2, "user_seed": 78235480, "Nearest": {"max_delay": 0.1486246423063477, "cost": 163.1, "target_value": 189.39964230634772, "running_time": 2.0020008087158203, "local_count": 140, "common_count": 0}, "M-Greedy": {"max_delay": 0.1486246423063477, "cost": 145.17142857142858, "target_value": 184.91749944920485, "running_time": 3965.796709060669, "n_selected_site": 11, "local_count": 50, "common_count": 90}, "M-Greedy-V2(Tx+Tp+Tq)": {"max_delay": 0.1358503599798799, "cost": 134.4142857142857, "target_value": 169.45393140845133, "running_time": 4869.547367095947, "n_selected_site": 7, "local_count": 30, "common_count": 110}, "Ours": {"max_delay": 0.13416815443435237, "cost": 129.8, "target_value": 166.6181544343524, "running_time": 46190.91701507568, "local_count": 80, "common_count": 60}}}, "80": {"sim0": {"simulation_id": 0, "user_seed": 91129259, "Nearest": {"max_delay": 0.1514711853281628, "cost": 202.4875, "target_value": 202.09306032816284, "running_time": 3.001689910888672, "local_count": 160, "common_count": 0}, "M-Greedy": {"max_delay": 0.13877107480885875, "cost": 154.7625, "target_value": 177.46169980885873, "running_time": 4728.540897369385, "n_selected_site": 10, "local_count": 70, "common_count": 90}, "M-Greedy-V2(Tx+Tp+Tq)": {"max_delay": 0.1385507906657422, "cost": 159.2375, "target_value": 178.36016566574222, "running_time": 7613.053321838379, "n_selected_site": 9, "local_count": 32, "common_count": 128}, "Ours": {"max_delay": 0.13336623168629833, "cost": 155.525, "target_value": 172.24748168629833, "running_time": 58677.99711227417, "local_count": 73, "common_count": 87}}, "sim1": {"simulation_id": 1, "user_seed": 74427495, "Nearest": {"max_delay": 0.15024820293353014, "cost": 188.125, "target_value": 197.27945293353014, "running_time": 3.0031204223632812, "local_count": 160, "common_count": 0}, "M-Greedy": {"max_delay": 0.23353678607023215, "cost": 157.25, "target_value": 272.84928607023215, "running_time": 977.3328304290771, "n_selected_site": 1, "local_count": 160, "common_count": 0}, "M-Greedy-V2(Tx+Tp+Tq)": {"max_delay": 0.23353678607023215, "cost": 157.25, "target_value": 272.84928607023215, "running_time": 1758.9375972747803, "n_selected_site": 1, "local_count": 160, "common_count": 0}, "Ours": {"max_delay": 0.1328068455973851, "cost": 151.0625, "target_value": 170.5724705973851, "running_time": 58855.68165779114, "local_count": 94, "common_count": 66}}, "sim2": {"simulation_id": 2, "user_seed": 8647026, "Nearest": {"max_delay": 0.14553855554281836, "cost": 181.7375, "target_value": 190.97293054281835, "running_time": 3.0024051666259766, "local_count": 160, "common_count": 0}, "M-Greedy": {"max_delay": 0.13958157157593998, "cost": 150.975, "target_value": 177.32532157594, "running_time": 4675.570487976074, "n_selected_site": 10, "local_count": 64, "common_count": 96}, "M-Greedy-V2(Tx+Tp+Tq)": {"max_delay": 0.13846634128021135, "cost": 156.9875, "target_value": 177.71321628021133, "running_time": 5534.648656845093, "n_selected_site": 6, "local_count": 26, "common_count": 134}, "Ours": {"max_delay": 0.1326549030946833, "cost": 146.55, "target_value": 169.29240309468332, "running_time": 59451.950550079346, "local_count": 82, "common_count": 78}}}, "90": {"sim0": {"simulation_id": 0, "user_seed": 75585092, "Nearest": {"max_delay": 0.15085561098725186, "cost": 224.12222222222223, "target_value": 206.88616654280742, "running_time": 3.9114952087402344, "local_count": 180, "common_count": 0}, "M-Greedy": {"max_delay": 0.14072118103830122, "cost": 180.77777777777777, "target_value": 185.91562548274567, "running_time": 6433.575630187988, "n_selected_site": 11, "local_count": 104, "common_count": 76}, "M-Greedy-V2(Tx+Tp+Tq)": {"max_delay": 0.1397499181030275, "cost": 175.93333333333334, "target_value": 183.73325143636083, "running_time": 8892.953395843506, "n_selected_site": 8, "local_count": 44, "common_count": 136}, "Ours": {"max_delay": 0.13523808789467925, "cost": 169.24444444444444, "target_value": 177.54919900579037, "running_time": 74472.00632095337, "local_count": 96, "common_count": 84}}, "sim1": {"simulation_id": 1, "user_seed": 29038042, "Nearest": {"max_delay": 0.14729457573182297, "cost": 217.75555555555556, "target_value": 201.73346462071189, "running_time": 4.003047943115234, "local_count": 180, "common_count": 0}, "M-Greedy": {"max_delay": 0.15274086587578753, "cost": 180.63333333333333, "target_value": 197.89919920912087, "running_time": 5966.2926197052, "n_selected_site": 10, "local_count": 38, "common_count": 142}, "M-Greedy-V2(Tx+Tp+Tq)": {"max_delay": 0.13932543747589599, "cost": 176.07777777777778, "target_value": 183.34488192034044, "running_time": 9670.441150665283, "n_selected_site": 9, "local_count": 22, "common_count": 158}, "Ours": {"max_delay": 0.13261502435874994, "cost": 168.6, "target_value": 174.76502435874994, "running_time": 73698.01425933838, "local_count": 94, "common_count": 86}}, "sim2": {"simulation_id": 2, "user_seed": 98788004, "Nearest": {"max_delay": 0.15064954842962797, "cost": 218.95555555555555, "target_value": 205.38843731851685, "running_time": 3.002643585205078, "local_count": 180, "common_count": 0}, "M-Greedy": {"max_delay": 0.13669805777531946, "cost": 173.43333333333334, "target_value": 180.0563911086528, "running_time": 6052.4327754974365, "n_selected_site": 10, "local_count": 50, "common_count": 130}, "M-Greedy-V2(Tx+Tp+Tq)": {"max_delay": 0.13669805777531946, "cost": 174.9111111111111, "target_value": 180.42583555309722, "running_time": 10641.501665115356, "n_selected_site": 10, "local_count": 32, "common_count": 148}, "Ours": {"max_delay": 0.13198752900219, "cost": 167.27777777777777, "target_value": 173.80697344663446, "running_time": 73509.28616523743, "local_count": 83, "common_count": 97}}}, "100": {"sim0": {"simulation_id": 0, "user_seed": 99579997, "Nearest": {"max_delay": 0.15238740683484708, "cost": 227.08, "target_value": 209.15740683484708, "running_time": 4.003763198852539, "local_count": 200, "common_count": 0}, "M-Greedy": {"max_delay": 0.14053497385765243, "cost": 190.84, "target_value": 188.24497385765244, "running_time": 7953.566789627075, "n_selected_site": 11, "local_count": 106, "common_count": 94}, "M-Greedy-V2(Tx+Tp+Tq)": {"max_delay": 0.1384583067920181, "cost": 193.73, "target_value": 186.8908067920181, "running_time": 9831.691026687622, "n_selected_site": 7, "local_count": 48, "common_count": 152}, "Ours": {"max_delay": 0.13414950440386997, "cost": 179.8, "target_value": 179.09950440386996, "running_time": 92214.90216255188, "local_count": 115, "common_count": 85}}, "sim1": {"simulation_id": 1, "user_seed": 81467781, "Nearest": {"max_delay": 0.15011273811910494, "cost": 227.94, "target_value": 207.09773811910492, "running_time": 4.003047943115234, "local_count": 200, "common_count": 0}, "M-Greedy": {"max_delay": 0.13929533712467207, "cost": 179.93, "target_value": 184.2778371246721, "running_time": 7259.703874588013, "n_selected_site": 10, "local_count": 78, "common_count": 122}, "M-Greedy-V2(Tx+Tp+Tq)": {"max_delay": 0.13929533712467207, "cost": 181.95, "target_value": 184.78283712467208, "running_time": 8612.11633682251, "n_selected_site": 6, "local_count": 24, "common_count": 176}, "Ours": {"max_delay": 0.13308383289604464, "cost": 175.72, "target_value": 177.01383289604465, "running_time": 90252.42161750793, "local_count": 108, "common_count": 92}}, "sim2": {"simulation_id": 2, "user_seed": 48256217, "Nearest": {"max_delay": 0.15161700289418364, "cost": 239.37, "target_value": 211.45950289418366, "running_time": 4.004001617431641, "local_count": 200, "common_count": 0}, "M-Greedy": {"max_delay": 0.1385178585979835, "cost": 191.22, "target_value": 186.3228585979835, "running_time": 7043.0498123168945, "n_selected_site": 10, "local_count": 64, "common_count": 136}, "M-Greedy-V2(Tx+Tp+Tq)": {"max_delay": 0.1383733583334776, "cost": 191.83, "target_value": 186.3308583334776, "running_time": 9395.888805389404, "n_selected_site": 7, "local_count": 52, "common_count": 148}, "Ours": {"max_delay": 0.1342122251510824, "cost": 182.79, "target_value": 179.90972515108237, "running_time": 51111.95874214172, "local_count": 114, "common_count": 86}}}}