{"40": {"sim0": {"simulation_id": 0, "user_seed": 48738449, "Nearest": {"avg_delay": 0.09930331812413741, "cost": 136.35, "target_value": 119.7558181241374, "running_time": 2.0020008087158203, "local_count": 80, "common_count": 0}, "Modify-Assignment(Tx)": {"avg_delay": 0.10036859759438257, "cost": 141.9, "target_value": 121.65359759438257, "running_time": 52.04296112060547, "local_count": 80, "common_count": 0}, "Modify-Assignment(Tx+Tp+Tq)": {"avg_delay": 0.09568003649444608, "cost": 134.6, "target_value": 115.87003649444607, "running_time": 20064.205646514893, "local_count": 56, "common_count": 24}, "Ours": {"avg_delay": 0.09099646472229642, "cost": 111.475, "target_value": 107.71771472229642, "running_time": 342.39768981933594, "local_count": 44, "common_count": 36}}, "sim1": {"simulation_id": 1, "user_seed": 55450840, "Nearest": {"avg_delay": 0.09610767206798862, "cost": 124.6, "target_value": 114.79767206798861, "running_time": 2.0017623901367188, "local_count": 80, "common_count": 0}, "Modify-Assignment(Tx)": {"avg_delay": 0.09649230354004885, "cost": 126.425, "target_value": 115.45605354004886, "running_time": 47.03879356384277, "local_count": 80, "common_count": 0}, "Modify-Assignment(Tx+Tp+Tq)": {"avg_delay": 0.09266674623757287, "cost": 122.075, "target_value": 110.97799623757287, "running_time": 23640.75803756714, "local_count": 53, "common_count": 27}, "Ours": {"avg_delay": 0.08901689744298245, "cost": 100.225, "target_value": 104.05064744298245, "running_time": 335.2770805358887, "local_count": 50, "common_count": 30}}, "sim2": {"simulation_id": 2, "user_seed": 58378608, "Nearest": {"avg_delay": 0.0967658494577641, "cost": 130.25, "target_value": 116.3033494577641, "running_time": 1.0013580322265625, "local_count": 80, "common_count": 0}, "Modify-Assignment(Tx)": {"avg_delay": 0.09815097079829918, "cost": 133.1, "target_value": 118.11597079829919, "running_time": 46.038150787353516, "local_count": 80, "common_count": 0}, "Modify-Assignment(Tx+Tp+Tq)": {"avg_delay": 0.09457034929666723, "cost": 129.325, "target_value": 113.96909929666722, "running_time": 19982.62643814087, "local_count": 60, "common_count": 20}, "Ours": {"avg_delay": 0.09203604114132345, "cost": 111.3, "target_value": 108.73104114132346, "running_time": 337.2783660888672, "local_count": 62, "common_count": 18}}, "sim3": {"simulation_id": 3, "user_seed": 19209648, "Nearest": {"avg_delay": 0.09654965893967088, "cost": 125.525, "target_value": 115.37840893967088, "running_time": 1.001596450805664, "local_count": 80, "common_count": 0}, "Modify-Assignment(Tx)": {"avg_delay": 0.10046674331873792, "cost": 131.7, "target_value": 120.22174331873792, "running_time": 61.0508918762207, "local_count": 80, "common_count": 0}, "Modify-Assignment(Tx+Tp+Tq)": {"avg_delay": 0.09458543174168785, "cost": 125.175, "target_value": 113.36168174168785, "running_time": 18177.64687538147, "local_count": 60, "common_count": 20}, "Ours": {"avg_delay": 0.09173272125332495, "cost": 109.4, "target_value": 108.14272125332495, "running_time": 340.28053283691406, "local_count": 68, "common_count": 12}}, "sim4": {"simulation_id": 4, "user_seed": 71877943, "Nearest": {"avg_delay": 0.09627732223275576, "cost": 129.725, "target_value": 115.73607223275575, "running_time": 1.0004043579101562, "local_count": 80, "common_count": 0}, "Modify-Assignment(Tx)": {"avg_delay": 0.09695606202210204, "cost": 136.15, "target_value": 117.37856202210203, "running_time": 46.03743553161621, "local_count": 80, "common_count": 0}, "Modify-Assignment(Tx+Tp+Tq)": {"avg_delay": 0.09226725518240621, "cost": 125.825, "target_value": 111.1410051824062, "running_time": 25641.34454727173, "local_count": 48, "common_count": 32}, "Ours": {"avg_delay": 0.08639934591955972, "cost": 111.175, "target_value": 103.07559591955972, "running_time": 371.5217113494873, "local_count": 48, "common_count": 32}}, "sim5": {"simulation_id": 5, "user_seed": 35803173, "Nearest": {"avg_delay": 0.09900993382413095, "cost": 129.775, "target_value": 118.47618382413096, "running_time": 2.0020008087158203, "local_count": 80, "common_count": 0}, "Modify-Assignment(Tx)": {"avg_delay": 0.09922986144118413, "cost": 130.725, "target_value": 118.83861144118413, "running_time": 46.037912368774414, "local_count": 80, "common_count": 0}, "Modify-Assignment(Tx+Tp+Tq)": {"avg_delay": 0.09550842485107722, "cost": 127.65, "target_value": 114.65592485107723, "running_time": 20420.228958129883, "local_count": 54, "common_count": 26}, "Ours": {"avg_delay": 0.09053992113237117, "cost": 108.75, "target_value": 106.85242113237116, "running_time": 337.2781276702881, "local_count": 50, "common_count": 30}}, "sim6": {"simulation_id": 6, "user_seed": 74808143, "Nearest": {"avg_delay": 0.09549454917550097, "cost": 125.225, "target_value": 114.27829917550098, "running_time": 2.0020008087158203, "local_count": 80, "common_count": 0}, "Modify-Assignment(Tx)": {"avg_delay": 0.09892857216541127, "cost": 134.725, "target_value": 119.13732216541126, "running_time": 35.02845764160156, "local_count": 80, "common_count": 0}, "Modify-Assignment(Tx+Tp+Tq)": {"avg_delay": 0.09211901206754256, "cost": 123.1, "target_value": 110.58401206754256, "running_time": 16861.3064289093, "local_count": 60, "common_count": 20}, "Ours": {"avg_delay": 0.08869249794631763, "cost": 109.875, "target_value": 105.17374794631763, "running_time": 336.2770080566406, "local_count": 58, "common_count": 22}}, "sim7": {"simulation_id": 7, "user_seed": 71268337, "Nearest": {"avg_delay": 0.09755465689072215, "cost": 132.925, "target_value": 117.49340689072216, "running_time": 1.0001659393310547, "local_count": 80, "common_count": 0}, "Modify-Assignment(Tx)": {"avg_delay": 0.09827343466650242, "cost": 138.025, "target_value": 118.97718466650241, "running_time": 46.03838920593262, "local_count": 80, "common_count": 0}, "Modify-Assignment(Tx+Tp+Tq)": {"avg_delay": 0.09450247981474771, "cost": 131.75, "target_value": 114.26497981474772, "running_time": 22724.03335571289, "local_count": 50, "common_count": 30}, "Ours": {"avg_delay": 0.09091638261032817, "cost": 113.35, "target_value": 107.91888261032817, "running_time": 337.2783660888672, "local_count": 66, "common_count": 14}}}, "50": {"sim0": {"simulation_id": 0, "user_seed": 41549041, "Nearest": {"avg_delay": 0.09842954217282576, "cost": 154.2, "target_value": 121.55954217282576, "running_time": 2.0012855529785156, "local_count": 100, "common_count": 0}, "Modify-Assignment(Tx)": {"avg_delay": 0.09879788591736591, "cost": 155.08, "target_value": 122.0598859173659, "running_time": 87.07261085510254, "local_count": 100, "common_count": 0}, "Modify-Assignment(Tx+Tp+Tq)": {"avg_delay": 0.09489200985589698, "cost": 153.0, "target_value": 117.84200985589698, "running_time": 41874.12071228027, "local_count": 71, "common_count": 29}, "Ours": {"avg_delay": 0.09032272668683747, "cost": 119.68, "target_value": 108.27472668683747, "running_time": 489.40396308898926, "local_count": 68, "common_count": 32}}, "sim1": {"simulation_id": 1, "user_seed": 45184614, "Nearest": {"avg_delay": 0.09802357719571445, "cost": 145.56, "target_value": 119.85757719571446, "running_time": 2.001523971557617, "local_count": 100, "common_count": 0}, "Modify-Assignment(Tx)": {"avg_delay": 0.09981983761858451, "cost": 147.86, "target_value": 121.99883761858452, "running_time": 71.63286209106445, "local_count": 100, "common_count": 0}, "Modify-Assignment(Tx+Tp+Tq)": {"avg_delay": 0.09502057623243436, "cost": 145.44, "target_value": 116.83657623243437, "running_time": 41975.02374649048, "local_count": 68, "common_count": 32}, "Ours": {"avg_delay": 0.09016051363253347, "cost": 118.16, "target_value": 107.88451363253347, "running_time": 480.3962707519531, "local_count": 74, "common_count": 26}}, "sim2": {"simulation_id": 2, "user_seed": 22728421, "Nearest": {"avg_delay": 0.09627536265104222, "cost": 141.8, "target_value": 117.54536265104223, "running_time": 1.001119613647461, "local_count": 100, "common_count": 0}, "Modify-Assignment(Tx)": {"avg_delay": 0.09813520932061083, "cost": 151.54, "target_value": 120.86620932061082, "running_time": 82.06796646118164, "local_count": 100, "common_count": 0}, "Modify-Assignment(Tx+Tp+Tq)": {"avg_delay": 0.09382834743555128, "cost": 140.62, "target_value": 114.92134743555128, "running_time": 45043.113470077515, "local_count": 61, "common_count": 39}, "Ours": {"avg_delay": 0.09027662228246534, "cost": 119.04, "target_value": 108.13262228246535, "running_time": 480.5338382720947, "local_count": 68, "common_count": 32}}, "sim3": {"simulation_id": 3, "user_seed": 21039436, "Nearest": {"avg_delay": 0.09691179648899703, "cost": 142.92, "target_value": 118.34979648899703, "running_time": 1.001119613647461, "local_count": 100, "common_count": 0}, "Modify-Assignment(Tx)": {"avg_delay": 0.0975335888963905, "cost": 147.14, "target_value": 119.6045888963905, "running_time": 77.06332206726074, "local_count": 100, "common_count": 0}, "Modify-Assignment(Tx+Tp+Tq)": {"avg_delay": 0.09397657147819222, "cost": 141.44, "target_value": 115.1925714781922, "running_time": 42593.61720085144, "local_count": 63, "common_count": 37}, "Ours": {"avg_delay": 0.09123897803553768, "cost": 119.72, "target_value": 109.19697803553768, "running_time": 487.6279830932617, "local_count": 76, "common_count": 24}}, "sim4": {"simulation_id": 4, "user_seed": 96731524, "Nearest": {"avg_delay": 0.10004805921395554, "cost": 152.62, "target_value": 122.94105921395554, "running_time": 2.001523971557617, "local_count": 100, "common_count": 0}, "Modify-Assignment(Tx)": {"avg_delay": 0.10171160501713529, "cost": 153.84, "target_value": 124.78760501713529, "running_time": 61.0504150390625, "local_count": 100, "common_count": 0}, "Modify-Assignment(Tx+Tp+Tq)": {"avg_delay": 0.09746758802079097, "cost": 151.52, "target_value": 120.19558802079098, "running_time": 35336.65895462036, "local_count": 72, "common_count": 28}, "Ours": {"avg_delay": 0.09426411832747039, "cost": 124.5, "target_value": 112.93911832747038, "running_time": 492.40612983703613, "local_count": 72, "common_count": 28}}, "sim5": {"simulation_id": 5, "user_seed": 17626439, "Nearest": {"avg_delay": 0.09860255176350327, "cost": 154.88, "target_value": 121.83455176350327, "running_time": 2.0017623901367188, "local_count": 100, "common_count": 0}, "Modify-Assignment(Tx)": {"avg_delay": 0.09890082855076672, "cost": 156.24, "target_value": 122.33682855076671, "running_time": 63.05193901062012, "local_count": 100, "common_count": 0}, "Modify-Assignment(Tx+Tp+Tq)": {"avg_delay": 0.09576377480798563, "cost": 152.84, "target_value": 118.68977480798563, "running_time": 37569.33403015137, "local_count": 73, "common_count": 27}, "Ours": {"avg_delay": 0.0909013188915624, "cost": 128.98, "target_value": 110.24831889156239, "running_time": 492.40612983703613, "local_count": 70, "common_count": 30}}, "sim6": {"simulation_id": 6, "user_seed": 98360153, "Nearest": {"avg_delay": 0.10140990291267891, "cost": 151.18, "target_value": 124.08690291267891, "running_time": 2.001523971557617, "local_count": 100, "common_count": 0}, "Modify-Assignment(Tx)": {"avg_delay": 0.10499335399504077, "cost": 166.66, "target_value": 129.99235399504076, "running_time": 68.64547729492188, "local_count": 100, "common_count": 0}, "Modify-Assignment(Tx+Tp+Tq)": {"avg_delay": 0.0976661875061332, "cost": 149.4, "target_value": 120.07618750613321, "running_time": 40809.43274497986, "local_count": 70, "common_count": 30}, "Ours": {"avg_delay": 0.0943283863219855, "cost": 122.48, "target_value": 112.70038632198549, "running_time": 493.4074878692627, "local_count": 66, "common_count": 34}}, "sim7": {"simulation_id": 7, "user_seed": 41828312, "Nearest": {"avg_delay": 0.0997125342186683, "cost": 148.74, "target_value": 122.02353421866829, "running_time": 2.001523971557617, "local_count": 100, "common_count": 0}, "Modify-Assignment(Tx)": {"avg_delay": 0.10093294214093365, "cost": 152.02, "target_value": 123.73594214093364, "running_time": 68.0551528930664, "local_count": 100, "common_count": 0}, "Modify-Assignment(Tx+Tp+Tq)": {"avg_delay": 0.09589077154317034, "cost": 145.72, "target_value": 117.74877154317035, "running_time": 44026.43156051636, "local_count": 65, "common_count": 35}, "Ours": {"avg_delay": 0.09327968485132333, "cost": 122.86, "target_value": 111.70868485132334, "running_time": 492.53392219543457, "local_count": 64, "common_count": 36}}}, "60": {"sim0": {"simulation_id": 0, "user_seed": 49443079, "Nearest": {"avg_delay": 0.1012856006325081, "cost": 174.48333333333332, "target_value": 127.4581006325081, "running_time": 2.0017623901367188, "local_count": 120, "common_count": 0}, "Modify-Assignment(Tx)": {"avg_delay": 0.10196946273101706, "cost": 177.66666666666666, "target_value": 128.61946273101705, "running_time": 129.1065216064453, "local_count": 120, "common_count": 0}, "Modify-Assignment(Tx+Tp+Tq)": {"avg_delay": 0.09863263755547388, "cost": 172.31666666666666, "target_value": 124.48013755547387, "running_time": 66793.78461837769, "local_count": 85, "common_count": 35}, "Ours": {"avg_delay": 0.09481069692490064, "cost": 143.38333333333333, "target_value": 116.31819692490063, "running_time": 670.6905364990234, "local_count": 89, "common_count": 31}}, "sim1": {"simulation_id": 1, "user_seed": 26347321, "Nearest": {"avg_delay": 0.09992523734942013, "cost": 169.06666666666666, "target_value": 125.28523734942013, "running_time": 2.0017623901367188, "local_count": 120, "common_count": 0}, "Modify-Assignment(Tx)": {"avg_delay": 0.1008752357082228, "cost": 175.33333333333334, "target_value": 127.17523570822279, "running_time": 85.20388603210449, "local_count": 120, "common_count": 0}, "Modify-Assignment(Tx+Tp+Tq)": {"avg_delay": 0.09700031981573595, "cost": 167.73333333333332, "target_value": 122.16031981573595, "running_time": 65252.070903778076, "local_count": 82, "common_count": 38}, "Ours": {"avg_delay": 0.09316570169664141, "cost": 139.51666666666668, "target_value": 114.09320169664142, "running_time": 665.1709079742432, "local_count": 88, "common_count": 32}}, "sim2": {"simulation_id": 2, "user_seed": 9557681, "Nearest": {"avg_delay": 0.09884462571112228, "cost": 157.35, "target_value": 122.44712571112228, "running_time": 2.0017623901367188, "local_count": 120, "common_count": 0}, "Modify-Assignment(Tx)": {"avg_delay": 0.10039373135212387, "cost": 167.8, "target_value": 125.56373135212387, "running_time": 108.08920860290527, "local_count": 120, "common_count": 0}, "Modify-Assignment(Tx+Tp+Tq)": {"avg_delay": 0.09557605863668218, "cost": 154.83333333333334, "target_value": 118.8010586366822, "running_time": 78976.76277160645, "local_count": 74, "common_count": 46}, "Ours": {"avg_delay": 0.09111028853579839, "cost": 131.68333333333334, "target_value": 110.86278853579839, "running_time": 693.7158107757568, "local_count": 84, "common_count": 36}}, "sim3": {"simulation_id": 3, "user_seed": 45718448, "Nearest": {"avg_delay": 0.09484100984483276, "cost": 162.26666666666668, "target_value": 119.18100984483277, "running_time": 3.003358840942383, "local_count": 120, "common_count": 0}, "Modify-Assignment(Tx)": {"avg_delay": 0.09580286559027933, "cost": 165.13333333333333, "target_value": 120.57286559027932, "running_time": 100.0826358795166, "local_count": 120, "common_count": 0}, "Modify-Assignment(Tx+Tp+Tq)": {"avg_delay": 0.09191155349795545, "cost": 160.85, "target_value": 116.03905349795545, "running_time": 74806.99849128723, "local_count": 77, "common_count": 43}, "Ours": {"avg_delay": 0.08757290414500328, "cost": 133.05, "target_value": 107.53040414500327, "running_time": 648.2217311859131, "local_count": 82, "common_count": 38}}, "sim4": {"simulation_id": 4, "user_seed": 18460218, "Nearest": {"avg_delay": 0.09663369226365594, "cost": 163.96666666666667, "target_value": 121.22869226365593, "running_time": 3.002166748046875, "local_count": 120, "common_count": 0}, "Modify-Assignment(Tx)": {"avg_delay": 0.0964819128559619, "cost": 161.55, "target_value": 120.7144128559619, "running_time": 116.67609214782715, "local_count": 120, "common_count": 0}, "Modify-Assignment(Tx+Tp+Tq)": {"avg_delay": 0.09290297275355978, "cost": 161.08333333333334, "target_value": 117.06547275355979, "running_time": 77806.25033378601, "local_count": 77, "common_count": 43}, "Ours": {"avg_delay": 0.08732609612844641, "cost": 133.91666666666666, "target_value": 107.41359612844641, "running_time": 663.5470390319824, "local_count": 74, "common_count": 46}}, "sim5": {"simulation_id": 5, "user_seed": 53732196, "Nearest": {"avg_delay": 0.10075085773851097, "cost": 161.38333333333333, "target_value": 124.95835773851097, "running_time": 3.0024051666259766, "local_count": 120, "common_count": 0}, "Modify-Assignment(Tx)": {"avg_delay": 0.1040660954473954, "cost": 175.3, "target_value": 130.3610954473954, "running_time": 107.08880424499512, "local_count": 120, "common_count": 0}, "Modify-Assignment(Tx+Tp+Tq)": {"avg_delay": 0.09788871035739766, "cost": 159.71666666666667, "target_value": 121.84621035739765, "running_time": 59748.32034111023, "local_count": 92, "common_count": 28}, "Ours": {"avg_delay": 0.09585101756483198, "cost": 131.23333333333332, "target_value": 115.53601756483198, "running_time": 665.6692028045654, "local_count": 97, "common_count": 23}}, "sim6": {"simulation_id": 6, "user_seed": 33517418, "Nearest": {"avg_delay": 0.09731389540306215, "cost": 155.93333333333334, "target_value": 120.70389540306215, "running_time": 3.002643585205078, "local_count": 120, "common_count": 0}, "Modify-Assignment(Tx)": {"avg_delay": 0.09933317600256995, "cost": 164.3, "target_value": 123.97817600256995, "running_time": 95.0784683227539, "local_count": 120, "common_count": 0}, "Modify-Assignment(Tx+Tp+Tq)": {"avg_delay": 0.09425168172722125, "cost": 154.05, "target_value": 117.35918172722124, "running_time": 68823.92144203186, "local_count": 82, "common_count": 38}, "Ours": {"avg_delay": 0.09078678527792047, "cost": 132.76666666666668, "target_value": 110.70178527792048, "running_time": 700.5114555358887, "local_count": 90, "common_count": 30}}, "sim7": {"simulation_id": 7, "user_seed": 28547201, "Nearest": {"avg_delay": 0.09806539395389204, "cost": 170.6, "target_value": 123.65539395389204, "running_time": 2.002239227294922, "local_count": 120, "common_count": 0}, "Modify-Assignment(Tx)": {"avg_delay": 0.10000082288850763, "cost": 177.76666666666668, "target_value": 126.66582288850763, "running_time": 89.07270431518555, "local_count": 120, "common_count": 0}, "Modify-Assignment(Tx+Tp+Tq)": {"avg_delay": 0.09580456185780098, "cost": 170.16666666666666, "target_value": 121.32956185780097, "running_time": 64830.95479011536, "local_count": 91, "common_count": 29}, "Ours": {"avg_delay": 0.09362516882510342, "cost": 141.15, "target_value": 114.79766882510343, "running_time": 665.6477451324463, "local_count": 100, "common_count": 20}}}, "70": {"sim0": {"simulation_id": 0, "user_seed": 49552259, "Nearest": {"avg_delay": 0.09626778556017801, "cost": 191.52857142857144, "target_value": 124.99707127446374, "running_time": 3.0024051666259766, "local_count": 140, "common_count": 0}, "Modify-Assignment(Tx)": {"avg_delay": 0.09818872634014678, "cost": 202.32857142857142, "target_value": 128.5380120544325, "running_time": 148.12588691711426, "local_count": 140, "common_count": 0}, "Modify-Assignment(Tx+Tp+Tq)": {"avg_delay": 0.0938240649441239, "cost": 190.21428571428572, "target_value": 122.35620780126676, "running_time": 99332.03530311584, "local_count": 103, "common_count": 37}, "Ours": {"avg_delay": 0.09076102728713246, "cost": 155.9142857142857, "target_value": 114.14817014427533, "running_time": 872.8697299957275, "local_count": 98, "common_count": 42}}, "sim1": {"simulation_id": 1, "user_seed": 67926304, "Nearest": {"avg_delay": 0.09611370768567833, "cost": 183.5142857142857, "target_value": 123.64085054282117, "running_time": 3.0031204223632812, "local_count": 140, "common_count": 0}, "Modify-Assignment(Tx)": {"avg_delay": 0.097004346372824, "cost": 189.0142857142857, "target_value": 125.35648922996685, "running_time": 122.100830078125, "local_count": 140, "common_count": 0}, "Modify-Assignment(Tx+Tp+Tq)": {"avg_delay": 0.0926820875045073, "cost": 180.95714285714286, "target_value": 119.82565893307873, "running_time": 113401.00407600403, "local_count": 93, "common_count": 47}, "Ours": {"avg_delay": 0.08917693632482815, "cost": 148.67142857142858, "target_value": 111.47765061054244, "running_time": 905.6615829467773, "local_count": 78, "common_count": 62}}, "sim2": {"simulation_id": 2, "user_seed": 14421772, "Nearest": {"avg_delay": 0.09794399742358101, "cost": 179.04285714285714, "target_value": 124.80042599500958, "running_time": 3.0031204223632812, "local_count": 140, "common_count": 0}, "Modify-Assignment(Tx)": {"avg_delay": 0.1002580241917327, "cost": 191.04285714285714, "target_value": 128.91445276316128, "running_time": 101.08351707458496, "local_count": 140, "common_count": 0}, "Modify-Assignment(Tx+Tp+Tq)": {"avg_delay": 0.09465593764992757, "cost": 178.4, "target_value": 121.41593764992757, "running_time": 108108.52098464966, "local_count": 102, "common_count": 38}, "Ours": {"avg_delay": 0.09123231030294118, "cost": 149.4857142857143, "target_value": 113.65516744579833, "running_time": 863.3179664611816, "local_count": 98, "common_count": 42}}, "sim3": {"simulation_id": 3, "user_seed": 96994054, "Nearest": {"avg_delay": 0.09488192196090743, "cost": 179.84285714285716, "target_value": 121.858350532336, "running_time": 3.0019283294677734, "local_count": 140, "common_count": 0}, "Modify-Assignment(Tx)": {"avg_delay": 0.09622391526661071, "cost": 186.34285714285716, "target_value": 124.17534383803928, "running_time": 100.0826358795166, "local_count": 140, "common_count": 0}, "Modify-Assignment(Tx+Tp+Tq)": {"avg_delay": 0.09212990971041539, "cost": 178.0857142857143, "target_value": 118.84276685327254, "running_time": 111460.63423156738, "local_count": 93, "common_count": 47}, "Ours": {"avg_delay": 0.08966298121698711, "cost": 149.52857142857144, "target_value": 112.09226693127282, "running_time": 861.8671894073486, "local_count": 99, "common_count": 41}}, "sim4": {"simulation_id": 4, "user_seed": 51070391, "Nearest": {"avg_delay": 0.09588201011433546, "cost": 171.5857142857143, "target_value": 121.6198672571926, "running_time": 3.0024051666259766, "local_count": 140, "common_count": 0}, "Modify-Assignment(Tx)": {"avg_delay": 0.09610265615272984, "cost": 176.12857142857143, "target_value": 122.52194186701556, "running_time": 101.08280181884766, "local_count": 140, "common_count": 0}, "Modify-Assignment(Tx+Tp+Tq)": {"avg_delay": 0.0928327390874481, "cost": 170.3, "target_value": 118.3777390874481, "running_time": 124513.22865486145, "local_count": 86, "common_count": 54}, "Ours": {"avg_delay": 0.09063232773955957, "cost": 145.84285714285716, "target_value": 112.50875631098815, "running_time": 887.653112411499, "local_count": 104, "common_count": 36}}, "sim5": {"simulation_id": 5, "user_seed": 52277260, "Nearest": {"avg_delay": 0.10174439449762472, "cost": 194.2, "target_value": 130.87439449762473, "running_time": 3.0031204223632812, "local_count": 140, "common_count": 0}, "Modify-Assignment(Tx)": {"avg_delay": 0.10286722768962359, "cost": 202.55714285714285, "target_value": 133.250799118195, "running_time": 103.80363464355469, "local_count": 140, "common_count": 0}, "Modify-Assignment(Tx+Tp+Tq)": {"avg_delay": 0.09785890243025701, "cost": 191.5142857142857, "target_value": 126.58604528739986, "running_time": 115902.66036987305, "local_count": 92, "common_count": 48}, "Ours": {"avg_delay": 0.09188507732065214, "cost": 148.9142857142857, "target_value": 114.222220177795, "running_time": 866.7221069335938, "local_count": 72, "common_count": 68}}, "sim6": {"simulation_id": 6, "user_seed": 87875479, "Nearest": {"avg_delay": 0.09635362002980404, "cost": 182.75714285714287, "target_value": 123.76719145837546, "running_time": 3.002643585205078, "local_count": 140, "common_count": 0}, "Modify-Assignment(Tx)": {"avg_delay": 0.09907203124303376, "cost": 194.81428571428572, "target_value": 128.29417410017663, "running_time": 168.13921928405762, "local_count": 140, "common_count": 0}, "Modify-Assignment(Tx+Tp+Tq)": {"avg_delay": 0.09306602900890398, "cost": 180.05714285714285, "target_value": 120.07460043747541, "running_time": 108699.30410385132, "local_count": 94, "common_count": 46}, "Ours": {"avg_delay": 0.08918050099492414, "cost": 150.62857142857143, "target_value": 111.77478670920986, "running_time": 871.7184066772461, "local_count": 72, "common_count": 68}}, "sim7": {"simulation_id": 7, "user_seed": 75023311, "Nearest": {"avg_delay": 0.09825262557448763, "cost": 181.45714285714286, "target_value": 125.47119700305906, "running_time": 3.0019283294677734, "local_count": 140, "common_count": 0}, "Modify-Assignment(Tx)": {"avg_delay": 0.09855588645152515, "cost": 184.28571428571428, "target_value": 126.19874359438228, "running_time": 124.10187721252441, "local_count": 140, "common_count": 0}, "Modify-Assignment(Tx+Tp+Tq)": {"avg_delay": 0.09515653901590895, "cost": 179.38571428571427, "target_value": 122.06439615876609, "running_time": 95713.80972862244, "local_count": 107, "common_count": 33}, "Ours": {"avg_delay": 0.09122035117013677, "cost": 152.71428571428572, "target_value": 114.12749402727962, "running_time": 925.5330562591553, "local_count": 92, "common_count": 48}}}, "80": {"sim0": {"simulation_id": 0, "user_seed": 95487272, "Nearest": {"avg_delay": 0.09836279946560288, "cost": 190.6375, "target_value": 126.95842446560287, "running_time": 3.002643585205078, "local_count": 160, "common_count": 0}, "Modify-Assignment(Tx)": {"avg_delay": 0.09955323847441415, "cost": 198.1125, "target_value": 129.27011347441413, "running_time": 93.87755393981934, "local_count": 160, "common_count": 0}, "Modify-Assignment(Tx+Tp+Tq)": {"avg_delay": 0.09525846036452121, "cost": 189.1875, "target_value": 123.63658536452121, "running_time": 136080.8289051056, "local_count": 115, "common_count": 45}, "Ours": {"avg_delay": 0.09204288700424261, "cost": 159.25, "target_value": 115.93038700424262, "running_time": 1118.377923965454, "local_count": 114, "common_count": 46}}, "sim1": {"simulation_id": 1, "user_seed": 6057504, "Nearest": {"avg_delay": 0.09696583055089487, "cost": 201.4375, "target_value": 127.18145555089488, "running_time": 3.0024051666259766, "local_count": 160, "common_count": 0}, "Modify-Assignment(Tx)": {"avg_delay": 0.09806011860668541, "cost": 208.1, "target_value": 129.2751186066854, "running_time": 174.36456680297852, "local_count": 160, "common_count": 0}, "Modify-Assignment(Tx+Tp+Tq)": {"avg_delay": 0.09447983440376743, "cost": 199.9875, "target_value": 124.47795940376744, "running_time": 160500.146150589, "local_count": 108, "common_count": 52}, "Ours": {"avg_delay": 0.09047786284814345, "cost": 164.575, "target_value": 115.16411284814345, "running_time": 1101.036548614502, "local_count": 108, "common_count": 52}}, "sim2": {"simulation_id": 2, "user_seed": 63913045, "Nearest": {"avg_delay": 0.09755143084558433, "cost": 193.925, "target_value": 126.64018084558434, "running_time": 4.003286361694336, "local_count": 160, "common_count": 0}, "Modify-Assignment(Tx)": {"avg_delay": 0.09885797714841255, "cost": 200.7625, "target_value": 128.97235214841254, "running_time": 144.43540573120117, "local_count": 160, "common_count": 0}, "Modify-Assignment(Tx+Tp+Tq)": {"avg_delay": 0.09404998396411353, "cost": 191.3375, "target_value": 122.75060896411352, "running_time": 170379.95886802673, "local_count": 106, "common_count": 54}, "Ours": {"avg_delay": 0.09050499582528118, "cost": 151.4875, "target_value": 113.22812082528118, "running_time": 1097.0091819763184, "local_count": 86, "common_count": 74}}, "sim3": {"simulation_id": 3, "user_seed": 60222111, "Nearest": {"avg_delay": 0.1007739839397223, "cost": 195.9375, "target_value": 130.1646089397223, "running_time": 4.004001617431641, "local_count": 160, "common_count": 0}, "Modify-Assignment(Tx)": {"avg_delay": 0.10170889310569885, "cost": 199.8, "target_value": 131.67889310569885, "running_time": 151.03530883789062, "local_count": 160, "common_count": 0}, "Modify-Assignment(Tx+Tp+Tq)": {"avg_delay": 0.09698416127966729, "cost": 193.2375, "target_value": 125.96978627966729, "running_time": 180159.2311859131, "local_count": 104, "common_count": 56}, "Ours": {"avg_delay": 0.0922798502066629, "cost": 156.55, "target_value": 115.7623502066629, "running_time": 1118.346929550171, "local_count": 92, "common_count": 68}}, "sim4": {"simulation_id": 4, "user_seed": 29373540, "Nearest": {"avg_delay": 0.1001111470332726, "cost": 199.6375, "target_value": 130.0567720332726, "running_time": 4.003047943115234, "local_count": 160, "common_count": 0}, "Modify-Assignment(Tx)": {"avg_delay": 0.10076991027474883, "cost": 203.1625, "target_value": 131.24428527474882, "running_time": 169.13914680480957, "local_count": 160, "common_count": 0}, "Modify-Assignment(Tx+Tp+Tq)": {"avg_delay": 0.09687933412881639, "cost": 197.2, "target_value": 126.45933412881638, "running_time": 172690.25588035583, "local_count": 109, "common_count": 51}, "Ours": {"avg_delay": 0.09411523181941966, "cost": 159.1125, "target_value": 117.98210681941967, "running_time": 1174.6742725372314, "local_count": 94, "common_count": 66}}, "sim5": {"simulation_id": 5, "user_seed": 63822423, "Nearest": {"avg_delay": 0.09926867755462002, "cost": 191.45, "target_value": 127.98617755462001, "running_time": 4.002809524536133, "local_count": 160, "common_count": 0}, "Modify-Assignment(Tx)": {"avg_delay": 0.10195220117275142, "cost": 204.975, "target_value": 132.69845117275142, "running_time": 161.5006923675537, "local_count": 160, "common_count": 0}, "Modify-Assignment(Tx+Tp+Tq)": {"avg_delay": 0.09636265760623668, "cost": 190.3125, "target_value": 124.90953260623668, "running_time": 155676.54633522034, "local_count": 116, "common_count": 44}, "Ours": {"avg_delay": 0.09311442074137614, "cost": 159.4, "target_value": 117.02442074137615, "running_time": 1102.3223400115967, "local_count": 116, "common_count": 44}}, "sim6": {"simulation_id": 6, "user_seed": 80989929, "Nearest": {"avg_delay": 0.10163422788522247, "cost": 190.6125, "target_value": 130.22610288522247, "running_time": 3.0024051666259766, "local_count": 160, "common_count": 0}, "Modify-Assignment(Tx)": {"avg_delay": 0.10410798363725154, "cost": 201.175, "target_value": 134.28423363725156, "running_time": 194.16046142578125, "local_count": 160, "common_count": 0}, "Modify-Assignment(Tx+Tp+Tq)": {"avg_delay": 0.09814225991069815, "cost": 188.1625, "target_value": 126.36663491069815, "running_time": 166434.956073761, "local_count": 105, "common_count": 55}, "Ours": {"avg_delay": 0.09346585713401748, "cost": 150.125, "target_value": 115.98460713401748, "running_time": 1129.1425228118896, "local_count": 86, "common_count": 74}}, "sim7": {"simulation_id": 7, "user_seed": 20077837, "Nearest": {"avg_delay": 0.10063852233116855, "cost": 197.7, "target_value": 130.29352233116853, "running_time": 4.003286361694336, "local_count": 160, "common_count": 0}, "Modify-Assignment(Tx)": {"avg_delay": 0.10253716726303491, "cost": 206.85, "target_value": 133.56466726303492, "running_time": 139.1150951385498, "local_count": 160, "common_count": 0}, "Modify-Assignment(Tx+Tp+Tq)": {"avg_delay": 0.0975010356402655, "cost": 196.225, "target_value": 126.93478564026549, "running_time": 167499.31073188782, "local_count": 113, "common_count": 47}, "Ours": {"avg_delay": 0.09282228869719464, "cost": 153.075, "target_value": 115.78353869719463, "running_time": 1098.5033512115479, "local_count": 102, "common_count": 58}}}, "90": {"sim0": {"simulation_id": 0, "user_seed": 73272656, "Nearest": {"avg_delay": 0.09973294201830768, "cost": 213.36666666666667, "target_value": 131.73794201830768, "running_time": 4.003763198852539, "local_count": 180, "common_count": 0}, "Modify-Assignment(Tx)": {"avg_delay": 0.10111621342669824, "cost": 219.92222222222222, "target_value": 134.10454676003155, "running_time": 235.19420623779297, "local_count": 180, "common_count": 0}, "Modify-Assignment(Tx+Tp+Tq)": {"avg_delay": 0.09639872507162865, "cost": 211.11111111111111, "target_value": 128.06539173829532, "running_time": 214648.99396896362, "local_count": 126, "common_count": 54}, "Ours": {"avg_delay": 0.09255574504734768, "cost": 167.77777777777777, "target_value": 117.72241171401433, "running_time": 1384.110927581787, "local_count": 106, "common_count": 74}}, "sim1": {"simulation_id": 1, "user_seed": 575943, "Nearest": {"avg_delay": 0.10010045519395572, "cost": 218.33333333333334, "target_value": 132.85045519395572, "running_time": 4.003763198852539, "local_count": 180, "common_count": 0}, "Modify-Assignment(Tx)": {"avg_delay": 0.10259227438755383, "cost": 233.82222222222222, "target_value": 137.66560772088715, "running_time": 251.34682655334473, "local_count": 180, "common_count": 0}, "Modify-Assignment(Tx+Tp+Tq)": {"avg_delay": 0.09740252009332807, "cost": 217.67777777777778, "target_value": 130.05418675999474, "running_time": 196964.09010887146, "local_count": 133, "common_count": 47}, "Ours": {"avg_delay": 0.09370683936067024, "cost": 169.2888888888889, "target_value": 119.10017269400358, "running_time": 1423.246145248413, "local_count": 126, "common_count": 54}}, "sim2": {"simulation_id": 2, "user_seed": 36274637, "Nearest": {"avg_delay": 0.09905073249380729, "cost": 211.7888888888889, "target_value": 130.8190658271406, "running_time": 4.003286361694336, "local_count": 180, "common_count": 0}, "Modify-Assignment(Tx)": {"avg_delay": 0.10096122444654047, "cost": 225.25555555555556, "target_value": 134.7495577798738, "running_time": 183.1510066986084, "local_count": 180, "common_count": 0}, "Modify-Assignment(Tx+Tp+Tq)": {"avg_delay": 0.09608912983304292, "cost": 210.11111111111111, "target_value": 127.60579649970958, "running_time": 209935.06002426147, "local_count": 129, "common_count": 51}, "Ours": {"avg_delay": 0.09329551080999829, "cost": 171.25555555555556, "target_value": 118.98384414333162, "running_time": 1371.9305992126465, "local_count": 124, "common_count": 56}}, "sim3": {"simulation_id": 3, "user_seed": 78211428, "Nearest": {"avg_delay": 0.09974167204659584, "cost": 225.06666666666666, "target_value": 133.50167204659584, "running_time": 4.004001617431641, "local_count": 180, "common_count": 0}, "Modify-Assignment(Tx)": {"avg_delay": 0.10027817462578867, "cost": 228.8111111111111, "target_value": 134.59984129245532, "running_time": 241.24670028686523, "local_count": 180, "common_count": 0}, "Modify-Assignment(Tx+Tp+Tq)": {"avg_delay": 0.09624917198529916, "cost": 223.23333333333332, "target_value": 129.73417198529916, "running_time": 252706.88724517822, "local_count": 121, "common_count": 59}, "Ours": {"avg_delay": 0.0926573051399008, "cost": 172.2111111111111, "target_value": 118.48897180656746, "running_time": 1402.4221897125244, "local_count": 109, "common_count": 71}}, "sim4": {"simulation_id": 4, "user_seed": 72693953, "Nearest": {"avg_delay": 0.09886370698943597, "cost": 230.64444444444445, "target_value": 133.46037365610263, "running_time": 4.0035247802734375, "local_count": 180, "common_count": 0}, "Modify-Assignment(Tx)": {"avg_delay": 0.10033793299835214, "cost": 229.66666666666666, "target_value": 134.78793299835215, "running_time": 233.1993579864502, "local_count": 180, "common_count": 0}, "Modify-Assignment(Tx+Tp+Tq)": {"avg_delay": 0.09600986369565549, "cost": 228.54444444444445, "target_value": 130.29153036232216, "running_time": 201318.64643096924, "local_count": 129, "common_count": 51}, "Ours": {"avg_delay": 0.09312547699657403, "cost": 175.25555555555556, "target_value": 119.41381032990736, "running_time": 1385.1475715637207, "local_count": 114, "common_count": 66}}, "sim5": {"simulation_id": 5, "user_seed": 48872569, "Nearest": {"avg_delay": 0.09891196012189656, "cost": 212.46666666666667, "target_value": 130.78196012189656, "running_time": 4.003047943115234, "local_count": 180, "common_count": 0}, "Modify-Assignment(Tx)": {"avg_delay": 0.10099631192774709, "cost": 224.61111111111111, "target_value": 134.68797859441375, "running_time": 168.19047927856445, "local_count": 180, "common_count": 0}, "Modify-Assignment(Tx+Tp+Tq)": {"avg_delay": 0.09562644632747219, "cost": 210.53333333333333, "target_value": 127.2064463274722, "running_time": 248023.5447883606, "local_count": 124, "common_count": 56}, "Ours": {"avg_delay": 0.09226401549274534, "cost": 169.46666666666667, "target_value": 117.68401549274533, "running_time": 1382.8182220458984, "local_count": 110, "common_count": 70}}, "sim6": {"simulation_id": 6, "user_seed": 79266839, "Nearest": {"avg_delay": 0.09994723708987954, "cost": 219.55555555555554, "target_value": 132.88057042321287, "running_time": 4.003047943115234, "local_count": 180, "common_count": 0}, "Modify-Assignment(Tx)": {"avg_delay": 0.1024291134078423, "cost": 229.03333333333333, "target_value": 136.7841134078423, "running_time": 208.17136764526367, "local_count": 180, "common_count": 0}, "Modify-Assignment(Tx+Tp+Tq)": {"avg_delay": 0.0971007185416538, "cost": 218.1888888888889, "target_value": 129.82905187498713, "running_time": 242721.34637832642, "local_count": 118, "common_count": 62}, "Ours": {"avg_delay": 0.09333201287038775, "cost": 168.83333333333334, "target_value": 118.65701287038776, "running_time": 1377.4209022521973, "local_count": 114, "common_count": 66}}, "sim7": {"simulation_id": 7, "user_seed": 21630697, "Nearest": {"avg_delay": 0.10183027787464818, "cost": 224.48888888888888, "target_value": 135.50361120798152, "running_time": 4.004001617431641, "local_count": 180, "common_count": 0}, "Modify-Assignment(Tx)": {"avg_delay": 0.10207348153025728, "cost": 227.75555555555556, "target_value": 136.2368148635906, "running_time": 186.23018264770508, "local_count": 180, "common_count": 0}, "Modify-Assignment(Tx+Tp+Tq)": {"avg_delay": 0.09834924855371294, "cost": 222.63333333333333, "target_value": 131.74424855371294, "running_time": 240696.25973701477, "local_count": 129, "common_count": 51}, "Ours": {"avg_delay": 0.09417966164783798, "cost": 168.98888888888888, "target_value": 119.5279949811713, "running_time": 1385.751485824585, "local_count": 114, "common_count": 66}}}, "100": {"sim0": {"simulation_id": 0, "user_seed": 2453458, "Nearest": {"avg_delay": 0.0984405631147891, "cost": 219.86, "target_value": 131.4195631147891, "running_time": 4.003286361694336, "local_count": 200, "common_count": 0}, "Modify-Assignment(Tx)": {"avg_delay": 0.10132512771841513, "cost": 237.97, "target_value": 137.02062771841514, "running_time": 293.2419776916504, "local_count": 200, "common_count": 0}, "Modify-Assignment(Tx+Tp+Tq)": {"avg_delay": 0.09580092345232313, "cost": 219.44, "target_value": 128.71692345232313, "running_time": 275564.0218257904, "local_count": 148, "common_count": 52}, "Ours": {"avg_delay": 0.09326673560783566, "cost": 182.44, "target_value": 120.63273560783566, "running_time": 1695.573091506958, "local_count": 146, "common_count": 54}}, "sim1": {"simulation_id": 1, "user_seed": 88796769, "Nearest": {"avg_delay": 0.09825850319251413, "cost": 239.46, "target_value": 134.1775031925141, "running_time": 4.004001617431641, "local_count": 200, "common_count": 0}, "Modify-Assignment(Tx)": {"avg_delay": 0.09944654875704996, "cost": 245.52, "target_value": 136.27454875704996, "running_time": 295.87292671203613, "local_count": 200, "common_count": 0}, "Modify-Assignment(Tx+Tp+Tq)": {"avg_delay": 0.09517896580547787, "cost": 237.94, "target_value": 130.86996580547788, "running_time": 322582.4251174927, "local_count": 144, "common_count": 56}, "Ours": {"avg_delay": 0.09261258853788154, "cost": 190.96, "target_value": 121.25658853788154, "running_time": 1660.7089042663574, "local_count": 132, "common_count": 68}}, "sim2": {"simulation_id": 2, "user_seed": 66980314, "Nearest": {"avg_delay": 0.09885410407971972, "cost": 236.3, "target_value": 134.2991040797197, "running_time": 4.007816314697266, "local_count": 200, "common_count": 0}, "Modify-Assignment(Tx)": {"avg_delay": 0.10051371946382552, "cost": 248.19, "target_value": 137.7422194638255, "running_time": 264.32156562805176, "local_count": 200, "common_count": 0}, "Modify-Assignment(Tx+Tp+Tq)": {"avg_delay": 0.09573618781991729, "cost": 234.35, "target_value": 130.8886878199173, "running_time": 345239.7725582123, "local_count": 129, "common_count": 71}, "Ours": {"avg_delay": 0.09205541591403198, "cost": 188.35, "target_value": 120.30791591403198, "running_time": 1699.406623840332, "local_count": 118, "common_count": 82}}, "sim3": {"simulation_id": 3, "user_seed": 82031234, "Nearest": {"avg_delay": 0.10075942180260909, "cost": 239.38, "target_value": 136.66642180260908, "running_time": 5.004405975341797, "local_count": 200, "common_count": 0}, "Modify-Assignment(Tx)": {"avg_delay": 0.1028563467686301, "cost": 249.87, "target_value": 140.3368467686301, "running_time": 246.20366096496582, "local_count": 200, "common_count": 0}, "Modify-Assignment(Tx+Tp+Tq)": {"avg_delay": 0.097593985243468, "cost": 237.79, "target_value": 133.262485243468, "running_time": 322715.2051925659, "local_count": 141, "common_count": 59}, "Ours": {"avg_delay": 0.09391750174565043, "cost": 185.32, "target_value": 121.71550174565043, "running_time": 1650.1152515411377, "local_count": 124, "common_count": 76}}, "sim4": {"simulation_id": 4, "user_seed": 27927232, "Nearest": {"avg_delay": 0.10025667270708359, "cost": 242.81, "target_value": 136.6781727070836, "running_time": 5.004405975341797, "local_count": 200, "common_count": 0}, "Modify-Assignment(Tx)": {"avg_delay": 0.10238443266922041, "cost": 253.68, "target_value": 140.4364326692204, "running_time": 282.23252296447754, "local_count": 200, "common_count": 0}, "Modify-Assignment(Tx+Tp+Tq)": {"avg_delay": 0.0971967717689402, "cost": 241.0, "target_value": 133.34677176894021, "running_time": 351919.83795166016, "local_count": 136, "common_count": 64}, "Ours": {"avg_delay": 0.09383042118083466, "cost": 190.15, "target_value": 122.35292118083467, "running_time": 1691.7855739593506, "local_count": 130, "common_count": 70}}, "sim5": {"simulation_id": 5, "user_seed": 34932982, "Nearest": {"avg_delay": 0.09736200366109429, "cost": 237.97, "target_value": 133.0575036610943, "running_time": 4.055500030517578, "local_count": 200, "common_count": 0}, "Modify-Assignment(Tx)": {"avg_delay": 0.09894583014546367, "cost": 250.16, "target_value": 136.46983014546367, "running_time": 206.24852180480957, "local_count": 200, "common_count": 0}, "Modify-Assignment(Tx+Tp+Tq)": {"avg_delay": 0.0944119749038294, "cost": 236.3, "target_value": 129.85697490382938, "running_time": 311402.66013145447, "local_count": 141, "common_count": 59}, "Ours": {"avg_delay": 0.09183928792221437, "cost": 190.16, "target_value": 120.36328792221437, "running_time": 1686.0592365264893, "local_count": 136, "common_count": 64}}, "sim6": {"simulation_id": 6, "user_seed": 9546494, "Nearest": {"avg_delay": 0.10142024069098772, "cost": 233.64, "target_value": 136.46624069098772, "running_time": 4.002571105957031, "local_count": 200, "common_count": 0}, "Modify-Assignment(Tx)": {"avg_delay": 0.10203522582449955, "cost": 238.9, "target_value": 137.87022582449956, "running_time": 173.99883270263672, "local_count": 200, "common_count": 0}, "Modify-Assignment(Tx+Tp+Tq)": {"avg_delay": 0.09800665866825517, "cost": 231.96, "target_value": 132.80065866825515, "running_time": 308184.3738555908, "local_count": 142, "common_count": 58}, "Ours": {"avg_delay": 0.09397575156740577, "cost": 183.17, "target_value": 121.45125156740576, "running_time": 1617.119312286377, "local_count": 134, "common_count": 66}}, "sim7": {"simulation_id": 7, "user_seed": 25506784, "Nearest": {"avg_delay": 0.09928211367020916, "cost": 250.46, "target_value": 136.85111367020914, "running_time": 4.002809524536133, "local_count": 200, "common_count": 0}, "Modify-Assignment(Tx)": {"avg_delay": 0.10049261055234976, "cost": 258.79, "target_value": 139.31111055234976, "running_time": 222.2597599029541, "local_count": 200, "common_count": 0}, "Modify-Assignment(Tx+Tp+Tq)": {"avg_delay": 0.09618811291790473, "cost": 248.31, "target_value": 133.43461291790473, "running_time": 314067.5346851349, "local_count": 133, "common_count": 67}, "Ours": {"avg_delay": 0.09229494648053922, "cost": 190.38, "target_value": 120.85194648053923, "running_time": 1503.9114952087402, "local_count": 112, "common_count": 88}}}}