{"40": {"sim0": {"simulation_id": 0, "user_seed": 90270674, "Nearest": {"avg_delay": 0.09896727622456586, "cost": 125.25, "target_value": 111.49227622456587, "running_time": 1.0004043579101562, "local_count": 80, "common_count": 0}, "Modify-Assignment(Tx)": {"avg_delay": 0.10125369381560277, "cost": 129.1, "target_value": 114.16369381560277, "running_time": 43.03598403930664, "local_count": 80, "common_count": 0}, "Modify-Assignment(Tx+Tp+Tq)": {"avg_delay": 0.09610240181934487, "cost": 122.95, "target_value": 108.39740181934488, "running_time": 19577.5249004364, "local_count": 57, "common_count": 23}, "Ours": {"avg_delay": 0.09259468401892557, "cost": 107.4, "target_value": 103.33468401892557, "running_time": 321.26498222351074, "local_count": 56, "common_count": 24}}, "sim1": {"simulation_id": 1, "user_seed": 21515750, "Nearest": {"avg_delay": 0.09890258144979233, "cost": 124.375, "target_value": 111.34008144979234, "running_time": 2.002239227294922, "local_count": 80, "common_count": 0}, "Modify-Assignment(Tx)": {"avg_delay": 0.10166493254580708, "cost": 133.425, "target_value": 115.00743254580708, "running_time": 39.0324592590332, "local_count": 80, "common_count": 0}, "Modify-Assignment(Tx+Tp+Tq)": {"avg_delay": 0.09660892557789007, "cost": 123.2, "target_value": 108.92892557789006, "running_time": 15035.152196884155, "local_count": 60, "common_count": 20}, "Ours": {"avg_delay": 0.09420185331945968, "cost": 110.4, "target_value": 105.2418533194597, "running_time": 318.26186180114746, "local_count": 67, "common_count": 13}}, "sim2": {"simulation_id": 2, "user_seed": 2392691, "Nearest": {"avg_delay": 0.09833239486059149, "cost": 139.375, "target_value": 112.26989486059149, "running_time": 2.001047134399414, "local_count": 80, "common_count": 0}, "Modify-Assignment(Tx)": {"avg_delay": 0.09858845542429244, "cost": 138.225, "target_value": 112.41095542429244, "running_time": 47.59788513183594, "local_count": 80, "common_count": 0}, "Modify-Assignment(Tx+Tp+Tq)": {"avg_delay": 0.0955960890108693, "cost": 138.45, "target_value": 109.4410890108693, "running_time": 19368.15094947815, "local_count": 59, "common_count": 21}, "Ours": {"avg_delay": 0.09016640930613519, "cost": 111.55, "target_value": 101.3214093061352, "running_time": 334.423303604126, "local_count": 54, "common_count": 26}}, "sim3": {"simulation_id": 3, "user_seed": 90878985, "Nearest": {"avg_delay": 0.09627247765355623, "cost": 133.525, "target_value": 109.62497765355624, "running_time": 1.0008811950683594, "local_count": 80, "common_count": 0}, "Modify-Assignment(Tx)": {"avg_delay": 0.09727645408982905, "cost": 139.575, "target_value": 111.23395408982904, "running_time": 34.02829170227051, "local_count": 80, "common_count": 0}, "Modify-Assignment(Tx+Tp+Tq)": {"avg_delay": 0.09320817091309117, "cost": 132.225, "target_value": 106.43067091309116, "running_time": 19646.24261856079, "local_count": 55, "common_count": 25}, "Ours": {"avg_delay": 0.08862727809997482, "cost": 112.45, "target_value": 99.87227809997484, "running_time": 341.2809371948242, "local_count": 56, "common_count": 24}}, "sim4": {"simulation_id": 4, "user_seed": 80803179, "Nearest": {"avg_delay": 0.10157264912464246, "cost": 132.9, "target_value": 114.86264912464247, "running_time": 1.0006427764892578, "local_count": 80, "common_count": 0}, "Modify-Assignment(Tx)": {"avg_delay": 0.10310604830936436, "cost": 134.675, "target_value": 116.57354830936436, "running_time": 51.04207992553711, "local_count": 80, "common_count": 0}, "Modify-Assignment(Tx+Tp+Tq)": {"avg_delay": 0.09861931023224627, "cost": 131.625, "target_value": 111.78181023224627, "running_time": 19197.006702423096, "local_count": 61, "common_count": 19}, "Ours": {"avg_delay": 0.09340358393262078, "cost": 111.25, "target_value": 104.52858393262079, "running_time": 369.3051338195801, "local_count": 65, "common_count": 15}}, "sim5": {"simulation_id": 5, "user_seed": 71960682, "Nearest": {"avg_delay": 0.09345637073424516, "cost": 143.025, "target_value": 107.75887073424516, "running_time": 2.0012855529785156, "local_count": 80, "common_count": 0}, "Modify-Assignment(Tx)": {"avg_delay": 0.09417662684171081, "cost": 144.375, "target_value": 108.61412684171081, "running_time": 46.038150787353516, "local_count": 80, "common_count": 0}, "Modify-Assignment(Tx+Tp+Tq)": {"avg_delay": 0.09100695745292846, "cost": 141.375, "target_value": 105.14445745292846, "running_time": 18284.15536880493, "local_count": 59, "common_count": 21}, "Ours": {"avg_delay": 0.08814533995604056, "cost": 119.75, "target_value": 100.12033995604057, "running_time": 339.4801616668701, "local_count": 66, "common_count": 14}}, "sim6": {"simulation_id": 6, "user_seed": 88798436, "Nearest": {"avg_delay": 0.09794400123118657, "cost": 133.75, "target_value": 111.31900123118658, "running_time": 1.0013580322265625, "local_count": 80, "common_count": 0}, "Modify-Assignment(Tx)": {"avg_delay": 0.09980398993467501, "cost": 134.275, "target_value": 113.23148993467501, "running_time": 61.0504150390625, "local_count": 80, "common_count": 0}, "Modify-Assignment(Tx+Tp+Tq)": {"avg_delay": 0.09522534216263048, "cost": 131.95, "target_value": 108.42034216263048, "running_time": 19744.261264801025, "local_count": 59, "common_count": 21}, "Ours": {"avg_delay": 0.09296814447444979, "cost": 117.85, "target_value": 104.75314447444978, "running_time": 353.29127311706543, "local_count": 68, "common_count": 12}}, "sim7": {"simulation_id": 7, "user_seed": 5307076, "Nearest": {"avg_delay": 0.09490316757387658, "cost": 126.175, "target_value": 107.52066757387658, "running_time": 1.0013580322265625, "local_count": 80, "common_count": 0}, "Modify-Assignment(Tx)": {"avg_delay": 0.0953252822972287, "cost": 128.3, "target_value": 108.1552822972287, "running_time": 43.03550720214844, "local_count": 80, "common_count": 0}, "Modify-Assignment(Tx+Tp+Tq)": {"avg_delay": 0.09156090403099248, "cost": 123.2, "target_value": 103.8809040309925, "running_time": 21937.974452972412, "local_count": 52, "common_count": 28}, "Ours": {"avg_delay": 0.08821342938241127, "cost": 108.85, "target_value": 99.09842938241127, "running_time": 332.5462341308594, "local_count": 54, "common_count": 26}}}, "50": {"sim0": {"simulation_id": 0, "user_seed": 22280712, "Nearest": {"avg_delay": 0.09506074829511946, "cost": 160.46, "target_value": 111.10674829511946, "running_time": 2.0017623901367188, "local_count": 100, "common_count": 0}, "Modify-Assignment(Tx)": {"avg_delay": 0.09656398099585368, "cost": 159.02, "target_value": 112.46598099585368, "running_time": 85.06989479064941, "local_count": 100, "common_count": 0}, "Modify-Assignment(Tx+Tp+Tq)": {"avg_delay": 0.09188459351211237, "cost": 158.58, "target_value": 107.74259351211236, "running_time": 40387.37392425537, "local_count": 67, "common_count": 33}, "Ours": {"avg_delay": 0.08635285486204332, "cost": 136.04, "target_value": 99.95685486204331, "running_time": 483.40654373168945, "local_count": 64, "common_count": 36}}, "sim1": {"simulation_id": 1, "user_seed": 88090824, "Nearest": {"avg_delay": 0.09981793157544698, "cost": 145.08, "target_value": 114.32593157544699, "running_time": 2.0017623901367188, "local_count": 100, "common_count": 0}, "Modify-Assignment(Tx)": {"avg_delay": 0.10054728798118194, "cost": 148.46, "target_value": 115.39328798118194, "running_time": 86.07149124145508, "local_count": 100, "common_count": 0}, "Modify-Assignment(Tx+Tp+Tq)": {"avg_delay": 0.09711218141936753, "cost": 142.4, "target_value": 111.35218141936753, "running_time": 40902.2753238678, "local_count": 68, "common_count": 32}, "Ours": {"avg_delay": 0.09349932568509554, "cost": 123.26, "target_value": 105.82532568509555, "running_time": 482.39803314208984, "local_count": 74, "common_count": 26}}, "sim2": {"simulation_id": 2, "user_seed": 33860367, "Nearest": {"avg_delay": 0.09807423833958871, "cost": 146.02, "target_value": 112.67623833958872, "running_time": 2.0020008087158203, "local_count": 100, "common_count": 0}, "Modify-Assignment(Tx)": {"avg_delay": 0.099066382258811, "cost": 150.56, "target_value": 114.12238225881099, "running_time": 62.183380126953125, "local_count": 100, "common_count": 0}, "Modify-Assignment(Tx+Tp+Tq)": {"avg_delay": 0.09493350223092023, "cost": 144.34, "target_value": 109.36750223092022, "running_time": 46791.945695877075, "local_count": 65, "common_count": 35}, "Ours": {"avg_delay": 0.0916352739175183, "cost": 127.62, "target_value": 104.3972739175183, "running_time": 494.40765380859375, "local_count": 77, "common_count": 23}}, "sim3": {"simulation_id": 3, "user_seed": 62659574, "Nearest": {"avg_delay": 0.09911283695685771, "cost": 167.28, "target_value": 115.84083695685771, "running_time": 2.002239227294922, "local_count": 100, "common_count": 0}, "Modify-Assignment(Tx)": {"avg_delay": 0.10001794940326858, "cost": 169.06, "target_value": 116.92394940326858, "running_time": 80.06620407104492, "local_count": 100, "common_count": 0}, "Modify-Assignment(Tx+Tp+Tq)": {"avg_delay": 0.09613092780023125, "cost": 166.6, "target_value": 112.79092780023124, "running_time": 43328.3007144928, "local_count": 65, "common_count": 35}, "Ours": {"avg_delay": 0.09216187268813684, "cost": 135.64, "target_value": 105.72587268813683, "running_time": 484.68518257141113, "local_count": 72, "common_count": 28}}, "sim4": {"simulation_id": 4, "user_seed": 22052531, "Nearest": {"avg_delay": 0.10093138277087613, "cost": 162.26, "target_value": 117.15738277087613, "running_time": 2.0020008087158203, "local_count": 100, "common_count": 0}, "Modify-Assignment(Tx)": {"avg_delay": 0.10210369601395079, "cost": 164.46, "target_value": 118.5496960139508, "running_time": 67.05498695373535, "local_count": 100, "common_count": 0}, "Modify-Assignment(Tx+Tp+Tq)": {"avg_delay": 0.09859396331950866, "cost": 161.42, "target_value": 114.73596331950866, "running_time": 37583.18519592285, "local_count": 74, "common_count": 26}, "Ours": {"avg_delay": 0.09423573564859057, "cost": 128.42, "target_value": 107.07773564859058, "running_time": 487.5612258911133, "local_count": 76, "common_count": 24}}, "sim5": {"simulation_id": 5, "user_seed": 95751085, "Nearest": {"avg_delay": 0.09655569030716671, "cost": 153.46, "target_value": 111.90169030716672, "running_time": 2.0017623901367188, "local_count": 100, "common_count": 0}, "Modify-Assignment(Tx)": {"avg_delay": 0.09938776081607305, "cost": 161.66, "target_value": 115.55376081607305, "running_time": 72.05963134765625, "local_count": 100, "common_count": 0}, "Modify-Assignment(Tx+Tp+Tq)": {"avg_delay": 0.09420403757389799, "cost": 152.96, "target_value": 109.500037573898, "running_time": 36290.87710380554, "local_count": 76, "common_count": 24}, "Ours": {"avg_delay": 0.09082172689950689, "cost": 132.26, "target_value": 104.04772689950688, "running_time": 491.405725479126, "local_count": 83, "common_count": 17}}, "sim6": {"simulation_id": 6, "user_seed": 81590427, "Nearest": {"avg_delay": 0.09927174342894766, "cost": 153.82, "target_value": 114.65374342894766, "running_time": 2.0017623901367188, "local_count": 100, "common_count": 0}, "Modify-Assignment(Tx)": {"avg_delay": 0.09988370999829778, "cost": 157.22, "target_value": 115.60570999829778, "running_time": 37.03141212463379, "local_count": 100, "common_count": 0}, "Modify-Assignment(Tx+Tp+Tq)": {"avg_delay": 0.09537059529030735, "cost": 151.26, "target_value": 110.49659529030735, "running_time": 39832.78298377991, "local_count": 70, "common_count": 30}, "Ours": {"avg_delay": 0.09138912712697682, "cost": 131.14, "target_value": 104.50312712697682, "running_time": 486.4017963409424, "local_count": 69, "common_count": 31}}, "sim7": {"simulation_id": 7, "user_seed": 67991895, "Nearest": {"avg_delay": 0.09809692359322358, "cost": 156.94, "target_value": 113.79092359322358, "running_time": 1.0013580322265625, "local_count": 100, "common_count": 0}, "Modify-Assignment(Tx)": {"avg_delay": 0.09968896348026714, "cost": 158.84, "target_value": 115.57296348026713, "running_time": 62.05105781555176, "local_count": 100, "common_count": 0}, "Modify-Assignment(Tx+Tp+Tq)": {"avg_delay": 0.09454796891685911, "cost": 154.32, "target_value": 109.97996891685912, "running_time": 43301.04970932007, "local_count": 67, "common_count": 33}, "Ours": {"avg_delay": 0.09040937208271449, "cost": 133.42, "target_value": 103.75137208271448, "running_time": 485.1109981536865, "local_count": 63, "common_count": 37}}}, "60": {"sim0": {"simulation_id": 0, "user_seed": 47896740, "Nearest": {"avg_delay": 0.09655442828069466, "cost": 171.78333333333333, "target_value": 113.73276161402799, "running_time": 2.0017623901367188, "local_count": 120, "common_count": 0}, "Modify-Assignment(Tx)": {"avg_delay": 0.0980305702492778, "cost": 176.96666666666667, "target_value": 115.72723691594447, "running_time": 80.06620407104492, "local_count": 120, "common_count": 0}, "Modify-Assignment(Tx+Tp+Tq)": {"avg_delay": 0.09325772515749244, "cost": 169.51666666666668, "target_value": 110.2093918241591, "running_time": 70134.83333587646, "local_count": 80, "common_count": 40}, "Ours": {"avg_delay": 0.0897800552570776, "cost": 145.23333333333332, "target_value": 104.30338859041095, "running_time": 665.4484272003174, "local_count": 87, "common_count": 33}}, "sim1": {"simulation_id": 1, "user_seed": 81248188, "Nearest": {"avg_delay": 0.09540195199156713, "cost": 182.9, "target_value": 113.69195199156714, "running_time": 3.002643585205078, "local_count": 120, "common_count": 0}, "Modify-Assignment(Tx)": {"avg_delay": 0.09670595413581198, "cost": 192.75, "target_value": 115.98095413581198, "running_time": 110.09073257446289, "local_count": 120, "common_count": 0}, "Modify-Assignment(Tx+Tp+Tq)": {"avg_delay": 0.09257354751697772, "cost": 181.48333333333332, "target_value": 110.72188085031104, "running_time": 71250.56600570679, "local_count": 81, "common_count": 39}, "Ours": {"avg_delay": 0.08925912312759482, "cost": 154.81666666666666, "target_value": 104.74078979426149, "running_time": 683.6133003234863, "local_count": 88, "common_count": 32}}, "sim2": {"simulation_id": 2, "user_seed": 13020948, "Nearest": {"avg_delay": 0.09858617977034907, "cost": 159.7, "target_value": 114.55617977034908, "running_time": 2.001523971557617, "local_count": 120, "common_count": 0}, "Modify-Assignment(Tx)": {"avg_delay": 0.10040670985425082, "cost": 169.05, "target_value": 117.31170985425082, "running_time": 81.06684684753418, "local_count": 120, "common_count": 0}, "Modify-Assignment(Tx+Tp+Tq)": {"avg_delay": 0.0958794726426741, "cost": 158.11666666666667, "target_value": 111.69113930934077, "running_time": 66815.1957988739, "local_count": 86, "common_count": 34}, "Ours": {"avg_delay": 0.09159687468966848, "cost": 133.96666666666667, "target_value": 104.99354135633516, "running_time": 711.742639541626, "local_count": 87, "common_count": 33}}, "sim3": {"simulation_id": 3, "user_seed": 51501079, "Nearest": {"avg_delay": 0.10012209463536255, "cost": 179.95, "target_value": 118.11709463536255, "running_time": 3.0028820037841797, "local_count": 120, "common_count": 0}, "Modify-Assignment(Tx)": {"avg_delay": 0.10050791925912578, "cost": 181.36666666666667, "target_value": 118.64458592579244, "running_time": 92.07606315612793, "local_count": 120, "common_count": 0}, "Modify-Assignment(Tx+Tp+Tq)": {"avg_delay": 0.09716901592810456, "cost": 177.98333333333332, "target_value": 114.96734926143789, "running_time": 60661.34715080261, "local_count": 89, "common_count": 31}, "Ours": {"avg_delay": 0.09309581969093807, "cost": 147.66666666666666, "target_value": 107.86248635760474, "running_time": 659.5439910888672, "local_count": 86, "common_count": 34}}, "sim4": {"simulation_id": 4, "user_seed": 91974727, "Nearest": {"avg_delay": 0.09822669958594392, "cost": 173.66666666666666, "target_value": 115.5933662526106, "running_time": 2.001523971557617, "local_count": 120, "common_count": 0}, "Modify-Assignment(Tx)": {"avg_delay": 0.10007532678316408, "cost": 179.81666666666666, "target_value": 118.05699344983076, "running_time": 103.08480262756348, "local_count": 120, "common_count": 0}, "Modify-Assignment(Tx+Tp+Tq)": {"avg_delay": 0.09572669690958363, "cost": 172.48333333333332, "target_value": 112.97503024291697, "running_time": 49433.20298194885, "local_count": 97, "common_count": 23}, "Ours": {"avg_delay": 0.09274639478588426, "cost": 142.66666666666666, "target_value": 107.01306145255093, "running_time": 662.5509262084961, "local_count": 90, "common_count": 30}}, "sim5": {"simulation_id": 5, "user_seed": 11706952, "Nearest": {"avg_delay": 0.10076915116378064, "cost": 172.91666666666666, "target_value": 118.06081783044732, "running_time": 2.001523971557617, "local_count": 120, "common_count": 0}, "Modify-Assignment(Tx)": {"avg_delay": 0.10242248129243461, "cost": 178.9, "target_value": 120.31248129243461, "running_time": 80.06572723388672, "local_count": 120, "common_count": 0}, "Modify-Assignment(Tx+Tp+Tq)": {"avg_delay": 0.09697252487308565, "cost": 171.06666666666666, "target_value": 114.07919153975232, "running_time": 68050.71711540222, "local_count": 86, "common_count": 34}, "Ours": {"avg_delay": 0.09265997873969474, "cost": 150.66666666666666, "target_value": 107.7266454063614, "running_time": 666.6629314422607, "local_count": 80, "common_count": 40}}, "sim6": {"simulation_id": 6, "user_seed": 61982143, "Nearest": {"avg_delay": 0.09826516484314847, "cost": 179.63333333333333, "target_value": 116.2284981764818, "running_time": 3.002166748046875, "local_count": 120, "common_count": 0}, "Modify-Assignment(Tx)": {"avg_delay": 0.10008795054389887, "cost": 186.13333333333333, "target_value": 118.7012838772322, "running_time": 87.07118034362793, "local_count": 120, "common_count": 0}, "Modify-Assignment(Tx+Tp+Tq)": {"avg_delay": 0.0946322868471394, "cost": 177.16666666666666, "target_value": 112.34895351380607, "running_time": 77525.36606788635, "local_count": 76, "common_count": 44}, "Ours": {"avg_delay": 0.09042414955696974, "cost": 145.5, "target_value": 104.97414955696973, "running_time": 787.1556282043457, "local_count": 80, "common_count": 40}}, "sim7": {"simulation_id": 7, "user_seed": 36101618, "Nearest": {"avg_delay": 0.09952772787487614, "cost": 179.2, "target_value": 117.44772787487614, "running_time": 3.0024051666259766, "local_count": 120, "common_count": 0}, "Modify-Assignment(Tx)": {"avg_delay": 0.10095387652918922, "cost": 190.16666666666666, "target_value": 119.97054319585588, "running_time": 71.05851173400879, "local_count": 120, "common_count": 0}, "Modify-Assignment(Tx+Tp+Tq)": {"avg_delay": 0.09611695042485072, "cost": 177.11666666666667, "target_value": 113.82861709151739, "running_time": 70038.77282142639, "local_count": 88, "common_count": 32}, "Ours": {"avg_delay": 0.0924892741004275, "cost": 154.93333333333334, "target_value": 107.98260743376083, "running_time": 669.2345142364502, "local_count": 84, "common_count": 36}}}, "70": {"sim0": {"simulation_id": 0, "user_seed": 90381983, "Nearest": {"avg_delay": 0.09575799652001159, "cost": 200.61428571428573, "target_value": 115.81942509144017, "running_time": 3.002166748046875, "local_count": 140, "common_count": 0}, "Modify-Assignment(Tx)": {"avg_delay": 0.09777050373707785, "cost": 204.5857142857143, "target_value": 118.22907516564928, "running_time": 107.08737373352051, "local_count": 140, "common_count": 0}, "Modify-Assignment(Tx+Tp+Tq)": {"avg_delay": 0.09308167749854517, "cost": 199.38571428571427, "target_value": 113.0202489271166, "running_time": 93246.54531478882, "local_count": 106, "common_count": 34}, "Ours": {"avg_delay": 0.08828593414193314, "cost": 159.71428571428572, "target_value": 104.25736271336172, "running_time": 873.8625049591064, "local_count": 100, "common_count": 40}}, "sim1": {"simulation_id": 1, "user_seed": 23949374, "Nearest": {"avg_delay": 0.09772204822436366, "cost": 192.37142857142857, "target_value": 116.95919108150652, "running_time": 3.0024051666259766, "local_count": 140, "common_count": 0}, "Modify-Assignment(Tx)": {"avg_delay": 0.0993197770350607, "cost": 199.97142857142856, "target_value": 119.31691989220356, "running_time": 147.12119102478027, "local_count": 140, "common_count": 0}, "Modify-Assignment(Tx+Tp+Tq)": {"avg_delay": 0.09462702602587458, "cost": 191.15714285714284, "target_value": 113.74274031158888, "running_time": 111271.0371017456, "local_count": 95, "common_count": 45}, "Ours": {"avg_delay": 0.09203268075316519, "cost": 157.14285714285714, "target_value": 107.7469664674509, "running_time": 906.3920974731445, "local_count": 107, "common_count": 33}}, "sim2": {"simulation_id": 2, "user_seed": 39422067, "Nearest": {"avg_delay": 0.09729123423502545, "cost": 181.8, "target_value": 115.47123423502545, "running_time": 3.0028820037841797, "local_count": 140, "common_count": 0}, "Modify-Assignment(Tx)": {"avg_delay": 0.0977338880692706, "cost": 183.27142857142857, "target_value": 116.06103092641345, "running_time": 66.0545825958252, "local_count": 140, "common_count": 0}, "Modify-Assignment(Tx+Tp+Tq)": {"avg_delay": 0.09459813082405619, "cost": 179.15714285714284, "target_value": 112.51384510977047, "running_time": 108368.36814880371, "local_count": 101, "common_count": 39}, "Ours": {"avg_delay": 0.09251769058997797, "cost": 150.45714285714286, "target_value": 107.56340487569226, "running_time": 861.3038063049316, "local_count": 104, "common_count": 36}}, "sim3": {"simulation_id": 3, "user_seed": 39510799, "Nearest": {"avg_delay": 0.10076426144993071, "cost": 198.25714285714287, "target_value": 120.589975735645, "running_time": 3.002643585205078, "local_count": 140, "common_count": 0}, "Modify-Assignment(Tx)": {"avg_delay": 0.10093053830952536, "cost": 203.07142857142858, "target_value": 121.23768116666822, "running_time": 79.62512969970703, "local_count": 140, "common_count": 0}, "Modify-Assignment(Tx+Tp+Tq)": {"avg_delay": 0.09794502321889274, "cost": 197.4, "target_value": 117.68502321889275, "running_time": 93753.57389450073, "local_count": 107, "common_count": 33}, "Ours": {"avg_delay": 0.09371869398625679, "cost": 157.18571428571428, "target_value": 109.43726541482823, "running_time": 883.9213848114014, "local_count": 102, "common_count": 38}}, "sim4": {"simulation_id": 4, "user_seed": 27978882, "Nearest": {"avg_delay": 0.10008875662819387, "cost": 199.12857142857143, "target_value": 120.00161377105103, "running_time": 3.0028820037841797, "local_count": 140, "common_count": 0}, "Modify-Assignment(Tx)": {"avg_delay": 0.10271829432219848, "cost": 209.34285714285716, "target_value": 123.6525800364842, "running_time": 185.15276908874512, "local_count": 140, "common_count": 0}, "Modify-Assignment(Tx+Tp+Tq)": {"avg_delay": 0.09726397548836424, "cost": 197.44285714285715, "target_value": 117.00826120264995, "running_time": 105124.4249343872, "local_count": 99, "common_count": 41}, "Ours": {"avg_delay": 0.0938035537412944, "cost": 162.1, "target_value": 110.0135537412944, "running_time": 930.7765960693359, "local_count": 106, "common_count": 34}}, "sim5": {"simulation_id": 5, "user_seed": 27980561, "Nearest": {"avg_delay": 0.09762387118493808, "cost": 188.68571428571428, "target_value": 116.49244261350951, "running_time": 3.0028820037841797, "local_count": 140, "common_count": 0}, "Modify-Assignment(Tx)": {"avg_delay": 0.09970942129734033, "cost": 199.17142857142858, "target_value": 119.62656415448319, "running_time": 128.10540199279785, "local_count": 140, "common_count": 0}, "Modify-Assignment(Tx+Tp+Tq)": {"avg_delay": 0.0947982889005174, "cost": 186.2, "target_value": 113.41828890051741, "running_time": 102823.58837127686, "local_count": 100, "common_count": 40}, "Ours": {"avg_delay": 0.09198739543902168, "cost": 156.31428571428572, "target_value": 107.61882401045025, "running_time": 880.3763389587402, "local_count": 101, "common_count": 39}}, "sim6": {"simulation_id": 6, "user_seed": 72190611, "Nearest": {"avg_delay": 0.09853037656082012, "cost": 204.1, "target_value": 118.94037656082011, "running_time": 3.002643585205078, "local_count": 140, "common_count": 0}, "Modify-Assignment(Tx)": {"avg_delay": 0.09903433477663245, "cost": 201.25714285714287, "target_value": 119.16004906234673, "running_time": 145.68829536437988, "local_count": 140, "common_count": 0}, "Modify-Assignment(Tx+Tp+Tq)": {"avg_delay": 0.09519676983246958, "cost": 201.7, "target_value": 115.36676983246959, "running_time": 115307.66916275024, "local_count": 94, "common_count": 46}, "Ours": {"avg_delay": 0.09095041058436121, "cost": 163.4142857142857, "target_value": 107.29183915578977, "running_time": 868.8786029815674, "local_count": 102, "common_count": 38}}, "sim7": {"simulation_id": 7, "user_seed": 38710822, "Nearest": {"avg_delay": 0.09790037814507203, "cost": 183.82857142857142, "target_value": 116.28323528792919, "running_time": 3.001689910888672, "local_count": 140, "common_count": 0}, "Modify-Assignment(Tx)": {"avg_delay": 0.10092608658820296, "cost": 194.7, "target_value": 120.39608658820296, "running_time": 143.11766624450684, "local_count": 140, "common_count": 0}, "Modify-Assignment(Tx+Tp+Tq)": {"avg_delay": 0.09505524149334374, "cost": 181.84285714285716, "target_value": 113.23952720762946, "running_time": 106743.66044998169, "local_count": 96, "common_count": 44}, "Ours": {"avg_delay": 0.09179923420515974, "cost": 154.78571428571428, "target_value": 107.27780563373118, "running_time": 894.8564529418945, "local_count": 104, "common_count": 36}}}, "80": {"sim0": {"simulation_id": 0, "user_seed": 8336659, "Nearest": {"avg_delay": 0.09811966568274924, "cost": 218.05, "target_value": 119.92466568274925, "running_time": 3.0028820037841797, "local_count": 160, "common_count": 0}, "Modify-Assignment(Tx)": {"avg_delay": 0.09760073289440076, "cost": 214.0625, "target_value": 119.00698289440076, "running_time": 172.14179039001465, "local_count": 160, "common_count": 0}, "Modify-Assignment(Tx+Tp+Tq)": {"avg_delay": 0.0947064459546517, "cost": 215.625, "target_value": 116.2689459546517, "running_time": 161292.84191131592, "local_count": 111, "common_count": 49}, "Ours": {"avg_delay": 0.08963254378728475, "cost": 176.775, "target_value": 107.31004378728474, "running_time": 1100.1522541046143, "local_count": 96, "common_count": 64}}, "sim1": {"simulation_id": 1, "user_seed": 43670286, "Nearest": {"avg_delay": 0.09665320959067321, "cost": 199.5, "target_value": 116.60320959067322, "running_time": 3.0028820037841797, "local_count": 160, "common_count": 0}, "Modify-Assignment(Tx)": {"avg_delay": 0.09972865759145398, "cost": 218.2375, "target_value": 121.55240759145398, "running_time": 225.3730297088623, "local_count": 160, "common_count": 0}, "Modify-Assignment(Tx+Tp+Tq)": {"avg_delay": 0.0942535037474658, "cost": 198.1625, "target_value": 114.0697537474658, "running_time": 122188.16089630127, "local_count": 124, "common_count": 36}, "Ours": {"avg_delay": 0.09153196615614419, "cost": 175.8, "target_value": 109.11196615614419, "running_time": 1098.5815525054932, "local_count": 128, "common_count": 32}}, "sim2": {"simulation_id": 2, "user_seed": 39425301, "Nearest": {"avg_delay": 0.09802889479568576, "cost": 203.9625, "target_value": 118.42514479568575, "running_time": 3.0024051666259766, "local_count": 160, "common_count": 0}, "Modify-Assignment(Tx)": {"avg_delay": 0.09967368209802735, "cost": 214.875, "target_value": 121.16118209802735, "running_time": 169.13938522338867, "local_count": 160, "common_count": 0}, "Modify-Assignment(Tx+Tp+Tq)": {"avg_delay": 0.09507379834642894, "cost": 201.9875, "target_value": 115.27254834642895, "running_time": 149048.34699630737, "local_count": 114, "common_count": 46}, "Ours": {"avg_delay": 0.09098807795730282, "cost": 169.2, "target_value": 107.90807795730282, "running_time": 1092.6055908203125, "local_count": 110, "common_count": 50}}, "sim3": {"simulation_id": 3, "user_seed": 94650118, "Nearest": {"avg_delay": 0.0977206647979772, "cost": 202.6875, "target_value": 117.98941479797719, "running_time": 3.002166748046875, "local_count": 160, "common_count": 0}, "Modify-Assignment(Tx)": {"avg_delay": 0.09914994426439186, "cost": 208.25, "target_value": 119.97494426439187, "running_time": 187.15381622314453, "local_count": 160, "common_count": 0}, "Modify-Assignment(Tx+Tp+Tq)": {"avg_delay": 0.09481717220476979, "cost": 201.1625, "target_value": 114.93342220476978, "running_time": 159842.20361709595, "local_count": 114, "common_count": 46}, "Ours": {"avg_delay": 0.09096577501610958, "cost": 169.625, "target_value": 107.9282750161096, "running_time": 1134.2782974243164, "local_count": 108, "common_count": 52}}, "sim4": {"simulation_id": 4, "user_seed": 70525577, "Nearest": {"avg_delay": 0.10063700568284265, "cost": 212.3625, "target_value": 121.87325568284264, "running_time": 4.003763198852539, "local_count": 160, "common_count": 0}, "Modify-Assignment(Tx)": {"avg_delay": 0.1034634346591926, "cost": 225.725, "target_value": 126.0359346591926, "running_time": 163.13672065734863, "local_count": 160, "common_count": 0}, "Modify-Assignment(Tx+Tp+Tq)": {"avg_delay": 0.09728502261783704, "cost": 210.75, "target_value": 118.36002261783705, "running_time": 157771.08788490295, "local_count": 115, "common_count": 45}, "Ours": {"avg_delay": 0.09349838993869364, "cost": 175.85, "target_value": 111.08338993869364, "running_time": 1132.0481300354004, "local_count": 108, "common_count": 52}}, "sim5": {"simulation_id": 5, "user_seed": 67200163, "Nearest": {"avg_delay": 0.09988465920481124, "cost": 206.15, "target_value": 120.49965920481125, "running_time": 4.003286361694336, "local_count": 160, "common_count": 0}, "Modify-Assignment(Tx)": {"avg_delay": 0.10098999761700524, "cost": 214.9875, "target_value": 122.48874761700523, "running_time": 198.70233535766602, "local_count": 160, "common_count": 0}, "Modify-Assignment(Tx+Tp+Tq)": {"avg_delay": 0.09660180759543524, "cost": 203.9375, "target_value": 116.99555759543524, "running_time": 192133.43501091003, "local_count": 100, "common_count": 60}, "Ours": {"avg_delay": 0.09180382970841812, "cost": 170.825, "target_value": 108.88632970841812, "running_time": 1106.0254573822021, "local_count": 108, "common_count": 52}}, "sim6": {"simulation_id": 6, "user_seed": 12286510, "Nearest": {"avg_delay": 0.09844049651946253, "cost": 215.7, "target_value": 120.01049651946252, "running_time": 4.003286361694336, "local_count": 160, "common_count": 0}, "Modify-Assignment(Tx)": {"avg_delay": 0.09907408223787016, "cost": 216.825, "target_value": 120.75658223787016, "running_time": 149.1227149963379, "local_count": 160, "common_count": 0}, "Modify-Assignment(Tx+Tp+Tq)": {"avg_delay": 0.0946841816999156, "cost": 213.75, "target_value": 116.0591816999156, "running_time": 167690.6054019928, "local_count": 112, "common_count": 48}, "Ours": {"avg_delay": 0.0895247371428516, "cost": 173.55, "target_value": 106.8797371428516, "running_time": 1147.2079753875732, "local_count": 104, "common_count": 56}}, "sim7": {"simulation_id": 7, "user_seed": 40883604, "Nearest": {"avg_delay": 0.09841972559238195, "cost": 202.3125, "target_value": 118.65097559238195, "running_time": 3.002643585205078, "local_count": 160, "common_count": 0}, "Modify-Assignment(Tx)": {"avg_delay": 0.1009607532172748, "cost": 213.4125, "target_value": 122.3020032172748, "running_time": 204.6377658843994, "local_count": 160, "common_count": 0}, "Modify-Assignment(Tx+Tp+Tq)": {"avg_delay": 0.09521895200277598, "cost": 200.1, "target_value": 115.22895200277598, "running_time": 181099.4849205017, "local_count": 110, "common_count": 50}, "Ours": {"avg_delay": 0.09103001196156078, "cost": 169.7375, "target_value": 108.0037619615608, "running_time": 1119.4126605987549, "local_count": 118, "common_count": 42}}}, "90": {"sim0": {"simulation_id": 0, "user_seed": 69890964, "Nearest": {"avg_delay": 0.09734513038464894, "cost": 219.05555555555554, "target_value": 119.25068594020449, "running_time": 4.002809524536133, "local_count": 180, "common_count": 0}, "Modify-Assignment(Tx)": {"avg_delay": 0.09832728896685643, "cost": 223.5, "target_value": 120.67728896685642, "running_time": 169.13962364196777, "local_count": 180, "common_count": 0}, "Modify-Assignment(Tx+Tp+Tq)": {"avg_delay": 0.09437002605952588, "cost": 217.5, "target_value": 116.12002605952588, "running_time": 223948.29893112183, "local_count": 124, "common_count": 56}, "Ours": {"avg_delay": 0.09028499342630598, "cost": 177.15555555555557, "target_value": 108.00054898186154, "running_time": 1352.3125648498535, "local_count": 120, "common_count": 60}}, "sim1": {"simulation_id": 1, "user_seed": 41169465, "Nearest": {"avg_delay": 0.09998265397400677, "cost": 230.9, "target_value": 123.07265397400677, "running_time": 4.002571105957031, "local_count": 180, "common_count": 0}, "Modify-Assignment(Tx)": {"avg_delay": 0.10047553490041618, "cost": 229.82222222222222, "target_value": 123.4577571226384, "running_time": 161.1325740814209, "local_count": 180, "common_count": 0}, "Modify-Assignment(Tx+Tp+Tq)": {"avg_delay": 0.09720683102747853, "cost": 229.07777777777778, "target_value": 120.11460880525631, "running_time": 249498.63409996033, "local_count": 121, "common_count": 59}, "Ours": {"avg_delay": 0.09300570706421168, "cost": 183.56666666666666, "target_value": 111.36237373087836, "running_time": 1397.6764678955078, "local_count": 135, "common_count": 45}}, "sim2": {"simulation_id": 2, "user_seed": 98367259, "Nearest": {"avg_delay": 0.10095019116060924, "cost": 238.76666666666668, "target_value": 124.8268578272759, "running_time": 4.003047943115234, "local_count": 180, "common_count": 0}, "Modify-Assignment(Tx)": {"avg_delay": 0.10178645439407817, "cost": 243.85555555555555, "target_value": 126.17200994963373, "running_time": 167.13809967041016, "local_count": 180, "common_count": 0}, "Modify-Assignment(Tx+Tp+Tq)": {"avg_delay": 0.0975885839476243, "cost": 237.22222222222223, "target_value": 121.31080616984653, "running_time": 228395.04504203796, "local_count": 129, "common_count": 51}, "Ours": {"avg_delay": 0.09218932131463094, "cost": 190.04444444444445, "target_value": 111.19376575907538, "running_time": 1364.0778064727783, "local_count": 121, "common_count": 59}}, "sim3": {"simulation_id": 3, "user_seed": 94422570, "Nearest": {"avg_delay": 0.09882626711880103, "cost": 229.1888888888889, "target_value": 121.74515600768991, "running_time": 3.002166748046875, "local_count": 180, "common_count": 0}, "Modify-Assignment(Tx)": {"avg_delay": 0.10013515387805548, "cost": 238.53333333333333, "target_value": 123.98848721138882, "running_time": 161.1330509185791, "local_count": 180, "common_count": 0}, "Modify-Assignment(Tx+Tp+Tq)": {"avg_delay": 0.09589575522996648, "cost": 228.3111111111111, "target_value": 118.7268663410776, "running_time": 216751.18112564087, "local_count": 127, "common_count": 53}, "Ours": {"avg_delay": 0.09243625586509889, "cost": 191.05555555555554, "target_value": 111.54181142065444, "running_time": 1438.2646083831787, "local_count": 140, "common_count": 40}}, "sim4": {"simulation_id": 4, "user_seed": 78093816, "Nearest": {"avg_delay": 0.09846635940574607, "cost": 232.5, "target_value": 121.71635940574606, "running_time": 4.003286361694336, "local_count": 180, "common_count": 0}, "Modify-Assignment(Tx)": {"avg_delay": 0.10044383525096574, "cost": 243.43333333333334, "target_value": 124.78716858429908, "running_time": 236.19508743286133, "local_count": 180, "common_count": 0}, "Modify-Assignment(Tx+Tp+Tq)": {"avg_delay": 0.09598646827600206, "cost": 231.34444444444443, "target_value": 119.1209127204465, "running_time": 191190.16814231873, "local_count": 137, "common_count": 43}, "Ours": {"avg_delay": 0.09134246641970452, "cost": 181.35555555555555, "target_value": 109.47802197526008, "running_time": 1365.6976222991943, "local_count": 130, "common_count": 50}}, "sim5": {"simulation_id": 5, "user_seed": 64703014, "Nearest": {"avg_delay": 0.09805606193981103, "cost": 221.48888888888888, "target_value": 120.20495082869992, "running_time": 4.002809524536133, "local_count": 180, "common_count": 0}, "Modify-Assignment(Tx)": {"avg_delay": 0.10066004846616962, "cost": 238.9777777777778, "target_value": 124.55782624394739, "running_time": 218.17994117736816, "local_count": 180, "common_count": 0}, "Modify-Assignment(Tx+Tp+Tq)": {"avg_delay": 0.09478529926099977, "cost": 220.44444444444446, "target_value": 116.82974370544422, "running_time": 241642.80939102173, "local_count": 122, "common_count": 58}, "Ours": {"avg_delay": 0.09154584768124345, "cost": 184.53333333333333, "target_value": 109.99918101457678, "running_time": 1388.564109802246, "local_count": 142, "common_count": 38}}, "sim6": {"simulation_id": 6, "user_seed": 30947650, "Nearest": {"avg_delay": 0.10064389990419947, "cost": 222.2, "target_value": 122.86389990419947, "running_time": 4.003286361694336, "local_count": 180, "common_count": 0}, "Modify-Assignment(Tx)": {"avg_delay": 0.10331557470880252, "cost": 238.4777777777778, "target_value": 127.16335248658031, "running_time": 184.15188789367676, "local_count": 180, "common_count": 0}, "Modify-Assignment(Tx+Tp+Tq)": {"avg_delay": 0.09759742968449049, "cost": 221.54444444444445, "target_value": 119.75187412893494, "running_time": 205864.14051055908, "local_count": 134, "common_count": 46}, "Ours": {"avg_delay": 0.09355833907876111, "cost": 177.32222222222222, "target_value": 111.29056130098333, "running_time": 1359.1246604919434, "local_count": 136, "common_count": 44}}, "sim7": {"simulation_id": 7, "user_seed": 36767805, "Nearest": {"avg_delay": 0.09672293741977796, "cost": 222.7111111111111, "target_value": 118.99404853088907, "running_time": 4.003047943115234, "local_count": 180, "common_count": 0}, "Modify-Assignment(Tx)": {"avg_delay": 0.09757772914042596, "cost": 226.7111111111111, "target_value": 120.24884025153708, "running_time": 226.18627548217773, "local_count": 180, "common_count": 0}, "Modify-Assignment(Tx+Tp+Tq)": {"avg_delay": 0.09356922653489633, "cost": 220.67777777777778, "target_value": 115.63700431267411, "running_time": 235383.1012248993, "local_count": 120, "common_count": 60}, "Ours": {"avg_delay": 0.08947165706396204, "cost": 179.38888888888889, "target_value": 107.41054595285092, "running_time": 1381.148338317871, "local_count": 113, "common_count": 67}}}, "100": {"sim0": {"simulation_id": 0, "user_seed": 64072458, "Nearest": {"avg_delay": 0.09860237525508223, "cost": 242.97, "target_value": 122.89937525508222, "running_time": 4.0035247802734375, "local_count": 200, "common_count": 0}, "Modify-Assignment(Tx)": {"avg_delay": 0.0996756509609837, "cost": 248.1, "target_value": 124.4856509609837, "running_time": 273.2253074645996, "local_count": 200, "common_count": 0}, "Modify-Assignment(Tx+Tp+Tq)": {"avg_delay": 0.09491356223217977, "cost": 240.14, "target_value": 118.92756223217977, "running_time": 340729.1622161865, "local_count": 136, "common_count": 64}, "Ours": {"avg_delay": 0.0904284720312256, "cost": 192.44, "target_value": 109.6724720312256, "running_time": 1711.2677097320557, "local_count": 120, "common_count": 80}}, "sim1": {"simulation_id": 1, "user_seed": 27236993, "Nearest": {"avg_delay": 0.0974179352139403, "cost": 262.15, "target_value": 123.6329352139403, "running_time": 5.008459091186523, "local_count": 200, "common_count": 0}, "Modify-Assignment(Tx)": {"avg_delay": 0.09904700868760782, "cost": 271.6, "target_value": 126.20700868760784, "running_time": 292.2406196594238, "local_count": 200, "common_count": 0}, "Modify-Assignment(Tx+Tp+Tq)": {"avg_delay": 0.09442245417213402, "cost": 260.16, "target_value": 120.43845417213403, "running_time": 309441.9548511505, "local_count": 144, "common_count": 56}, "Ours": {"avg_delay": 0.08984575848806023, "cost": 213.88, "target_value": 111.23375848806023, "running_time": 1659.3389511108398, "local_count": 138, "common_count": 62}}, "sim2": {"simulation_id": 2, "user_seed": 62947754, "Nearest": {"avg_delay": 0.09815419359584865, "cost": 254.67, "target_value": 123.62119359584865, "running_time": 5.063772201538086, "local_count": 200, "common_count": 0}, "Modify-Assignment(Tx)": {"avg_delay": 0.09894045824215157, "cost": 259.85, "target_value": 124.92545824215158, "running_time": 254.2097568511963, "local_count": 200, "common_count": 0}, "Modify-Assignment(Tx+Tp+Tq)": {"avg_delay": 0.09481130197173483, "cost": 251.77, "target_value": 119.98830197173484, "running_time": 352626.30319595337, "local_count": 131, "common_count": 69}, "Ours": {"avg_delay": 0.09125735568481569, "cost": 195.36, "target_value": 110.7933556848157, "running_time": 1681.5223693847656, "local_count": 128, "common_count": 72}}, "sim3": {"simulation_id": 3, "user_seed": 19356949, "Nearest": {"avg_delay": 0.09701637081707046, "cost": 234.24, "target_value": 120.44037081707046, "running_time": 5.003690719604492, "local_count": 200, "common_count": 0}, "Modify-Assignment(Tx)": {"avg_delay": 0.09931037002964911, "cost": 251.74, "target_value": 124.48437002964911, "running_time": 257.21216201782227, "local_count": 200, "common_count": 0}, "Modify-Assignment(Tx+Tp+Tq)": {"avg_delay": 0.09457821268981813, "cost": 232.63, "target_value": 117.84121268981814, "running_time": 315639.5983695984, "local_count": 139, "common_count": 61}, "Ours": {"avg_delay": 0.09164892224082771, "cost": 195.25, "target_value": 111.17392224082772, "running_time": 1687.6165866851807, "local_count": 146, "common_count": 54}}, "sim4": {"simulation_id": 4, "user_seed": 40007201, "Nearest": {"avg_delay": 0.09954067796092256, "cost": 239.43, "target_value": 123.48367796092255, "running_time": 4.003763198852539, "local_count": 200, "common_count": 0}, "Modify-Assignment(Tx)": {"avg_delay": 0.10139213437909007, "cost": 253.26, "target_value": 126.71813437909009, "running_time": 266.77608489990234, "local_count": 200, "common_count": 0}, "Modify-Assignment(Tx+Tp+Tq)": {"avg_delay": 0.09614874280385026, "cost": 237.84, "target_value": 119.93274280385026, "running_time": 317518.892288208, "local_count": 148, "common_count": 52}, "Ours": {"avg_delay": 0.09251965800952995, "cost": 197.47, "target_value": 112.26665800952995, "running_time": 1729.2191982269287, "local_count": 142, "common_count": 58}}, "sim5": {"simulation_id": 5, "user_seed": 22621917, "Nearest": {"avg_delay": 0.09824126746827791, "cost": 249.9, "target_value": 123.2312674682779, "running_time": 4.003286361694336, "local_count": 200, "common_count": 0}, "Modify-Assignment(Tx)": {"avg_delay": 0.09937434480301156, "cost": 252.92, "target_value": 124.66634480301157, "running_time": 272.34482765197754, "local_count": 200, "common_count": 0}, "Modify-Assignment(Tx+Tp+Tq)": {"avg_delay": 0.0944142422450198, "cost": 246.98, "target_value": 119.11224224501981, "running_time": 336143.85318756104, "local_count": 139, "common_count": 61}, "Ours": {"avg_delay": 0.09056195235255661, "cost": 199.56, "target_value": 110.51795235255662, "running_time": 1692.9585933685303, "local_count": 112, "common_count": 88}}, "sim6": {"simulation_id": 6, "user_seed": 65331082, "Nearest": {"avg_delay": 0.09902917805349587, "cost": 259.66, "target_value": 124.99517805349588, "running_time": 5.0067901611328125, "local_count": 200, "common_count": 0}, "Modify-Assignment(Tx)": {"avg_delay": 0.10019173262312303, "cost": 268.37, "target_value": 127.02873262312303, "running_time": 233.20889472961426, "local_count": 200, "common_count": 0}, "Modify-Assignment(Tx+Tp+Tq)": {"avg_delay": 0.09599550299816098, "cost": 257.32, "target_value": 121.72750299816099, "running_time": 336356.18686676025, "local_count": 131, "common_count": 69}, "Ours": {"avg_delay": 0.09263565216604079, "cost": 212.77, "target_value": 113.91265216604079, "running_time": 1646.8265056610107, "local_count": 136, "common_count": 64}}, "sim7": {"simulation_id": 7, "user_seed": 93487098, "Nearest": {"avg_delay": 0.09891306736388206, "cost": 253.52, "target_value": 124.26506736388205, "running_time": 4.0073394775390625, "local_count": 200, "common_count": 0}, "Modify-Assignment(Tx)": {"avg_delay": 0.10073986468104532, "cost": 261.8, "target_value": 126.91986468104533, "running_time": 263.2172107696533, "local_count": 200, "common_count": 0}, "Modify-Assignment(Tx+Tp+Tq)": {"avg_delay": 0.09587754812394231, "cost": 252.22, "target_value": 121.0995481239423, "running_time": 317937.1132850647, "local_count": 144, "common_count": 56}, "Ours": {"avg_delay": 0.09221071130344155, "cost": 199.82, "target_value": 112.19271130344156, "running_time": 1574.2151737213135, "local_count": 154, "common_count": 46}}}}