{"40": {"sim0": {"simulation_id": 0, "user_seed": 44330540, "Nearest": {"avg_delay": 0.09729712180290961, "cost": 133.625, "target_value": 110.65962180290961, "running_time": 2.001047134399414, "local_count": 80, "common_count": 0}, "Modify-Assignment(Tx)": {"avg_delay": 0.09923713800287598, "cost": 140.9, "target_value": 113.32713800287598, "running_time": 41.03398323059082, "local_count": 80, "common_count": 0}, "Modify-Assignment(Tx+Tp+Tq)": {"avg_delay": 0.0944098809661892, "cost": 132.65, "target_value": 107.6748809661892, "running_time": 16160.632610321045, "local_count": 60, "common_count": 20}, "Ours": {"avg_delay": 0.0915666760403564, "cost": 117.975, "target_value": 103.3641760403564, "running_time": 324.8169422149658, "local_count": 59, "common_count": 21}}, "sim1": {"simulation_id": 1, "user_seed": 94237581, "Nearest": {"avg_delay": 0.09375299572392094, "cost": 138.25, "target_value": 107.57799572392095, "running_time": 1.0013580322265625, "local_count": 80, "common_count": 0}, "Modify-Assignment(Tx)": {"avg_delay": 0.09745716069478286, "cost": 151.725, "target_value": 112.62966069478286, "running_time": 43.03598403930664, "local_count": 80, "common_count": 0}, "Modify-Assignment(Tx+Tp+Tq)": {"avg_delay": 0.0909496518544855, "cost": 137.325, "target_value": 104.68215185448551, "running_time": 19564.205646514893, "local_count": 56, "common_count": 24}, "Ours": {"avg_delay": 0.0876466720699125, "cost": 115.35, "target_value": 99.1816720699125, "running_time": 320.2641010284424, "local_count": 60, "common_count": 20}}, "sim2": {"simulation_id": 2, "user_seed": 51570790, "Nearest": {"avg_delay": 0.09331543975387566, "cost": 135.475, "target_value": 106.86293975387565, "running_time": 1.001119613647461, "local_count": 80, "common_count": 0}, "Modify-Assignment(Tx)": {"avg_delay": 0.097567643039999, "cost": 148.15, "target_value": 112.382643039999, "running_time": 48.03967475891113, "local_count": 80, "common_count": 0}, "Modify-Assignment(Tx+Tp+Tq)": {"avg_delay": 0.09097592013393543, "cost": 134.55, "target_value": 104.43092013393543, "running_time": 14028.971910476685, "local_count": 65, "common_count": 15}, "Ours": {"avg_delay": 0.08681840429093267, "cost": 113.375, "target_value": 98.15590429093267, "running_time": 333.2798480987549, "local_count": 62, "common_count": 18}}, "sim3": {"simulation_id": 3, "user_seed": 40140127, "Nearest": {"avg_delay": 0.09675072360437112, "cost": 120.65, "target_value": 108.81572360437112, "running_time": 1.0006427764892578, "local_count": 80, "common_count": 0}, "Modify-Assignment(Tx)": {"avg_delay": 0.0981392662201114, "cost": 129.575, "target_value": 111.0967662201114, "running_time": 47.03879356384277, "local_count": 80, "common_count": 0}, "Modify-Assignment(Tx+Tp+Tq)": {"avg_delay": 0.09432272055029549, "cost": 118.975, "target_value": 106.2202205502955, "running_time": 16873.738288879395, "local_count": 60, "common_count": 20}, "Ours": {"avg_delay": 0.09269093123155372, "cost": 109.925, "target_value": 103.68343123155373, "running_time": 338.853120803833, "local_count": 64, "common_count": 16}}, "sim4": {"simulation_id": 4, "user_seed": 79801878, "Nearest": {"avg_delay": 0.0956623159192406, "cost": 135.35, "target_value": 109.1973159192406, "running_time": 2.0017623901367188, "local_count": 80, "common_count": 0}, "Modify-Assignment(Tx)": {"avg_delay": 0.09623947853252048, "cost": 138.325, "target_value": 110.07197853252048, "running_time": 42.03462600708008, "local_count": 80, "common_count": 0}, "Modify-Assignment(Tx+Tp+Tq)": {"avg_delay": 0.09187798290001752, "cost": 133.0, "target_value": 105.17798290001751, "running_time": 21775.346279144287, "local_count": 53, "common_count": 27}, "Ours": {"avg_delay": 0.08746816210725873, "cost": 114.55, "target_value": 98.92316210725873, "running_time": 375.52809715270996, "local_count": 50, "common_count": 30}}, "sim5": {"simulation_id": 5, "user_seed": 7112245, "Nearest": {"avg_delay": 0.09841269396891898, "cost": 140.575, "target_value": 112.47019396891899, "running_time": 1.0008811950683594, "local_count": 80, "common_count": 0}, "Modify-Assignment(Tx)": {"avg_delay": 0.10020788623007634, "cost": 145.65, "target_value": 114.77288623007634, "running_time": 42.03462600708008, "local_count": 80, "common_count": 0}, "Modify-Assignment(Tx+Tp+Tq)": {"avg_delay": 0.09473078899239276, "cost": 139.425, "target_value": 108.67328899239277, "running_time": 20551.387071609497, "local_count": 54, "common_count": 26}, "Ours": {"avg_delay": 0.09062946035142294, "cost": 110.125, "target_value": 101.64196035142294, "running_time": 339.88499641418457, "local_count": 58, "common_count": 22}}, "sim6": {"simulation_id": 6, "user_seed": 43172383, "Nearest": {"avg_delay": 0.09728583655390714, "cost": 140.375, "target_value": 111.32333655390715, "running_time": 1.0006427764892578, "local_count": 80, "common_count": 0}, "Modify-Assignment(Tx)": {"avg_delay": 0.09764927024544486, "cost": 144.05, "target_value": 112.05427024544485, "running_time": 49.03984069824219, "local_count": 80, "common_count": 0}, "Modify-Assignment(Tx+Tp+Tq)": {"avg_delay": 0.09483315008994092, "cost": 138.475, "target_value": 108.68065008994091, "running_time": 17543.531894683838, "local_count": 61, "common_count": 19}, "Ours": {"avg_delay": 0.0900623573834948, "cost": 113.75, "target_value": 101.4373573834948, "running_time": 343.4793949127197, "local_count": 60, "common_count": 20}}, "sim7": {"simulation_id": 7, "user_seed": 44605787, "Nearest": {"avg_delay": 0.09666815779052755, "cost": 127.5, "target_value": 109.41815779052754, "running_time": 2.001523971557617, "local_count": 80, "common_count": 0}, "Modify-Assignment(Tx)": {"avg_delay": 0.10020215461200585, "cost": 135.325, "target_value": 113.73465461200585, "running_time": 54.04400825500488, "local_count": 80, "common_count": 0}, "Modify-Assignment(Tx+Tp+Tq)": {"avg_delay": 0.09417457230965887, "cost": 127.35, "target_value": 106.90957230965887, "running_time": 17651.050090789795, "local_count": 58, "common_count": 22}, "Ours": {"avg_delay": 0.09243461295876307, "cost": 115.375, "target_value": 103.97211295876306, "running_time": 341.2821292877197, "local_count": 66, "common_count": 14}}}, "50": {"sim0": {"simulation_id": 0, "user_seed": 99990298, "Nearest": {"avg_delay": 0.09678978640736673, "cost": 149.36, "target_value": 111.72578640736673, "running_time": 2.0017623901367188, "local_count": 100, "common_count": 0}, "Modify-Assignment(Tx)": {"avg_delay": 0.09871213505789322, "cost": 157.52, "target_value": 114.46413505789323, "running_time": 86.07077598571777, "local_count": 100, "common_count": 0}, "Modify-Assignment(Tx+Tp+Tq)": {"avg_delay": 0.09392430635660111, "cost": 147.38, "target_value": 108.6623063566011, "running_time": 36301.89371109009, "local_count": 71, "common_count": 29}, "Ours": {"avg_delay": 0.0897395351346618, "cost": 129.76, "target_value": 102.7155351346618, "running_time": 492.5966262817383, "local_count": 62, "common_count": 38}}, "sim1": {"simulation_id": 1, "user_seed": 6084678, "Nearest": {"avg_delay": 0.0998668594379837, "cost": 157.22, "target_value": 115.5888594379837, "running_time": 2.0017623901367188, "local_count": 100, "common_count": 0}, "Modify-Assignment(Tx)": {"avg_delay": 0.1011047364359165, "cost": 158.06, "target_value": 116.91073643591649, "running_time": 58.048248291015625, "local_count": 100, "common_count": 0}, "Modify-Assignment(Tx+Tp+Tq)": {"avg_delay": 0.09656794935719461, "cost": 155.8, "target_value": 112.1479493571946, "running_time": 37959.01942253113, "local_count": 75, "common_count": 25}, "Ours": {"avg_delay": 0.09184725188730286, "cost": 130.66, "target_value": 104.91325188730286, "running_time": 494.02832984924316, "local_count": 71, "common_count": 29}}, "sim2": {"simulation_id": 2, "user_seed": 20604324, "Nearest": {"avg_delay": 0.0949802487770958, "cost": 153.24, "target_value": 110.3042487770958, "running_time": 2.0020008087158203, "local_count": 100, "common_count": 0}, "Modify-Assignment(Tx)": {"avg_delay": 0.09701735410600582, "cost": 163.18, "target_value": 113.33535410600581, "running_time": 56.958675384521484, "local_count": 100, "common_count": 0}, "Modify-Assignment(Tx+Tp+Tq)": {"avg_delay": 0.091680775874782, "cost": 151.98, "target_value": 106.87877587478201, "running_time": 38530.45296669006, "local_count": 72, "common_count": 28}, "Ours": {"avg_delay": 0.08870035629301191, "cost": 132.34, "target_value": 101.93435629301192, "running_time": 487.5502586364746, "local_count": 74, "common_count": 26}}, "sim3": {"simulation_id": 3, "user_seed": 59531411, "Nearest": {"avg_delay": 0.097064306927131, "cost": 159.58, "target_value": 113.022306927131, "running_time": 2.001523971557617, "local_count": 100, "common_count": 0}, "Modify-Assignment(Tx)": {"avg_delay": 0.09886837896363769, "cost": 163.0, "target_value": 115.16837896363769, "running_time": 52.042484283447266, "local_count": 100, "common_count": 0}, "Modify-Assignment(Tx+Tp+Tq)": {"avg_delay": 0.09451192944662637, "cost": 158.38, "target_value": 110.34992944662636, "running_time": 40813.38953971863, "local_count": 68, "common_count": 32}, "Ours": {"avg_delay": 0.08916184554083657, "cost": 135.08, "target_value": 102.66984554083658, "running_time": 489.4077777862549, "local_count": 74, "common_count": 26}}, "sim4": {"simulation_id": 4, "user_seed": 93202760, "Nearest": {"avg_delay": 0.09585197895994292, "cost": 153.34, "target_value": 111.18597895994293, "running_time": 2.001523971557617, "local_count": 100, "common_count": 0}, "Modify-Assignment(Tx)": {"avg_delay": 0.09820653443962284, "cost": 160.78, "target_value": 114.28453443962285, "running_time": 67.05546379089355, "local_count": 100, "common_count": 0}, "Modify-Assignment(Tx+Tp+Tq)": {"avg_delay": 0.09350544499227721, "cost": 152.42, "target_value": 108.74744499227721, "running_time": 38341.39347076416, "local_count": 72, "common_count": 28}, "Ours": {"avg_delay": 0.09035700118177603, "cost": 135.48, "target_value": 103.90500118177603, "running_time": 492.1541213989258, "local_count": 84, "common_count": 16}}, "sim5": {"simulation_id": 5, "user_seed": 1293849, "Nearest": {"avg_delay": 0.09511587970789163, "cost": 154.12, "target_value": 110.52787970789164, "running_time": 2.0020008087158203, "local_count": 100, "common_count": 0}, "Modify-Assignment(Tx)": {"avg_delay": 0.09753286108778762, "cost": 161.24, "target_value": 113.65686108778763, "running_time": 82.63754844665527, "local_count": 100, "common_count": 0}, "Modify-Assignment(Tx+Tp+Tq)": {"avg_delay": 0.09249387090247903, "cost": 151.88, "target_value": 107.68187090247903, "running_time": 35680.30834197998, "local_count": 73, "common_count": 27}, "Ours": {"avg_delay": 0.08977848617591315, "cost": 134.02, "target_value": 103.18048617591315, "running_time": 491.6231632232666, "local_count": 78, "common_count": 22}}, "sim6": {"simulation_id": 6, "user_seed": 53821715, "Nearest": {"avg_delay": 0.0976274573147659, "cost": 153.94, "target_value": 113.0214573147659, "running_time": 2.0012855529785156, "local_count": 100, "common_count": 0}, "Modify-Assignment(Tx)": {"avg_delay": 0.10059841566648192, "cost": 165.36, "target_value": 117.13441566648193, "running_time": 70.05763053894043, "local_count": 100, "common_count": 0}, "Modify-Assignment(Tx+Tp+Tq)": {"avg_delay": 0.09512799182794648, "cost": 152.4, "target_value": 110.3679918279465, "running_time": 30784.467697143555, "local_count": 79, "common_count": 21}, "Ours": {"avg_delay": 0.0912189287555348, "cost": 130.16, "target_value": 104.23492875553481, "running_time": 485.97121238708496, "local_count": 82, "common_count": 18}}, "sim7": {"simulation_id": 7, "user_seed": 74717886, "Nearest": {"avg_delay": 0.09781253265122453, "cost": 159.54, "target_value": 113.76653265122454, "running_time": 2.0012855529785156, "local_count": 100, "common_count": 0}, "Modify-Assignment(Tx)": {"avg_delay": 0.09969967926840874, "cost": 167.82, "target_value": 116.48167926840874, "running_time": 75.06132125854492, "local_count": 100, "common_count": 0}, "Modify-Assignment(Tx+Tp+Tq)": {"avg_delay": 0.0955272045243233, "cost": 158.34, "target_value": 111.3612045243233, "running_time": 42119.88592147827, "local_count": 70, "common_count": 30}, "Ours": {"avg_delay": 0.09299534599521944, "cost": 138.78, "target_value": 106.87334599521944, "running_time": 495.4087734222412, "local_count": 85, "common_count": 15}}}, "60": {"sim0": {"simulation_id": 0, "user_seed": 1982308, "Nearest": {"avg_delay": 0.0948931451426204, "cost": 171.0, "target_value": 111.99314514262039, "running_time": 2.001523971557617, "local_count": 120, "common_count": 0}, "Modify-Assignment(Tx)": {"avg_delay": 0.09558390475979225, "cost": 175.3, "target_value": 113.11390475979225, "running_time": 99.08533096313477, "local_count": 120, "common_count": 0}, "Modify-Assignment(Tx+Tp+Tq)": {"avg_delay": 0.09167996489260712, "cost": 168.16666666666666, "target_value": 108.49663155927378, "running_time": 74512.20774650574, "local_count": 76, "common_count": 44}, "Ours": {"avg_delay": 0.08708981613588292, "cost": 141.43333333333334, "target_value": 101.23314946921624, "running_time": 667.550802230835, "local_count": 78, "common_count": 42}}, "sim1": {"simulation_id": 1, "user_seed": 33689003, "Nearest": {"avg_delay": 0.09952579082497622, "cost": 177.7, "target_value": 117.29579082497621, "running_time": 3.0031204223632812, "local_count": 120, "common_count": 0}, "Modify-Assignment(Tx)": {"avg_delay": 0.100551360333101, "cost": 183.31666666666666, "target_value": 118.88302699976767, "running_time": 86.07125282287598, "local_count": 120, "common_count": 0}, "Modify-Assignment(Tx+Tp+Tq)": {"avg_delay": 0.09628133508723945, "cost": 176.01666666666668, "target_value": 113.88300175390611, "running_time": 72816.21193885803, "local_count": 79, "common_count": 41}, "Ours": {"avg_delay": 0.09230227448183731, "cost": 145.21666666666667, "target_value": 106.82394114850399, "running_time": 662.8475189208984, "local_count": 84, "common_count": 36}}, "sim2": {"simulation_id": 2, "user_seed": 27464499, "Nearest": {"avg_delay": 0.09788676859283399, "cost": 176.3, "target_value": 115.51676859283398, "running_time": 3.0024051666259766, "local_count": 120, "common_count": 0}, "Modify-Assignment(Tx)": {"avg_delay": 0.09858819468982373, "cost": 173.86666666666667, "target_value": 115.9748613564904, "running_time": 102.08439826965332, "local_count": 120, "common_count": 0}, "Modify-Assignment(Tx+Tp+Tq)": {"avg_delay": 0.09463160471024903, "cost": 173.65, "target_value": 111.99660471024904, "running_time": 73049.24654960632, "local_count": 81, "common_count": 39}, "Ours": {"avg_delay": 0.09109539144708277, "cost": 140.6, "target_value": 105.15539144708278, "running_time": 676.5577793121338, "local_count": 84, "common_count": 36}}, "sim3": {"simulation_id": 3, "user_seed": 90152220, "Nearest": {"avg_delay": 0.0986726498130983, "cost": 177.13333333333333, "target_value": 116.38598314643164, "running_time": 3.0028820037841797, "local_count": 120, "common_count": 0}, "Modify-Assignment(Tx)": {"avg_delay": 0.0999316467637689, "cost": 181.8, "target_value": 118.1116467637689, "running_time": 99.08151626586914, "local_count": 120, "common_count": 0}, "Modify-Assignment(Tx+Tp+Tq)": {"avg_delay": 0.09519946337968534, "cost": 175.83333333333334, "target_value": 112.78279671301868, "running_time": 68411.3416671753, "local_count": 85, "common_count": 35}, "Ours": {"avg_delay": 0.09065730993417398, "cost": 147.71666666666667, "target_value": 105.42897660084066, "running_time": 700.5777359008789, "local_count": 77, "common_count": 43}}, "sim4": {"simulation_id": 4, "user_seed": 34088379, "Nearest": {"avg_delay": 0.09640459178203975, "cost": 186.15, "target_value": 115.01959178203975, "running_time": 3.002643585205078, "local_count": 120, "common_count": 0}, "Modify-Assignment(Tx)": {"avg_delay": 0.0967452909375063, "cost": 191.31666666666666, "target_value": 115.87695760417299, "running_time": 63.051462173461914, "local_count": 120, "common_count": 0}, "Modify-Assignment(Tx+Tp+Tq)": {"avg_delay": 0.09356448374999281, "cost": 184.7, "target_value": 112.0344837499928, "running_time": 59870.35632133484, "local_count": 84, "common_count": 36}, "Ours": {"avg_delay": 0.08926425821311267, "cost": 151.85, "target_value": 104.44925821311267, "running_time": 668.2381629943848, "local_count": 78, "common_count": 42}}, "sim5": {"simulation_id": 5, "user_seed": 50124850, "Nearest": {"avg_delay": 0.0996145032050281, "cost": 167.98333333333332, "target_value": 116.41283653836143, "running_time": 3.002166748046875, "local_count": 120, "common_count": 0}, "Modify-Assignment(Tx)": {"avg_delay": 0.10117051419279113, "cost": 172.78333333333333, "target_value": 118.44884752612447, "running_time": 80.06596565246582, "local_count": 120, "common_count": 0}, "Modify-Assignment(Tx+Tp+Tq)": {"avg_delay": 0.09641471588710115, "cost": 166.55, "target_value": 113.06971588710115, "running_time": 68593.510389328, "local_count": 88, "common_count": 32}, "Ours": {"avg_delay": 0.09163202122195918, "cost": 136.85, "target_value": 105.31702122195918, "running_time": 667.7544116973877, "local_count": 76, "common_count": 44}}, "sim6": {"simulation_id": 6, "user_seed": 42593096, "Nearest": {"avg_delay": 0.09744100803949919, "cost": 166.61666666666667, "target_value": 114.10267470616586, "running_time": 2.0017623901367188, "local_count": 120, "common_count": 0}, "Modify-Assignment(Tx)": {"avg_delay": 0.09884331320092582, "cost": 174.78333333333333, "target_value": 116.32164653425916, "running_time": 119.09794807434082, "local_count": 120, "common_count": 0}, "Modify-Assignment(Tx+Tp+Tq)": {"avg_delay": 0.0945723038549328, "cost": 164.98333333333332, "target_value": 111.07063718826613, "running_time": 63744.343757629395, "local_count": 88, "common_count": 32}, "Ours": {"avg_delay": 0.09209786035750082, "cost": 145.15, "target_value": 106.61286035750082, "running_time": 714.7510051727295, "local_count": 95, "common_count": 25}}, "sim7": {"simulation_id": 7, "user_seed": 24256809, "Nearest": {"avg_delay": 0.09985813047647264, "cost": 173.15, "target_value": 117.17313047647264, "running_time": 2.0020008087158203, "local_count": 120, "common_count": 0}, "Modify-Assignment(Tx)": {"avg_delay": 0.10174238800910512, "cost": 179.11666666666667, "target_value": 119.65405467577179, "running_time": 112.09273338317871, "local_count": 120, "common_count": 0}, "Modify-Assignment(Tx+Tp+Tq)": {"avg_delay": 0.09669608584050492, "cost": 170.83333333333334, "target_value": 113.77941917383825, "running_time": 70999.54199790955, "local_count": 83, "common_count": 37}, "Ours": {"avg_delay": 0.09305712276610138, "cost": 146.3, "target_value": 107.6871227661014, "running_time": 680.5610656738281, "local_count": 90, "common_count": 30}}}, "70": {"sim0": {"simulation_id": 0, "user_seed": 10367612, "Nearest": {"avg_delay": 0.09878244705319189, "cost": 207.54285714285714, "target_value": 119.5367327674776, "running_time": 2.0017623901367188, "local_count": 140, "common_count": 0}, "Modify-Assignment(Tx)": {"avg_delay": 0.09964025267884567, "cost": 207.77142857142857, "target_value": 120.41739553598853, "running_time": 141.11566543579102, "local_count": 140, "common_count": 0}, "Modify-Assignment(Tx+Tp+Tq)": {"avg_delay": 0.0952009397369062, "cost": 205.8, "target_value": 115.7809397369062, "running_time": 104192.0428276062, "local_count": 97, "common_count": 43}, "Ours": {"avg_delay": 0.09032148128809186, "cost": 166.54285714285714, "target_value": 106.97576700237758, "running_time": 886.7321014404297, "local_count": 100, "common_count": 40}}, "sim1": {"simulation_id": 1, "user_seed": 83587998, "Nearest": {"avg_delay": 0.0967282311566029, "cost": 189.8, "target_value": 115.7082311566029, "running_time": 3.0024051666259766, "local_count": 140, "common_count": 0}, "Modify-Assignment(Tx)": {"avg_delay": 0.09696711924287438, "cost": 193.0, "target_value": 116.26711924287437, "running_time": 131.10709190368652, "local_count": 140, "common_count": 0}, "Modify-Assignment(Tx+Tp+Tq)": {"avg_delay": 0.0935119127053138, "cost": 187.8, "target_value": 112.29191270531379, "running_time": 113219.61116790771, "local_count": 98, "common_count": 42}, "Ours": {"avg_delay": 0.0893704532004812, "cost": 155.9142857142857, "target_value": 104.96188177190979, "running_time": 923.9780902862549, "local_count": 96, "common_count": 44}}, "sim2": {"simulation_id": 2, "user_seed": 26952335, "Nearest": {"avg_delay": 0.09671301340579136, "cost": 189.11428571428573, "target_value": 115.62444197721993, "running_time": 3.002166748046875, "local_count": 140, "common_count": 0}, "Modify-Assignment(Tx)": {"avg_delay": 0.09764724538090724, "cost": 192.2, "target_value": 116.86724538090725, "running_time": 111.09209060668945, "local_count": 140, "common_count": 0}, "Modify-Assignment(Tx+Tp+Tq)": {"avg_delay": 0.0930567686685296, "cost": 186.02857142857144, "target_value": 111.65962581138675, "running_time": 99574.94330406189, "local_count": 106, "common_count": 34}, "Ours": {"avg_delay": 0.0884126237874524, "cost": 151.71428571428572, "target_value": 103.58405235888098, "running_time": 872.03049659729, "local_count": 76, "common_count": 64}}, "sim3": {"simulation_id": 3, "user_seed": 52977472, "Nearest": {"avg_delay": 0.09756284103260038, "cost": 189.6, "target_value": 116.52284103260038, "running_time": 3.003358840942383, "local_count": 140, "common_count": 0}, "Modify-Assignment(Tx)": {"avg_delay": 0.09939353895009861, "cost": 197.15714285714284, "target_value": 119.1092532358129, "running_time": 163.13433647155762, "local_count": 140, "common_count": 0}, "Modify-Assignment(Tx+Tp+Tq)": {"avg_delay": 0.09425422728962309, "cost": 186.7, "target_value": 112.92422728962309, "running_time": 107951.86233520508, "local_count": 100, "common_count": 40}, "Ours": {"avg_delay": 0.08992661635199801, "cost": 153.85714285714286, "target_value": 105.31233063771231, "running_time": 889.7347450256348, "local_count": 90, "common_count": 50}}, "sim4": {"simulation_id": 4, "user_seed": 6696543, "Nearest": {"avg_delay": 0.09825640093587586, "cost": 187.62857142857143, "target_value": 117.019258078733, "running_time": 3.0031204223632812, "local_count": 140, "common_count": 0}, "Modify-Assignment(Tx)": {"avg_delay": 0.09992005385517734, "cost": 186.68571428571428, "target_value": 118.58862528374877, "running_time": 164.13545608520508, "local_count": 140, "common_count": 0}, "Modify-Assignment(Tx+Tp+Tq)": {"avg_delay": 0.09526618504889985, "cost": 185.5857142857143, "target_value": 113.82475647747127, "running_time": 99061.08522415161, "local_count": 102, "common_count": 38}, "Ours": {"avg_delay": 0.09130233576962062, "cost": 156.38571428571427, "target_value": 106.94090719819204, "running_time": 915.9097671508789, "local_count": 92, "common_count": 48}}, "sim5": {"simulation_id": 5, "user_seed": 44536913, "Nearest": {"avg_delay": 0.09726199147367881, "cost": 196.64285714285714, "target_value": 116.92627718796452, "running_time": 3.0024051666259766, "local_count": 140, "common_count": 0}, "Modify-Assignment(Tx)": {"avg_delay": 0.09790700416926905, "cost": 201.94285714285715, "target_value": 118.10128988355476, "running_time": 88.07229995727539, "local_count": 140, "common_count": 0}, "Modify-Assignment(Tx+Tp+Tq)": {"avg_delay": 0.0933655439774602, "cost": 194.27142857142857, "target_value": 112.79268683460306, "running_time": 111621.97351455688, "local_count": 97, "common_count": 43}, "Ours": {"avg_delay": 0.08982531727486792, "cost": 159.04285714285714, "target_value": 105.72960298915365, "running_time": 875.4017353057861, "local_count": 96, "common_count": 44}}, "sim6": {"simulation_id": 6, "user_seed": 76309811, "Nearest": {"avg_delay": 0.09537281078181352, "cost": 184.0857142857143, "target_value": 113.78138221038495, "running_time": 3.0024051666259766, "local_count": 140, "common_count": 0}, "Modify-Assignment(Tx)": {"avg_delay": 0.09589398785932399, "cost": 187.57142857142858, "target_value": 114.65113071646684, "running_time": 143.11838150024414, "local_count": 140, "common_count": 0}, "Modify-Assignment(Tx+Tp+Tq)": {"avg_delay": 0.0928522870432555, "cost": 181.64285714285714, "target_value": 111.01657275754121, "running_time": 93329.20813560486, "local_count": 99, "common_count": 41}, "Ours": {"avg_delay": 0.08949231705600655, "cost": 157.0, "target_value": 105.19231705600654, "running_time": 865.3273582458496, "local_count": 100, "common_count": 40}}, "sim7": {"simulation_id": 7, "user_seed": 2529498, "Nearest": {"avg_delay": 0.09761808916832004, "cost": 182.54285714285714, "target_value": 115.87237488260575, "running_time": 3.0031204223632812, "local_count": 140, "common_count": 0}, "Modify-Assignment(Tx)": {"avg_delay": 0.10071260573207992, "cost": 193.4857142857143, "target_value": 120.06117716065135, "running_time": 115.09561538696289, "local_count": 140, "common_count": 0}, "Modify-Assignment(Tx+Tp+Tq)": {"avg_delay": 0.09462028171038721, "cost": 180.32857142857142, "target_value": 112.65313885324434, "running_time": 97290.26508331299, "local_count": 104, "common_count": 36}, "Ours": {"avg_delay": 0.09127982676759247, "cost": 155.64285714285714, "target_value": 106.84411248187818, "running_time": 911.1244678497314, "local_count": 102, "common_count": 38}}}, "80": {"sim0": {"simulation_id": 0, "user_seed": 86587020, "Nearest": {"avg_delay": 0.0974661262074652, "cost": 198.95, "target_value": 117.36112620746519, "running_time": 4.002809524536133, "local_count": 160, "common_count": 0}, "Modify-Assignment(Tx)": {"avg_delay": 0.09976648145193355, "cost": 209.2625, "target_value": 120.69273145193354, "running_time": 185.14633178710938, "local_count": 160, "common_count": 0}, "Modify-Assignment(Tx+Tp+Tq)": {"avg_delay": 0.0947841603860206, "cost": 197.375, "target_value": 114.5216603860206, "running_time": 132787.85037994385, "local_count": 124, "common_count": 36}, "Ours": {"avg_delay": 0.09272296907118198, "cost": 169.5375, "target_value": 109.67671907118198, "running_time": 1116.6470050811768, "local_count": 120, "common_count": 40}}, "sim1": {"simulation_id": 1, "user_seed": 68562943, "Nearest": {"avg_delay": 0.10112880121353675, "cost": 204.7875, "target_value": 121.60755121353675, "running_time": 3.0024051666259766, "local_count": 160, "common_count": 0}, "Modify-Assignment(Tx)": {"avg_delay": 0.1033798998720485, "cost": 215.1375, "target_value": 124.8936498720485, "running_time": 187.15476989746094, "local_count": 160, "common_count": 0}, "Modify-Assignment(Tx+Tp+Tq)": {"avg_delay": 0.09793121726124482, "cost": 202.625, "target_value": 118.19371726124483, "running_time": 159708.7757587433, "local_count": 114, "common_count": 46}, "Ours": {"avg_delay": 0.09537467348749892, "cost": 169.8625, "target_value": 112.36092348749892, "running_time": 1165.5778884887695, "local_count": 110, "common_count": 50}}, "sim2": {"simulation_id": 2, "user_seed": 39840268, "Nearest": {"avg_delay": 0.09938822753891711, "cost": 208.0125, "target_value": 120.18947753891712, "running_time": 4.004240036010742, "local_count": 160, "common_count": 0}, "Modify-Assignment(Tx)": {"avg_delay": 0.1010818718956699, "cost": 217.8875, "target_value": 122.8706218956699, "running_time": 116.01924896240234, "local_count": 160, "common_count": 0}, "Modify-Assignment(Tx+Tp+Tq)": {"avg_delay": 0.09599649435526034, "cost": 206.2875, "target_value": 116.62524435526034, "running_time": 157254.5063495636, "local_count": 113, "common_count": 47}, "Ours": {"avg_delay": 0.09130530457914414, "cost": 170.9625, "target_value": 108.40155457914413, "running_time": 1119.8029518127441, "local_count": 110, "common_count": 50}}, "sim3": {"simulation_id": 3, "user_seed": 76900335, "Nearest": {"avg_delay": 0.09890224914752861, "cost": 218.0125, "target_value": 120.7034991475286, "running_time": 3.002643585205078, "local_count": 160, "common_count": 0}, "Modify-Assignment(Tx)": {"avg_delay": 0.10061435335684418, "cost": 229.4875, "target_value": 123.56310335684418, "running_time": 226.18651390075684, "local_count": 160, "common_count": 0}, "Modify-Assignment(Tx+Tp+Tq)": {"avg_delay": 0.09605418363829862, "cost": 215.7875, "target_value": 117.63293363829862, "running_time": 166070.97721099854, "local_count": 107, "common_count": 53}, "Ours": {"avg_delay": 0.0916915332363844, "cost": 177.4625, "target_value": 109.4377832363844, "running_time": 1132.2405338287354, "local_count": 112, "common_count": 48}}, "sim4": {"simulation_id": 4, "user_seed": 9804443, "Nearest": {"avg_delay": 0.10096861132616881, "cost": 221.775, "target_value": 123.1461113261688, "running_time": 3.0062198638916016, "local_count": 160, "common_count": 0}, "Modify-Assignment(Tx)": {"avg_delay": 0.10381265493521545, "cost": 232.175, "target_value": 127.03015493521545, "running_time": 195.08814811706543, "local_count": 160, "common_count": 0}, "Modify-Assignment(Tx+Tp+Tq)": {"avg_delay": 0.0982818139912086, "cost": 220.425, "target_value": 120.3243139912086, "running_time": 138883.76450538635, "local_count": 122, "common_count": 38}, "Ours": {"avg_delay": 0.09356165973871892, "cost": 177.475, "target_value": 111.30915973871893, "running_time": 1156.7234992980957, "local_count": 112, "common_count": 48}}, "sim5": {"simulation_id": 5, "user_seed": 51700081, "Nearest": {"avg_delay": 0.09695212758761272, "cost": 215.9375, "target_value": 118.54587758761272, "running_time": 4.002571105957031, "local_count": 160, "common_count": 0}, "Modify-Assignment(Tx)": {"avg_delay": 0.09895219368042922, "cost": 227.4625, "target_value": 121.69844368042922, "running_time": 132.1091651916504, "local_count": 160, "common_count": 0}, "Modify-Assignment(Tx+Tp+Tq)": {"avg_delay": 0.09379299364387235, "cost": 213.9, "target_value": 115.18299364387235, "running_time": 155554.88514900208, "local_count": 112, "common_count": 48}, "Ours": {"avg_delay": 0.09023877674498744, "cost": 178.4125, "target_value": 108.08002674498744, "running_time": 1133.6877346038818, "local_count": 112, "common_count": 48}}, "sim6": {"simulation_id": 6, "user_seed": 36007019, "Nearest": {"avg_delay": 0.09526223412775638, "cost": 218.575, "target_value": 117.11973412775637, "running_time": 4.003286361694336, "local_count": 160, "common_count": 0}, "Modify-Assignment(Tx)": {"avg_delay": 0.09645510988670485, "cost": 233.8, "target_value": 119.83510988670486, "running_time": 206.24184608459473, "local_count": 160, "common_count": 0}, "Modify-Assignment(Tx+Tp+Tq)": {"avg_delay": 0.09251966212007362, "cost": 217.175, "target_value": 114.23716212007362, "running_time": 148618.94345283508, "local_count": 114, "common_count": 46}, "Ours": {"avg_delay": 0.08851960372041506, "cost": 180.525, "target_value": 106.57210372041507, "running_time": 1163.8329029083252, "local_count": 126, "common_count": 34}}, "sim7": {"simulation_id": 7, "user_seed": 73361236, "Nearest": {"avg_delay": 0.10131287435091142, "cost": 204.2875, "target_value": 121.74162435091142, "running_time": 3.002166748046875, "local_count": 160, "common_count": 0}, "Modify-Assignment(Tx)": {"avg_delay": 0.1027663961847059, "cost": 210.2375, "target_value": 123.7901461847059, "running_time": 116.08552932739258, "local_count": 160, "common_count": 0}, "Modify-Assignment(Tx+Tp+Tq)": {"avg_delay": 0.09784599189566288, "cost": 202.45, "target_value": 118.0909918956629, "running_time": 172819.37432289124, "local_count": 113, "common_count": 47}, "Ours": {"avg_delay": 0.09367151835113571, "cost": 165.925, "target_value": 110.26401835113572, "running_time": 1125.6108283996582, "local_count": 106, "common_count": 54}}}, "90": {"sim0": {"simulation_id": 0, "user_seed": 59552004, "Nearest": {"avg_delay": 0.09939736012336227, "cost": 237.2111111111111, "target_value": 123.11847123447339, "running_time": 4.003047943115234, "local_count": 180, "common_count": 0}, "Modify-Assignment(Tx)": {"avg_delay": 0.10159804522554199, "cost": 250.77777777777777, "target_value": 126.67582300331976, "running_time": 207.36289024353027, "local_count": 180, "common_count": 0}, "Modify-Assignment(Tx+Tp+Tq)": {"avg_delay": 0.09655108884127239, "cost": 236.01111111111112, "target_value": 120.1521999523835, "running_time": 226912.01758384705, "local_count": 125, "common_count": 55}, "Ours": {"avg_delay": 0.09178881459277795, "cost": 190.45555555555555, "target_value": 110.8343701483335, "running_time": 1370.9914684295654, "local_count": 123, "common_count": 57}}, "sim1": {"simulation_id": 1, "user_seed": 44734999, "Nearest": {"avg_delay": 0.0961965695005835, "cost": 225.2, "target_value": 118.7165695005835, "running_time": 4.002809524536133, "local_count": 180, "common_count": 0}, "Modify-Assignment(Tx)": {"avg_delay": 0.09750668091226847, "cost": 231.84444444444443, "target_value": 120.69112535671292, "running_time": 157.12976455688477, "local_count": 180, "common_count": 0}, "Modify-Assignment(Tx+Tp+Tq)": {"avg_delay": 0.09331694362543587, "cost": 222.96666666666667, "target_value": 115.61361029210254, "running_time": 242026.93796157837, "local_count": 115, "common_count": 65}, "Ours": {"avg_delay": 0.08990367535906678, "cost": 185.94444444444446, "target_value": 108.49811980351123, "running_time": 1403.1617641448975, "local_count": 134, "common_count": 46}}, "sim2": {"simulation_id": 2, "user_seed": 84222685, "Nearest": {"avg_delay": 0.09520587129718736, "cost": 229.5222222222222, "target_value": 118.15809351940958, "running_time": 4.003047943115234, "local_count": 180, "common_count": 0}, "Modify-Assignment(Tx)": {"avg_delay": 0.09707026400199385, "cost": 242.17777777777778, "target_value": 121.28804177977163, "running_time": 209.24997329711914, "local_count": 180, "common_count": 0}, "Modify-Assignment(Tx+Tp+Tq)": {"avg_delay": 0.09272753630588523, "cost": 227.98888888888888, "target_value": 115.52642519477413, "running_time": 216129.18710708618, "local_count": 129, "common_count": 51}, "Ours": {"avg_delay": 0.0894048431439632, "cost": 190.9777777777778, "target_value": 108.50262092174098, "running_time": 1388.4968757629395, "local_count": 132, "common_count": 48}}, "sim3": {"simulation_id": 3, "user_seed": 92349676, "Nearest": {"avg_delay": 0.0980646154162676, "cost": 207.43333333333334, "target_value": 118.80794874960094, "running_time": 4.004001617431641, "local_count": 180, "common_count": 0}, "Modify-Assignment(Tx)": {"avg_delay": 0.10059759679372479, "cost": 222.34444444444443, "target_value": 122.83204123816924, "running_time": 183.699369430542, "local_count": 180, "common_count": 0}, "Modify-Assignment(Tx+Tp+Tq)": {"avg_delay": 0.09511284883737979, "cost": 205.6888888888889, "target_value": 115.68173772626868, "running_time": 190019.4878578186, "local_count": 132, "common_count": 48}, "Ours": {"avg_delay": 0.09273229535016599, "cost": 178.43333333333334, "target_value": 110.57562868349932, "running_time": 1427.8621673583984, "local_count": 130, "common_count": 50}}, "sim4": {"simulation_id": 4, "user_seed": 5127966, "Nearest": {"avg_delay": 0.10160394456440636, "cost": 232.9111111111111, "target_value": 124.89505567551747, "running_time": 5.0048828125, "local_count": 180, "common_count": 0}, "Modify-Assignment(Tx)": {"avg_delay": 0.10325977220737775, "cost": 237.1888888888889, "target_value": 126.97866109626665, "running_time": 232.1920394897461, "local_count": 180, "common_count": 0}, "Modify-Assignment(Tx+Tp+Tq)": {"avg_delay": 0.09762014389446068, "cost": 230.37777777777777, "target_value": 120.65792167223846, "running_time": 274698.46749305725, "local_count": 115, "common_count": 65}, "Ours": {"avg_delay": 0.09330970259065617, "cost": 181.4, "target_value": 111.44970259065617, "running_time": 1393.7208652496338, "local_count": 119, "common_count": 61}}, "sim5": {"simulation_id": 5, "user_seed": 64006211, "Nearest": {"avg_delay": 0.09784307543816702, "cost": 220.96666666666667, "target_value": 119.93974210483368, "running_time": 4.159450531005859, "local_count": 180, "common_count": 0}, "Modify-Assignment(Tx)": {"avg_delay": 0.09908892034508766, "cost": 229.67777777777778, "target_value": 122.05669812286544, "running_time": 220.18074989318848, "local_count": 180, "common_count": 0}, "Modify-Assignment(Tx+Tp+Tq)": {"avg_delay": 0.09503571870265554, "cost": 219.34444444444443, "target_value": 116.97016314709998, "running_time": 219853.74307632446, "local_count": 125, "common_count": 55}, "Ours": {"avg_delay": 0.09238774966397498, "cost": 186.85555555555555, "target_value": 111.07330521953052, "running_time": 1426.1808395385742, "local_count": 138, "common_count": 42}}, "sim6": {"simulation_id": 6, "user_seed": 40790866, "Nearest": {"avg_delay": 0.10070798609277634, "cost": 228.04444444444445, "target_value": 123.51243053722078, "running_time": 4.0035247802734375, "local_count": 180, "common_count": 0}, "Modify-Assignment(Tx)": {"avg_delay": 0.10271216880318501, "cost": 242.66666666666666, "target_value": 126.97883546985167, "running_time": 245.20230293273926, "local_count": 180, "common_count": 0}, "Modify-Assignment(Tx+Tp+Tq)": {"avg_delay": 0.09773661766283691, "cost": 226.51111111111112, "target_value": 120.38772877394803, "running_time": 195160.61973571777, "local_count": 137, "common_count": 43}, "Ours": {"avg_delay": 0.09394132443502752, "cost": 188.61111111111111, "target_value": 112.80243554613864, "running_time": 1385.7276439666748, "local_count": 124, "common_count": 56}}, "sim7": {"simulation_id": 7, "user_seed": 20931534, "Nearest": {"avg_delay": 0.09890070616615891, "cost": 232.0888888888889, "target_value": 122.1095950550478, "running_time": 4.003286361694336, "local_count": 180, "common_count": 0}, "Modify-Assignment(Tx)": {"avg_delay": 0.1004761564380617, "cost": 240.63333333333333, "target_value": 124.53948977139503, "running_time": 193.1900978088379, "local_count": 180, "common_count": 0}, "Modify-Assignment(Tx+Tp+Tq)": {"avg_delay": 0.09620885276814471, "cost": 230.7111111111111, "target_value": 119.27996387925582, "running_time": 226758.43834877014, "local_count": 128, "common_count": 52}, "Ours": {"avg_delay": 0.09297064369026412, "cost": 194.12222222222223, "target_value": 112.38286591248634, "running_time": 1423.3965873718262, "local_count": 132, "common_count": 48}}}, "100": {"sim0": {"simulation_id": 0, "user_seed": 84430358, "Nearest": {"avg_delay": 0.09756737095440965, "cost": 244.92, "target_value": 122.05937095440966, "running_time": 4.003286361694336, "local_count": 200, "common_count": 0}, "Modify-Assignment(Tx)": {"avg_delay": 0.10000558710057879, "cost": 258.97, "target_value": 125.9025871005788, "running_time": 256.2904357910156, "local_count": 200, "common_count": 0}, "Modify-Assignment(Tx+Tp+Tq)": {"avg_delay": 0.094212988756815, "cost": 243.52, "target_value": 118.564988756815, "running_time": 320464.49637413025, "local_count": 140, "common_count": 60}, "Ours": {"avg_delay": 0.0914869947223642, "cost": 201.31, "target_value": 111.6179947223642, "running_time": 1728.0831336975098, "local_count": 138, "common_count": 62}}, "sim1": {"simulation_id": 1, "user_seed": 97920594, "Nearest": {"avg_delay": 0.09665341742942885, "cost": 260.37, "target_value": 122.69041742942885, "running_time": 4.003047943115234, "local_count": 200, "common_count": 0}, "Modify-Assignment(Tx)": {"avg_delay": 0.09827891480025772, "cost": 270.65, "target_value": 125.3439148002577, "running_time": 279.23011779785156, "local_count": 200, "common_count": 0}, "Modify-Assignment(Tx+Tp+Tq)": {"avg_delay": 0.0935085585373468, "cost": 259.08, "target_value": 119.4165585373468, "running_time": 335329.23793792725, "local_count": 139, "common_count": 61}, "Ours": {"avg_delay": 0.08927872981914789, "cost": 212.22, "target_value": 110.50072981914789, "running_time": 1704.3335437774658, "local_count": 142, "common_count": 58}}, "sim2": {"simulation_id": 2, "user_seed": 92209122, "Nearest": {"avg_delay": 0.09944048497944843, "cost": 226.62, "target_value": 122.10248497944843, "running_time": 4.003286361694336, "local_count": 200, "common_count": 0}, "Modify-Assignment(Tx)": {"avg_delay": 0.10110958553333985, "cost": 237.06, "target_value": 124.81558553333986, "running_time": 288.2416248321533, "local_count": 200, "common_count": 0}, "Modify-Assignment(Tx+Tp+Tq)": {"avg_delay": 0.09643880274461061, "cost": 225.36, "target_value": 118.97480274461061, "running_time": 302994.49014663696, "local_count": 146, "common_count": 54}, "Ours": {"avg_delay": 0.09317315362785895, "cost": 191.44, "target_value": 112.31715362785896, "running_time": 1726.5429496765137, "local_count": 156, "common_count": 44}}, "sim3": {"simulation_id": 3, "user_seed": 13753418, "Nearest": {"avg_delay": 0.09951736940274908, "cost": 238.56, "target_value": 123.37336940274909, "running_time": 5.003690719604492, "local_count": 200, "common_count": 0}, "Modify-Assignment(Tx)": {"avg_delay": 0.10308723569621095, "cost": 264.55, "target_value": 129.54223569621095, "running_time": 268.221378326416, "local_count": 200, "common_count": 0}, "Modify-Assignment(Tx+Tp+Tq)": {"avg_delay": 0.09558627949666873, "cost": 236.91, "target_value": 119.27727949666873, "running_time": 299936.1090660095, "local_count": 145, "common_count": 55}, "Ours": {"avg_delay": 0.09210574740147692, "cost": 196.36, "target_value": 111.74174740147691, "running_time": 1670.12619972229, "local_count": 132, "common_count": 68}}, "sim4": {"simulation_id": 4, "user_seed": 60395328, "Nearest": {"avg_delay": 0.09830871392101408, "cost": 259.22, "target_value": 124.23071392101409, "running_time": 5.003690719604492, "local_count": 200, "common_count": 0}, "Modify-Assignment(Tx)": {"avg_delay": 0.09994209622464936, "cost": 272.3, "target_value": 127.17209622464937, "running_time": 213.1788730621338, "local_count": 200, "common_count": 0}, "Modify-Assignment(Tx+Tp+Tq)": {"avg_delay": 0.09496451612713439, "cost": 257.94, "target_value": 120.75851612713438, "running_time": 331085.5860710144, "local_count": 138, "common_count": 62}, "Ours": {"avg_delay": 0.09076294575192852, "cost": 205.55, "target_value": 111.31794575192852, "running_time": 1747.7984428405762, "local_count": 148, "common_count": 52}}, "sim5": {"simulation_id": 5, "user_seed": 6319789, "Nearest": {"avg_delay": 0.09646194269308893, "cost": 251.61, "target_value": 121.62294269308893, "running_time": 5.004167556762695, "local_count": 200, "common_count": 0}, "Modify-Assignment(Tx)": {"avg_delay": 0.09775580475712789, "cost": 257.62, "target_value": 123.51780475712789, "running_time": 268.2209014892578, "local_count": 200, "common_count": 0}, "Modify-Assignment(Tx+Tp+Tq)": {"avg_delay": 0.09356371471542009, "cost": 249.33, "target_value": 118.4967147154201, "running_time": 320181.4901828766, "local_count": 140, "common_count": 60}, "Ours": {"avg_delay": 0.09023958972132531, "cost": 203.45, "target_value": 110.58458972132532, "running_time": 1720.6013202667236, "local_count": 148, "common_count": 52}}, "sim6": {"simulation_id": 6, "user_seed": 96363005, "Nearest": {"avg_delay": 0.09696308976553535, "cost": 239.32, "target_value": 120.89508976553535, "running_time": 4.003286361694336, "local_count": 200, "common_count": 0}, "Modify-Assignment(Tx)": {"avg_delay": 0.09841481540845876, "cost": 251.61, "target_value": 123.57581540845875, "running_time": 235.23807525634766, "local_count": 200, "common_count": 0}, "Modify-Assignment(Tx+Tp+Tq)": {"avg_delay": 0.09392428540628571, "cost": 238.1, "target_value": 117.73428540628571, "running_time": 260122.46775627136, "local_count": 150, "common_count": 50}, "Ours": {"avg_delay": 0.08955493515806894, "cost": 199.58, "target_value": 109.51293515806893, "running_time": 1698.8329887390137, "local_count": 144, "common_count": 56}}, "sim7": {"simulation_id": 7, "user_seed": 76802041, "Nearest": {"avg_delay": 0.09720924129435983, "cost": 243.75, "target_value": 121.58424129435983, "running_time": 4.0035247802734375, "local_count": 200, "common_count": 0}, "Modify-Assignment(Tx)": {"avg_delay": 0.0992680564430265, "cost": 260.17, "target_value": 125.28505644302649, "running_time": 253.82447242736816, "local_count": 200, "common_count": 0}, "Modify-Assignment(Tx+Tp+Tq)": {"avg_delay": 0.09471349351472264, "cost": 243.31, "target_value": 119.04449351472263, "running_time": 265794.3699359894, "local_count": 149, "common_count": 51}, "Ours": {"avg_delay": 0.09159519433088892, "cost": 199.33, "target_value": 111.52819433088892, "running_time": 1718.1854248046875, "local_count": 156, "common_count": 44}}}}