{"40": {"sim0": {"simulation_id": 0, "user_seed": 765687573, "0": {"Nearest": {"max_delay": 0.14375485661424608, "cost": 0.0, "target_value": 143.75485661424608, "running_time": 0.0, "local_count": 80, "common_count": 0}, "M-Greedy": {"max_delay": 0.13266622778143516, "cost": 0.0, "target_value": 132.66622778143517, "running_time": 1122.4148273468018, "n_selected_site": 10, "local_count": 32, "common_count": 48}, "M-Greedy-V2(Tx+Tp+Tq)": {"max_delay": 0.13266622778143516, "cost": 0.0, "target_value": 132.66622778143517, "running_time": 3004.2519569396973, "n_selected_site": 9, "local_count": 12, "common_count": 68}, "Ours": {"max_delay": 0.13157962604771117, "cost": 0.0, "target_value": 131.57962604771117, "running_time": 13530.850648880005, "local_count": 34, "common_count": 46}}, "0.1": {"Nearest": {"max_delay": 0.14543938232737136, "cost": 132.3, "target_value": 158.66938232737135, "running_time": 1.0006427764892578, "local_count": 80, "common_count": 0}, "M-Greedy": {"max_delay": 0.13369252443180252, "cost": 115.125, "target_value": 145.2050244318025, "running_time": 1206.1707973480225, "n_selected_site": 10, "local_count": 32, "common_count": 48}, "M-Greedy-V2(Tx+Tp+Tq)": {"max_delay": 0.13369252443180252, "cost": 116.625, "target_value": 145.35502443180252, "running_time": 1595.905065536499, "n_selected_site": 7, "local_count": 12, "common_count": 68}, "Ours": {"max_delay": 0.13305983358688672, "cost": 113.475, "target_value": 144.40733358688672, "running_time": 19435.872793197632, "local_count": 46, "common_count": 34}}, "0.25": {"Nearest": {"max_delay": 0.14974196822788938, "cost": 117.2, "target_value": 179.04196822788938, "running_time": 1.0006427764892578, "local_count": 80, "common_count": 0}, "M-Greedy": {"max_delay": 0.13673671130236686, "cost": 95.2, "target_value": 160.53671130236688, "running_time": 1372.6494312286377, "n_selected_site": 10, "local_count": 32, "common_count": 48}, "M-Greedy-V2(Tx+Tp+Tq)": {"max_delay": 0.13673671130236686, "cost": 97.8, "target_value": 161.18671130236686, "running_time": 2000.154733657837, "n_selected_site": 8, "local_count": 12, "common_count": 68}, "Ours": {"max_delay": 0.13259855187665226, "cost": 96.475, "target_value": 156.71730187665227, "running_time": 19977.777004241943, "local_count": 33, "common_count": 47}}, "0.5": {"Nearest": {"max_delay": 0.1563800437824564, "cost": 108.075, "target_value": 210.4175437824564, "running_time": 1.5723705291748047, "local_count": 80, "common_count": 0}, "M-Greedy": {"max_delay": 0.14214284678521705, "cost": 92.275, "target_value": 188.28034678521703, "running_time": 1388.275146484375, "n_selected_site": 10, "local_count": 32, "common_count": 48}, "M-Greedy-V2(Tx+Tp+Tq)": {"max_delay": 0.14214284678521705, "cost": 96.2, "target_value": 190.24284678521704, "running_time": 2016.9317722320557, "n_selected_site": 8, "local_count": 12, "common_count": 68}, "Ours": {"max_delay": 0.13673671130236686, "cost": 88.25, "target_value": 180.86171130236687, "running_time": 19933.881521224976, "local_count": 52, "common_count": 28}}, "0.75": {"Nearest": {"max_delay": 0.1563800437824564, "cost": 102.575, "target_value": 233.3112937824564, "running_time": 1.001119613647461, "local_count": 80, "common_count": 0}, "M-Greedy": {"max_delay": 0.14214284678521705, "cost": 90.525, "target_value": 210.03659678521706, "running_time": 1370.373249053955, "n_selected_site": 10, "local_count": 32, "common_count": 48}, "M-Greedy-V2(Tx+Tp+Tq)": {"max_delay": 0.14214284678521705, "cost": 93.4, "target_value": 212.19284678521706, "running_time": 1967.0751094818115, "n_selected_site": 8, "local_count": 12, "common_count": 68}, "Ours": {"max_delay": 0.13865799969400544, "cost": 83.475, "target_value": 201.26424969400543, "running_time": 17825.583696365356, "local_count": 54, "common_count": 26}}}, "sim1": {"simulation_id": 1, "user_seed": 458674558, "0": {"Nearest": {"max_delay": 0.13451612903225807, "cost": 0.0, "target_value": 134.51612903225808, "running_time": 0.0, "local_count": 80, "common_count": 0}, "M-Greedy": {"max_delay": 0.13475485661424608, "cost": 0.0, "target_value": 134.75485661424608, "running_time": 940.9048557281494, "n_selected_site": 7, "local_count": 30, "common_count": 50}, "M-Greedy-V2(Tx+Tp+Tq)": {"max_delay": 0.12340957966764418, "cost": 0.0, "target_value": 123.40957966764418, "running_time": 2609.0826988220215, "n_selected_site": 5, "local_count": 6, "common_count": 74}, "Ours": {"max_delay": 0.12256327985739751, "cost": 0.0, "target_value": 122.56327985739752, "running_time": 14819.529294967651, "local_count": 23, "common_count": 57}}, "0.1": {"Nearest": {"max_delay": 0.13571505632656916, "cost": 125.725, "target_value": 148.28755632656916, "running_time": 1.0004043579101562, "local_count": 80, "common_count": 0}, "M-Greedy": {"max_delay": 0.1370397833156636, "cost": 118.875, "target_value": 148.9272833156636, "running_time": 937.3295307159424, "n_selected_site": 7, "local_count": 30, "common_count": 50}, "M-Greedy-V2(Tx+Tp+Tq)": {"max_delay": 0.12545119412277367, "cost": 111.625, "target_value": 136.61369412277367, "running_time": 1595.975637435913, "n_selected_site": 5, "local_count": 6, "common_count": 74}, "Ours": {"max_delay": 0.12384568979817137, "cost": 104.475, "target_value": 134.29318979817137, "running_time": 18283.353090286255, "local_count": 43, "common_count": 37}}, "0.25": {"Nearest": {"max_delay": 0.1377544624770507, "cost": 112.125, "target_value": 165.7857124770507, "running_time": 2.0017623901367188, "local_count": 80, "common_count": 0}, "M-Greedy": {"max_delay": 0.13913570143855603, "cost": 103.125, "target_value": 164.91695143855603, "running_time": 936.9330406188965, "n_selected_site": 7, "local_count": 30, "common_count": 50}, "M-Greedy-V2(Tx+Tp+Tq)": {"max_delay": 0.1274906002732552, "cost": 94.45, "target_value": 151.10310027325522, "running_time": 1333.0838680267334, "n_selected_site": 5, "local_count": 6, "common_count": 74}, "Ours": {"max_delay": 0.12475725054038228, "cost": 89.075, "target_value": 147.02600054038228, "running_time": 18062.679529190063, "local_count": 35, "common_count": 45}}, "0.5": {"Nearest": {"max_delay": 0.14107585372947642, "cost": 99.375, "target_value": 190.76335372947642, "running_time": 1.001119613647461, "local_count": 80, "common_count": 0}, "M-Greedy": {"max_delay": 0.14107585372947642, "cost": 98.05, "target_value": 190.10085372947643, "running_time": 948.0712413787842, "n_selected_site": 7, "local_count": 30, "common_count": 50}, "M-Greedy-V2(Tx+Tp+Tq)": {"max_delay": 0.1274906002732552, "cost": 91.35, "target_value": 173.16560027325522, "running_time": 1486.3646030426025, "n_selected_site": 6, "local_count": 6, "common_count": 74}, "Ours": {"max_delay": 0.1274906002732552, "cost": 81.775, "target_value": 168.3781002732552, "running_time": 17360.0914478302, "local_count": 44, "common_count": 36}}, "0.75": {"Nearest": {"max_delay": 0.14944225055398866, "cost": 95.3, "target_value": 220.91725055398865, "running_time": 1.0008811950683594, "local_count": 80, "common_count": 0}, "M-Greedy": {"max_delay": 0.14886675197849009, "cost": 85.125, "target_value": 212.71050197849007, "running_time": 952.8882503509521, "n_selected_site": 7, "local_count": 30, "common_count": 50}, "M-Greedy-V2(Tx+Tp+Tq)": {"max_delay": 0.1345342457750161, "cost": 78.525, "target_value": 193.42799577501611, "running_time": 1286.8452072143555, "n_selected_site": 5, "local_count": 6, "common_count": 74}, "Ours": {"max_delay": 0.1274906002732552, "cost": 81.25, "target_value": 188.4281002732552, "running_time": 18349.359273910522, "local_count": 44, "common_count": 36}}}, "sim2": {"simulation_id": 2, "user_seed": 241753170, "0": {"Nearest": {"max_delay": 0.13920553359683796, "cost": 0.0, "target_value": 139.20553359683797, "running_time": 0.0, "local_count": 80, "common_count": 0}, "M-Greedy": {"max_delay": 0.13920553359683796, "cost": 0.0, "target_value": 139.20553359683797, "running_time": 1419.5010662078857, "n_selected_site": 10, "local_count": 38, "common_count": 42}, "M-Greedy-V2(Tx+Tp+Tq)": {"max_delay": 0.13100386847195356, "cost": 0.0, "target_value": 131.00386847195355, "running_time": 2937.002658843994, "n_selected_site": 7, "local_count": 18, "common_count": 62}, "Ours": {"max_delay": 0.13100386847195356, "cost": 0.0, "target_value": 131.00386847195355, "running_time": 14888.260126113892, "local_count": 35, "common_count": 45}}, "0.1": {"Nearest": {"max_delay": 0.14120679840151695, "cost": 128.175, "target_value": 154.02429840151694, "running_time": 12.009859085083008, "local_count": 80, "common_count": 0}, "M-Greedy": {"max_delay": 0.14120679840151695, "cost": 122.65, "target_value": 153.47179840151693, "running_time": 1249.1543292999268, "n_selected_site": 10, "local_count": 38, "common_count": 42}, "M-Greedy-V2(Tx+Tp+Tq)": {"max_delay": 0.13245575474436277, "cost": 110.7, "target_value": 143.52575474436276, "running_time": 1711.7362022399902, "n_selected_site": 7, "local_count": 18, "common_count": 62}, "Ours": {"max_delay": 0.13194908823979215, "cost": 106.65, "target_value": 142.61408823979215, "running_time": 18434.874773025513, "local_count": 47, "common_count": 33}}, "0.25": {"Nearest": {"max_delay": 0.14647530727233696, "cost": 115.55, "target_value": 175.36280727233694, "running_time": 1.0001659393310547, "local_count": 80, "common_count": 0}, "M-Greedy": {"max_delay": 0.14647530727233696, "cost": 108.5, "target_value": 173.60030727233695, "running_time": 1234.144687652588, "n_selected_site": 10, "local_count": 38, "common_count": 42}, "M-Greedy-V2(Tx+Tp+Tq)": {"max_delay": 0.1374252335434136, "cost": 100.0, "target_value": 162.4252335434136, "running_time": 1570.352554321289, "n_selected_site": 5, "local_count": 0, "common_count": 80}, "Ours": {"max_delay": 0.1325730328033366, "cost": 91.425, "target_value": 155.42928280333658, "running_time": 18556.429386138916, "local_count": 44, "common_count": 36}}, "0.5": {"Nearest": {"max_delay": 0.14647530727233696, "cost": 103.875, "target_value": 198.41280727233695, "running_time": 2.0020008087158203, "local_count": 80, "common_count": 0}, "M-Greedy": {"max_delay": 0.14647530727233696, "cost": 100.775, "target_value": 196.86280727233697, "running_time": 1294.5449352264404, "n_selected_site": 10, "local_count": 38, "common_count": 42}, "M-Greedy-V2(Tx+Tp+Tq)": {"max_delay": 0.13781663456171472, "cost": 90.325, "target_value": 182.97913456171472, "running_time": 1681.6353797912598, "n_selected_site": 7, "local_count": 16, "common_count": 64}, "Ours": {"max_delay": 0.13634774455596316, "cost": 84.075, "target_value": 178.38524455596314, "running_time": 18216.5207862854, "local_count": 56, "common_count": 24}}, "0.75": {"Nearest": {"max_delay": 0.15592293680686864, "cost": 99.525, "target_value": 230.56668680686866, "running_time": 1.0006427764892578, "local_count": 80, "common_count": 0}, "M-Greedy": {"max_delay": 0.15592293680686864, "cost": 98.225, "target_value": 229.59168680686864, "running_time": 1239.412784576416, "n_selected_site": 10, "local_count": 38, "common_count": 42}, "M-Greedy-V2(Tx+Tp+Tq)": {"max_delay": 0.1379751651439608, "cost": 92.2, "target_value": 207.1251651439608, "running_time": 1491.595983505249, "n_selected_site": 6, "local_count": 10, "common_count": 70}, "Ours": {"max_delay": 0.13781663456171472, "cost": 82.525, "target_value": 199.71038456171473, "running_time": 18892.284631729126, "local_count": 62, "common_count": 18}}}, "sim3": {"simulation_id": 3, "user_seed": 444605712, "0": {"Nearest": {"max_delay": 0.14520553359683797, "cost": 0.0, "target_value": 145.20553359683797, "running_time": 0.0, "local_count": 80, "common_count": 0}, "M-Greedy": {"max_delay": 0.13266622778143516, "cost": 0.0, "target_value": 132.66622778143517, "running_time": 1253.188133239746, "n_selected_site": 10, "local_count": 20, "common_count": 60}, "M-Greedy-V2(Tx+Tp+Tq)": {"max_delay": 0.13266622778143516, "cost": 0.0, "target_value": 132.66622778143517, "running_time": 3121.755838394165, "n_selected_site": 8, "local_count": 20, "common_count": 60}, "Ours": {"max_delay": 0.13157962604771117, "cost": 0.0, "target_value": 131.57962604771117, "running_time": 14728.681087493896, "local_count": 59, "common_count": 21}}, "0.1": {"Nearest": {"max_delay": 0.1465918882155946, "cost": 124.125, "target_value": 159.0043882155946, "running_time": 1.001119613647461, "local_count": 80, "common_count": 0}, "M-Greedy": {"max_delay": 0.13459875760939002, "cost": 111.3, "target_value": 145.72875760939002, "running_time": 1248.3654022216797, "n_selected_site": 10, "local_count": 20, "common_count": 60}, "M-Greedy-V2(Tx+Tp+Tq)": {"max_delay": 0.13376712550294245, "cost": 112.375, "target_value": 145.00462550294247, "running_time": 2077.9919624328613, "n_selected_site": 9, "local_count": 20, "common_count": 60}, "Ours": {"max_delay": 0.13230799112455344, "cost": 101.675, "target_value": 142.47549112455343, "running_time": 18401.293992996216, "local_count": 41, "common_count": 39}}, "0.25": {"Nearest": {"max_delay": 0.1509134792163338, "cost": 110.225, "target_value": 178.4697292163338, "running_time": 1.0008811950683594, "local_count": 80, "common_count": 0}, "M-Greedy": {"max_delay": 0.13861738196867907, "cost": 93.725, "target_value": 162.04863196867908, "running_time": 1246.1438179016113, "n_selected_site": 10, "local_count": 20, "common_count": 60}, "M-Greedy-V2(Tx+Tp+Tq)": {"max_delay": 0.13734769686447565, "cost": 94.15, "target_value": 160.88519686447563, "running_time": 2053.34734916687, "n_selected_site": 9, "local_count": 20, "common_count": 60}, "Ours": {"max_delay": 0.13230799112455344, "cost": 89.15, "target_value": 154.59549112455343, "running_time": 17938.286304473877, "local_count": 44, "common_count": 36}}, "0.5": {"Nearest": {"max_delay": 0.15697800120598404, "cost": 98.525, "target_value": 206.24050120598406, "running_time": 2.001523971557617, "local_count": 80, "common_count": 0}, "M-Greedy": {"max_delay": 0.14006258640024266, "cost": 90.375, "target_value": 185.25008640024265, "running_time": 1250.7801055908203, "n_selected_site": 10, "local_count": 20, "common_count": 60}, "M-Greedy-V2(Tx+Tp+Tq)": {"max_delay": 0.14006258640024266, "cost": 89.975, "target_value": 185.05008640024266, "running_time": 1485.1224422454834, "n_selected_site": 6, "local_count": 20, "common_count": 60}, "Ours": {"max_delay": 0.13861738196867907, "cost": 79.575, "target_value": 178.40488196867906, "running_time": 18215.538263320923, "local_count": 48, "common_count": 32}}, "0.75": {"Nearest": {"max_delay": 0.15697800120598404, "cost": 95.625, "target_value": 228.69675120598404, "running_time": 1.0004043579101562, "local_count": 80, "common_count": 0}, "M-Greedy": {"max_delay": 0.14566102747043996, "cost": 77.225, "target_value": 203.57977747043995, "running_time": 1268.587589263916, "n_selected_site": 10, "local_count": 20, "common_count": 60}, "M-Greedy-V2(Tx+Tp+Tq)": {"max_delay": 0.14277982706320674, "cost": 80.85, "target_value": 203.41732706320673, "running_time": 1810.7542991638184, "n_selected_site": 8, "local_count": 12, "common_count": 68}, "Ours": {"max_delay": 0.14006258640024266, "cost": 75.65, "target_value": 196.80008640024266, "running_time": 17866.512537002563, "local_count": 55, "common_count": 25}}}}, "70": {"sim0": {"simulation_id": 0, "user_seed": 341980505, "0": {"Nearest": {"max_delay": 0.14020553359683796, "cost": 0.0, "target_value": 140.20553359683797, "running_time": 0.0, "local_count": 140, "common_count": 0}, "M-Greedy": {"max_delay": 0.14020553359683796, "cost": 0.0, "target_value": 140.20553359683797, "running_time": 4546.076536178589, "n_selected_site": 13, "local_count": 80, "common_count": 60}, "M-Greedy-V2(Tx+Tp+Tq)": {"max_delay": 0.13103030303030302, "cost": 0.0, "target_value": 131.03030303030303, "running_time": 9069.162130355835, "n_selected_site": 10, "local_count": 28, "common_count": 112}, "Ours": {"max_delay": 0.13103030303030302, "cost": 0.0, "target_value": 131.03030303030303, "running_time": 40984.82441902161, "local_count": 96, "common_count": 44}}, "0.1": {"Nearest": {"max_delay": 0.14281501448111855, "cost": 200.4142857142857, "target_value": 162.85644305254712, "running_time": 3.0024051666259766, "local_count": 140, "common_count": 0}, "M-Greedy": {"max_delay": 0.14281501448111855, "cost": 170.28571428571428, "target_value": 159.84358590968998, "running_time": 4564.616441726685, "n_selected_site": 13, "local_count": 80, "common_count": 60}, "M-Greedy-V2(Tx+Tp+Tq)": {"max_delay": 0.13243478077428117, "cost": 161.5857142857143, "target_value": 148.5933522028526, "running_time": 5346.047878265381, "n_selected_site": 7, "local_count": 28, "common_count": 112}, "Ours": {"max_delay": 0.1317089525336714, "cost": 155.87142857142857, "target_value": 147.29609539081426, "running_time": 49978.66439819336, "local_count": 62, "common_count": 78}}, "0.25": {"Nearest": {"max_delay": 0.14705633314912797, "cost": 182.35714285714286, "target_value": 192.6456188634137, "running_time": 3.0028820037841797, "local_count": 140, "common_count": 0}, "M-Greedy": {"max_delay": 0.14705633314912797, "cost": 157.84285714285716, "target_value": 186.51704743484225, "running_time": 5013.888359069824, "n_selected_site": 13, "local_count": 80, "common_count": 60}, "M-Greedy-V2(Tx+Tp+Tq)": {"max_delay": 0.1356942971625678, "cost": 150.8, "target_value": 173.3942971625678, "running_time": 5175.742864608765, "n_selected_site": 7, "local_count": 28, "common_count": 112}, "Ours": {"max_delay": 0.13243478077428117, "cost": 139.31428571428572, "target_value": 167.2633522028526, "running_time": 48098.116397857666, "local_count": 70, "common_count": 70}}, "0.5": {"Nearest": {"max_delay": 0.15478679684576713, "cost": 171.0142857142857, "target_value": 240.29393970291, "running_time": 3.002166748046875, "local_count": 140, "common_count": 0}, "M-Greedy": {"max_delay": 0.15478679684576713, "cost": 142.8, "target_value": 226.18679684576713, "running_time": 4580.701589584351, "n_selected_site": 13, "local_count": 80, "common_count": 60}, "M-Greedy-V2(Tx+Tp+Tq)": {"max_delay": 0.14132168541867698, "cost": 136.1, "target_value": 209.37168541867698, "running_time": 6655.166387557983, "n_selected_site": 10, "local_count": 28, "common_count": 112}, "Ours": {"max_delay": 0.1356942971625678, "cost": 130.67142857142858, "target_value": 201.0300114482821, "running_time": 47550.97699165344, "local_count": 78, "common_count": 62}}, "0.75": {"Nearest": {"max_delay": 0.15478679684576713, "cost": 164.22857142857143, "target_value": 277.9582254171957, "running_time": 2.0017623901367188, "local_count": 140, "common_count": 0}, "M-Greedy": {"max_delay": 0.15478679684576713, "cost": 140.55714285714285, "target_value": 260.2046539886243, "running_time": 4685.703277587891, "n_selected_site": 13, "local_count": 80, "common_count": 60}, "M-Greedy-V2(Tx+Tp+Tq)": {"max_delay": 0.14149018358717516, "cost": 132.4142857142857, "target_value": 240.80089787288944, "running_time": 4343.690395355225, "n_selected_site": 6, "local_count": 28, "common_count": 112}, "Ours": {"max_delay": 0.14149018358717516, "cost": 124.14285714285714, "target_value": 234.597326444318, "running_time": 48021.00992202759, "local_count": 81, "common_count": 59}}}, "sim1": {"simulation_id": 1, "user_seed": 602966712, "0": {"Nearest": {"max_delay": 0.14520553359683797, "cost": 0.0, "target_value": 145.20553359683797, "running_time": 0.0, "local_count": 140, "common_count": 0}, "M-Greedy": {"max_delay": 0.13266622778143516, "cost": 0.0, "target_value": 132.66622778143517, "running_time": 3721.226215362549, "n_selected_site": 10, "local_count": 62, "common_count": 78}, "M-Greedy-V2(Tx+Tp+Tq)": {"max_delay": 0.13266622778143516, "cost": 0.0, "target_value": 132.66622778143517, "running_time": 7040.568828582764, "n_selected_site": 6, "local_count": 30, "common_count": 110}, "Ours": {"max_delay": 0.13157962604771117, "cost": 0.0, "target_value": 131.57962604771117, "running_time": 40314.10503387451, "local_count": 58, "common_count": 82}}, "0.1": {"Nearest": {"max_delay": 0.1487497556305466, "cost": 186.5, "target_value": 167.3997556305466, "running_time": 3.0024051666259766, "local_count": 140, "common_count": 0}, "M-Greedy": {"max_delay": 0.13480482873860045, "cost": 153.57142857142858, "target_value": 150.1619715957433, "running_time": 3760.33878326416, "n_selected_site": 10, "local_count": 62, "common_count": 78}, "M-Greedy-V2(Tx+Tp+Tq)": {"max_delay": 0.13480482873860045, "cost": 153.67142857142858, "target_value": 150.1719715957433, "running_time": 4576.010704040527, "n_selected_site": 6, "local_count": 30, "common_count": 110}, "Ours": {"max_delay": 0.13230857702075058, "cost": 148.12857142857143, "target_value": 147.12143416360774, "running_time": 49269.72723007202, "local_count": 61, "common_count": 79}}, "0.25": {"Nearest": {"max_delay": 0.1514309804204823, "cost": 169.11428571428573, "target_value": 193.70955184905375, "running_time": 3.002166748046875, "local_count": 140, "common_count": 0}, "M-Greedy": {"max_delay": 0.13784592524844114, "cost": 133.5857142857143, "target_value": 171.24235381986972, "running_time": 3732.5847148895264, "n_selected_site": 10, "local_count": 62, "common_count": 78}, "M-Greedy-V2(Tx+Tp+Tq)": {"max_delay": 0.14400255534200274, "cost": 143.22857142857143, "target_value": 179.80969819914557, "running_time": 5470.317840576172, "n_selected_site": 8, "local_count": 8, "common_count": 132}, "Ours": {"max_delay": 0.13321781266510777, "cost": 133.21428571428572, "target_value": 166.52138409367922, "running_time": 50517.821073532104, "local_count": 84, "common_count": 56}}, "0.5": {"Nearest": {"max_delay": 0.15812303404285383, "cost": 157.95714285714286, "target_value": 237.10160547142524, "running_time": 2.001047134399414, "local_count": 140, "common_count": 0}, "M-Greedy": {"max_delay": 0.14192840573902177, "cost": 130.9857142857143, "target_value": 207.42126288187893, "running_time": 3763.3368968963623, "n_selected_site": 10, "local_count": 62, "common_count": 78}, "M-Greedy-V2(Tx+Tp+Tq)": {"max_delay": 0.13976848713937284, "cost": 134.45714285714286, "target_value": 206.99705856794426, "running_time": 4889.98818397522, "n_selected_site": 7, "local_count": 30, "common_count": 110}, "Ours": {"max_delay": 0.13639524826584926, "cost": 124.88571428571429, "target_value": 198.8381054087064, "running_time": 47417.33407974243, "local_count": 92, "common_count": 48}}, "0.75": {"Nearest": {"max_delay": 0.15812303404285383, "cost": 151.68571428571428, "target_value": 271.8873197571395, "running_time": 2.0020008087158203, "local_count": 140, "common_count": 0}, "M-Greedy": {"max_delay": 0.14268481354699183, "cost": 128.47142857142856, "target_value": 239.03838497556328, "running_time": 3721.881628036499, "n_selected_site": 10, "local_count": 62, "common_count": 78}, "M-Greedy-V2(Tx+Tp+Tq)": {"max_delay": 0.14268481354699183, "cost": 132.75714285714287, "target_value": 242.252670689849, "running_time": 5064.980745315552, "n_selected_site": 7, "local_count": 30, "common_count": 110}, "Ours": {"max_delay": 0.13784592524844114, "cost": 122.4, "target_value": 229.64592524844116, "running_time": 47199.31697845459, "local_count": 105, "common_count": 35}}}, "sim2": {"simulation_id": 2, "user_seed": 727611568, "0": {"Nearest": {"max_delay": 0.14320553359683796, "cost": 0.0, "target_value": 143.20553359683797, "running_time": 1.0008811950683594, "local_count": 140, "common_count": 0}, "M-Greedy": {"max_delay": 0.13266622778143516, "cost": 0.0, "target_value": 132.66622778143517, "running_time": 3840.2299880981445, "n_selected_site": 10, "local_count": 44, "common_count": 96}, "M-Greedy-V2(Tx+Tp+Tq)": {"max_delay": 0.13103030303030302, "cost": 0.0, "target_value": 131.03030303030303, "running_time": 9577.2225856781, "n_selected_site": 11, "local_count": 24, "common_count": 116}, "Ours": {"max_delay": 0.13103030303030302, "cost": 0.0, "target_value": 131.03030303030303, "running_time": 44349.55310821533, "local_count": 62, "common_count": 78}}, "0.1": {"Nearest": {"max_delay": 0.14528661118540026, "cost": 186.05714285714285, "target_value": 163.89232547111453, "running_time": 2.0017623901367188, "local_count": 140, "common_count": 0}, "M-Greedy": {"max_delay": 0.13380757275596783, "cost": 154.47142857142856, "target_value": 149.2547156131107, "running_time": 3778.639793395996, "n_selected_site": 10, "local_count": 44, "common_count": 96}, "M-Greedy-V2(Tx+Tp+Tq)": {"max_delay": 0.13247773091967144, "cost": 154.04285714285714, "target_value": 147.88201663395716, "running_time": 5878.626585006714, "n_selected_site": 8, "local_count": 24, "common_count": 116}, "Ours": {"max_delay": 0.13170757425577842, "cost": 146.84285714285716, "target_value": 146.39185997006413, "running_time": 51498.17728996277, "local_count": 50, "common_count": 90}}, "0.25": {"Nearest": {"max_delay": 0.1490314864464089, "cost": 170.31428571428572, "target_value": 191.61005787498033, "running_time": 3.002166748046875, "local_count": 140, "common_count": 0}, "M-Greedy": {"max_delay": 0.13791128841750594, "cost": 135.21428571428572, "target_value": 171.7148598460774, "running_time": 4201.411485671997, "n_selected_site": 10, "local_count": 44, "common_count": 96}, "M-Greedy-V2(Tx+Tp+Tq)": {"max_delay": 0.13590612867554636, "cost": 134.82857142857142, "target_value": 169.61327153268923, "running_time": 5168.611526489258, "n_selected_site": 7, "local_count": 24, "common_count": 116}, "Ours": {"max_delay": 0.13247773091967144, "cost": 131.9142857142857, "target_value": 165.45630234824287, "running_time": 49380.40494918823, "local_count": 70, "common_count": 70}}, "0.5": {"Nearest": {"max_delay": 0.1554132773748376, "cost": 157.3, "target_value": 234.0632773748376, "running_time": 3.0028820037841797, "local_count": 140, "common_count": 0}, "M-Greedy": {"max_delay": 0.14124141883117147, "cost": 131.4, "target_value": 206.94141883117146, "running_time": 3765.1495933532715, "n_selected_site": 10, "local_count": 44, "common_count": 96}, "M-Greedy-V2(Tx+Tp+Tq)": {"max_delay": 0.13824141883117147, "cost": 133.75714285714287, "target_value": 205.1199902597429, "running_time": 4921.347618103027, "n_selected_site": 7, "local_count": 24, "common_count": 116}, "Ours": {"max_delay": 0.13590612867554636, "cost": 125.08571428571429, "target_value": 198.44898581840351, "running_time": 46727.66590118408, "local_count": 80, "common_count": 60}}, "0.75": {"Nearest": {"max_delay": 0.1554132773748376, "cost": 153.61428571428573, "target_value": 270.6239916605519, "running_time": 2.001047134399414, "local_count": 140, "common_count": 0}, "M-Greedy": {"max_delay": 0.14240639119022, "cost": 130.68571428571428, "target_value": 240.4206769045057, "running_time": 3735.3968620300293, "n_selected_site": 10, "local_count": 44, "common_count": 96}, "M-Greedy-V2(Tx+Tp+Tq)": {"max_delay": 0.14223789302172182, "cost": 133.61428571428573, "target_value": 242.4486073074361, "running_time": 7275.896072387695, "n_selected_site": 11, "local_count": 24, "common_count": 116}, "Ours": {"max_delay": 0.14124141883117147, "cost": 119.02857142857142, "target_value": 230.51284740260004, "running_time": 50483.45470428467, "local_count": 88, "common_count": 52}}}, "sim3": {"simulation_id": 3, "user_seed": 777731635, "0": {"Nearest": {"max_delay": 0.14520553359683797, "cost": 0.0, "target_value": 145.20553359683797, "running_time": 0.0, "local_count": 140, "common_count": 0}, "M-Greedy": {"max_delay": 0.13266622778143516, "cost": 0.0, "target_value": 132.66622778143517, "running_time": 3720.3118801116943, "n_selected_site": 10, "local_count": 38, "common_count": 102}, "M-Greedy-V2(Tx+Tp+Tq)": {"max_delay": 0.13266622778143516, "cost": 0.0, "target_value": 132.66622778143517, "running_time": 7002.925872802734, "n_selected_site": 6, "local_count": 28, "common_count": 112}, "Ours": {"max_delay": 0.13157962604771117, "cost": 0.0, "target_value": 131.57962604771117, "running_time": 41248.65794181824, "local_count": 66, "common_count": 74}}, "0.1": {"Nearest": {"max_delay": 0.14777365164458273, "cost": 190.6, "target_value": 166.83365164458272, "running_time": 2.0017623901367188, "local_count": 140, "common_count": 0}, "M-Greedy": {"max_delay": 0.1339896590300403, "cost": 155.0, "target_value": 149.4896590300403, "running_time": 3787.8360748291016, "n_selected_site": 10, "local_count": 38, "common_count": 102}, "M-Greedy-V2(Tx+Tp+Tq)": {"max_delay": 0.1339896590300403, "cost": 152.72857142857143, "target_value": 149.26251617289742, "running_time": 4456.380367279053, "n_selected_site": 6, "local_count": 28, "common_count": 112}, "Ours": {"max_delay": 0.132385981500329, "cost": 148.15714285714284, "target_value": 147.20169578604327, "running_time": 48859.58003997803, "local_count": 53, "common_count": 87}}, "0.25": {"Nearest": {"max_delay": 0.1506214566109585, "cost": 172.78571428571428, "target_value": 193.81788518238704, "running_time": 3.0028820037841797, "local_count": 140, "common_count": 0}, "M-Greedy": {"max_delay": 0.13784592524844114, "cost": 136.0857142857143, "target_value": 171.86735381986972, "running_time": 3712.7556800842285, "n_selected_site": 10, "local_count": 38, "common_count": 102}, "M-Greedy-V2(Tx+Tp+Tq)": {"max_delay": 0.1371274614983472, "cost": 139.0, "target_value": 171.8774614983472, "running_time": 5555.709600448608, "n_selected_site": 8, "local_count": 28, "common_count": 112}, "Ours": {"max_delay": 0.13329521714468617, "cost": 132.45714285714286, "target_value": 166.4095028589719, "running_time": 49727.72026062012, "local_count": 72, "common_count": 68}}, "0.5": {"Nearest": {"max_delay": 0.16062929970701423, "cost": 161.81428571428572, "target_value": 241.53644256415708, "running_time": 2.0020008087158203, "local_count": 140, "common_count": 0}, "M-Greedy": {"max_delay": 0.14192840573902177, "cost": 133.0857142857143, "target_value": 208.4712628818789, "running_time": 3861.8502616882324, "n_selected_site": 10, "local_count": 38, "common_count": 102}, "M-Greedy-V2(Tx+Tp+Tq)": {"max_delay": 0.14044325097203142, "cost": 133.28571428571428, "target_value": 207.08610811488856, "running_time": 5070.908069610596, "n_selected_site": 7, "local_count": 28, "common_count": 112}, "Ours": {"max_delay": 0.13549109786198357, "cost": 125.41428571428571, "target_value": 198.19824071912643, "running_time": 49012.91728019714, "local_count": 81, "common_count": 59}}, "0.75": {"Nearest": {"max_delay": 0.16062929970701423, "cost": 154.35714285714286, "target_value": 276.3971568498714, "running_time": 2.001523971557617, "local_count": 140, "common_count": 0}, "M-Greedy": {"max_delay": 0.14485283522720865, "cost": 131.3, "target_value": 243.32783522720865, "running_time": 3870.6469535827637, "n_selected_site": 10, "local_count": 38, "common_count": 102}, "M-Greedy-V2(Tx+Tp+Tq)": {"max_delay": 0.14485283522720865, "cost": 131.4, "target_value": 243.40283522720867, "running_time": 5189.23807144165, "n_selected_site": 7, "local_count": 28, "common_count": 112}, "Ours": {"max_delay": 0.13892840573902177, "cost": 121.82857142857142, "target_value": 230.29983431045034, "running_time": 46490.2606010437, "local_count": 93, "common_count": 47}}}}, "100": {"sim0": {"simulation_id": 0, "user_seed": 387043710, "0": {"Nearest": {"max_delay": 0.14520553359683797, "cost": 0.0, "target_value": 145.20553359683797, "running_time": 1.0006427764892578, "local_count": 200, "common_count": 0}, "M-Greedy": {"max_delay": 0.13266622778143516, "cost": 0.0, "target_value": 132.66622778143517, "running_time": 7732.532978057861, "n_selected_site": 10, "local_count": 88, "common_count": 112}, "M-Greedy-V2(Tx+Tp+Tq)": {"max_delay": 0.13266622778143516, "cost": 0.0, "target_value": 132.66622778143517, "running_time": 17635.00165939331, "n_selected_site": 10, "local_count": 52, "common_count": 148}, "Ours": {"max_delay": 0.13266622778143516, "cost": 0.0, "target_value": 132.66622778143517, "running_time": 81348.41823577881, "local_count": 86, "common_count": 114}}, "0.1": {"Nearest": {"max_delay": 0.14746658008927496, "cost": 256.65, "target_value": 173.13158008927496, "running_time": 4.003047943115234, "local_count": 200, "common_count": 0}, "M-Greedy": {"max_delay": 0.13421964436850936, "cost": 211.4, "target_value": 155.35964436850935, "running_time": 7977.849960327148, "n_selected_site": 10, "local_count": 88, "common_count": 112}, "M-Greedy-V2(Tx+Tp+Tq)": {"max_delay": 0.13421964436850936, "cost": 210.72, "target_value": 155.29164436850937, "running_time": 9677.565097808838, "n_selected_site": 6, "local_count": 52, "common_count": 148}, "Ours": {"max_delay": 0.13313715744582172, "cost": 198.25, "target_value": 152.96215744582173, "running_time": 90356.11987113953, "local_count": 109, "common_count": 91}}, "0.25": {"Nearest": {"max_delay": 0.15149947521286228, "cost": 239.51, "target_value": 211.37697521286228, "running_time": 4.0035247802734375, "local_count": 200, "common_count": 0}, "M-Greedy": {"max_delay": 0.13844564285353841, "cost": 191.77, "target_value": 186.3881428535384, "running_time": 7741.837501525879, "n_selected_site": 10, "local_count": 88, "common_count": 112}, "M-Greedy-V2(Tx+Tp+Tq)": {"max_delay": 0.13844564285353841, "cost": 191.83, "target_value": 186.4031428535384, "running_time": 11488.584280014038, "n_selected_site": 8, "local_count": 52, "common_count": 148}, "Ours": {"max_delay": 0.13421964436850936, "cost": 183.12, "target_value": 179.99964436850937, "running_time": 47804.494857788086, "local_count": 124, "common_count": 76}}, "0.5": {"Nearest": {"max_delay": 0.1559597952234316, "cost": 224.83, "target_value": 268.3747952234316, "running_time": 4.004001617431641, "local_count": 200, "common_count": 0}, "M-Greedy": {"max_delay": 0.1417249981762165, "cost": 178.04, "target_value": 230.74499817621648, "running_time": 7564.448118209839, "n_selected_site": 10, "local_count": 88, "common_count": 112}, "M-Greedy-V2(Tx+Tp+Tq)": {"max_delay": 0.1417249981762165, "cost": 181.54, "target_value": 232.49499817621648, "running_time": 11303.985118865967, "n_selected_site": 8, "local_count": 52, "common_count": 148}, "Ours": {"max_delay": 0.1365903641211517, "cost": 172.36, "target_value": 222.7703641211517, "running_time": 95034.5847606659, "local_count": 124, "common_count": 76}}, "0.75": {"Nearest": {"max_delay": 0.1657546005863813, "cost": 219.8, "target_value": 330.60460058638137, "running_time": 4.002809524536133, "local_count": 200, "common_count": 0}, "M-Greedy": {"max_delay": 0.1417249981762165, "cost": 178.04, "target_value": 275.25499817621653, "running_time": 7564.032316207886, "n_selected_site": 10, "local_count": 88, "common_count": 112}, "M-Greedy-V2(Tx+Tp+Tq)": {"max_delay": 0.1417249981762165, "cost": 181.54, "target_value": 277.87999817621653, "running_time": 11569.912433624268, "n_selected_site": 8, "local_count": 52, "common_count": 148}, "Ours": {"max_delay": 0.1417249981762165, "cost": 166.0, "target_value": 266.2249981762165, "running_time": 92895.83253860474, "local_count": 140, "common_count": 60}}}, "sim1": {"simulation_id": 1, "user_seed": 466142599, "0": {"Nearest": {"max_delay": 0.13920553359683796, "cost": 0.0, "target_value": 139.20553359683797, "running_time": 0.0, "local_count": 200, "common_count": 0}, "M-Greedy": {"max_delay": 0.14375485661424608, "cost": 0.0, "target_value": 143.75485661424608, "running_time": 7783.766031265259, "n_selected_site": 10, "local_count": 74, "common_count": 126}, "M-Greedy-V2(Tx+Tp+Tq)": {"max_delay": 0.13266622778143516, "cost": 0.0, "target_value": 132.66622778143517, "running_time": 13114.094972610474, "n_selected_site": 6, "local_count": 52, "common_count": 148}, "Ours": {"max_delay": 0.13181992797118847, "cost": 0.0, "target_value": 131.81992797118846, "running_time": 89321.79999351501, "local_count": 85, "common_count": 115}}, "0.1": {"Nearest": {"max_delay": 0.1417906155433192, "cost": 239.94, "target_value": 165.7846155433192, "running_time": 4.003286361694336, "local_count": 200, "common_count": 0}, "M-Greedy": {"max_delay": 0.14717941794198147, "cost": 208.51, "target_value": 168.03041794198148, "running_time": 8505.301475524902, "n_selected_site": 10, "local_count": 74, "common_count": 126}, "M-Greedy-V2(Tx+Tp+Tq)": {"max_delay": 0.13464218321234767, "cost": 201.24, "target_value": 154.76618321234767, "running_time": 11795.909881591797, "n_selected_site": 8, "local_count": 52, "common_count": 148}, "Ours": {"max_delay": 0.13318843956441812, "cost": 192.01, "target_value": 152.3894395644181, "running_time": 96578.07159423828, "local_count": 94, "common_count": 106}}, "0.25": {"Nearest": {"max_delay": 0.14395841149652908, "cost": 224.54, "target_value": 200.09341149652906, "running_time": 3.005504608154297, "local_count": 200, "common_count": 0}, "M-Greedy": {"max_delay": 0.14934721389519134, "cost": 200.15, "target_value": 199.38471389519134, "running_time": 8116.824626922607, "n_selected_site": 10, "local_count": 74, "common_count": 126}, "M-Greedy-V2(Tx+Tp+Tq)": {"max_delay": 0.13845955895573558, "cost": 189.66, "target_value": 185.87455895573558, "running_time": 9155.002117156982, "n_selected_site": 6, "local_count": 52, "common_count": 148}, "Ours": {"max_delay": 0.13367585697186105, "cost": 176.41, "target_value": 177.77835697186103, "running_time": 78418.24769973755, "local_count": 118, "common_count": 82}}, "0.5": {"Nearest": {"max_delay": 0.15215804689466195, "cost": 210.18, "target_value": 257.2480468946619, "running_time": 3.002643585205078, "local_count": 200, "common_count": 0}, "M-Greedy": {"max_delay": 0.15623250132341676, "cost": 185.43, "target_value": 248.94750132341676, "running_time": 8598.793983459473, "n_selected_site": 10, "local_count": 74, "common_count": 126}, "M-Greedy-V2(Tx+Tp+Tq)": {"max_delay": 0.14348144717126374, "cost": 176.55, "target_value": 231.75644717126374, "running_time": 12311.57660484314, "n_selected_site": 8, "local_count": 52, "common_count": 148}, "Ours": {"max_delay": 0.1369646094607861, "cost": 165.74, "target_value": 219.83460946078608, "running_time": 105799.0951538086, "local_count": 120, "common_count": 80}}, "0.75": {"Nearest": {"max_delay": 0.15249585052665968, "cost": 204.28, "target_value": 305.7058505266597, "running_time": 4.003047943115234, "local_count": 200, "common_count": 0}, "M-Greedy": {"max_delay": 0.15623250132341676, "cost": 181.99, "target_value": 292.7250013234168, "running_time": 8492.0175075531, "n_selected_site": 10, "local_count": 74, "common_count": 126}, "M-Greedy-V2(Tx+Tp+Tq)": {"max_delay": 0.1447489410933605, "cost": 171.9, "target_value": 273.67394109336055, "running_time": 10343.63055229187, "n_selected_site": 6, "local_count": 52, "common_count": 148}, "Ours": {"max_delay": 0.14348144717126374, "cost": 161.22, "target_value": 264.39644717126373, "running_time": 101119.91381645203, "local_count": 123, "common_count": 77}}}, "sim2": {"simulation_id": 2, "user_seed": 11159717, "0": {"Nearest": {"max_delay": 0.14220553359683796, "cost": 0.0, "target_value": 142.20553359683797, "running_time": 0.0, "local_count": 200, "common_count": 0}, "M-Greedy": {"max_delay": 0.13266622778143516, "cost": 0.0, "target_value": 132.66622778143517, "running_time": 8612.442970275879, "n_selected_site": 10, "local_count": 86, "common_count": 114}, "M-Greedy-V2(Tx+Tp+Tq)": {"max_delay": 0.13266622778143516, "cost": 0.0, "target_value": 132.66622778143517, "running_time": 14386.87252998352, "n_selected_site": 6, "local_count": 38, "common_count": 162}, "Ours": {"max_delay": 0.13303030303030303, "cost": 0.0, "target_value": 133.03030303030303, "running_time": 89444.86594200134, "local_count": 72, "common_count": 128}}, "0.1": {"Nearest": {"max_delay": 0.14543955662424285, "cost": 237.98, "target_value": 169.23755662424284, "running_time": 5.003690719604492, "local_count": 200, "common_count": 0}, "M-Greedy": {"max_delay": 0.1344630034726123, "cost": 199.34, "target_value": 154.3970034726123, "running_time": 8551.584005355835, "n_selected_site": 10, "local_count": 86, "common_count": 114}, "M-Greedy-V2(Tx+Tp+Tq)": {"max_delay": 0.1344630034726123, "cost": 203.48, "target_value": 154.8110034726123, "running_time": 12662.485837936401, "n_selected_site": 8, "local_count": 38, "common_count": 162}, "Ours": {"max_delay": 0.13352013910750266, "cost": 196.73, "target_value": 153.19313910750265, "running_time": 104543.67113113403, "local_count": 91, "common_count": 109}}, "0.25": {"Nearest": {"max_delay": 0.14848562333522003, "cost": 220.31, "target_value": 203.56312333522004, "running_time": 4.003047943115234, "local_count": 200, "common_count": 0}, "M-Greedy": {"max_delay": 0.1390181292638657, "cost": 182.21, "target_value": 184.5706292638657, "running_time": 8611.76609992981, "n_selected_site": 10, "local_count": 86, "common_count": 114}, "M-Greedy-V2(Tx+Tp+Tq)": {"max_delay": 0.1390181292638657, "cost": 182.21, "target_value": 184.5706292638657, "running_time": 9963.109493255615, "n_selected_site": 6, "local_count": 38, "common_count": 162}, "Ours": {"max_delay": 0.13396275555864526, "cost": 177.67, "target_value": 178.38025555864525, "running_time": 105379.6317577362, "local_count": 127, "common_count": 73}}, "0.5": {"Nearest": {"max_delay": 0.1524017875559336, "cost": 208.12, "target_value": 256.4617875559336, "running_time": 5.003690719604492, "local_count": 200, "common_count": 0}, "M-Greedy": {"max_delay": 0.14335803797567023, "cost": 174.45, "target_value": 230.58303797567024, "running_time": 8631.63161277771, "n_selected_site": 10, "local_count": 86, "common_count": 114}, "M-Greedy-V2(Tx+Tp+Tq)": {"max_delay": 0.14335803797567023, "cost": 177.99, "target_value": 232.35303797567025, "running_time": 10178.72929573059, "n_selected_site": 6, "local_count": 38, "common_count": 162}, "Ours": {"max_delay": 0.13729707312438771, "cost": 164.19, "target_value": 219.3920731243877, "running_time": 102964.8654460907, "local_count": 138, "common_count": 62}}, "0.75": {"Nearest": {"max_delay": 0.16264525056334447, "cost": 202.47, "target_value": 314.4977505633444, "running_time": 3.001689910888672, "local_count": 200, "common_count": 0}, "M-Greedy": {"max_delay": 0.14335803797567023, "cost": 171.41, "target_value": 271.91553797567025, "running_time": 7678.276538848877, "n_selected_site": 10, "local_count": 86, "common_count": 114}, "M-Greedy-V2(Tx+Tp+Tq)": {"max_delay": 0.14335803797567023, "cost": 173.31, "target_value": 273.34053797567026, "running_time": 9163.187503814697, "n_selected_site": 6, "local_count": 38, "common_count": 162}, "Ours": {"max_delay": 0.14335803797567023, "cost": 160.68, "target_value": 263.86803797567023, "running_time": 99741.57667160034, "local_count": 146, "common_count": 54}}}, "sim3": {"simulation_id": 3, "user_seed": 191815031, "0": {"Nearest": {"max_delay": 0.14375485661424608, "cost": 0.0, "target_value": 143.75485661424608, "running_time": 0.0, "local_count": 200, "common_count": 0}, "M-Greedy": {"max_delay": 0.13266622778143516, "cost": 0.0, "target_value": 132.66622778143517, "running_time": 8651.327133178711, "n_selected_site": 10, "local_count": 60, "common_count": 140}, "M-Greedy-V2(Tx+Tp+Tq)": {"max_delay": 0.13266622778143516, "cost": 0.0, "target_value": 132.66622778143517, "running_time": 14491.332292556763, "n_selected_site": 6, "local_count": 40, "common_count": 160}, "Ours": {"max_delay": 0.13503030303030303, "cost": 0.0, "target_value": 135.03030303030303, "running_time": 90224.9948978424, "local_count": 140, "common_count": 60}}, "0.1": {"Nearest": {"max_delay": 0.14669942137319564, "cost": 245.67, "target_value": 171.26642137319564, "running_time": 4.003047943115234, "local_count": 200, "common_count": 0}, "M-Greedy": {"max_delay": 0.13484910126122301, "cost": 195.72, "target_value": 154.42110126122301, "running_time": 8508.851289749146, "n_selected_site": 10, "local_count": 60, "common_count": 140}, "M-Greedy-V2(Tx+Tp+Tq)": {"max_delay": 0.13484910126122301, "cost": 195.48, "target_value": 154.397101261223, "running_time": 13734.359979629517, "n_selected_site": 9, "local_count": 40, "common_count": 160}, "Ours": {"max_delay": 0.13373701836199076, "cost": 184.56, "target_value": 152.19301836199074, "running_time": 102383.81743431091, "local_count": 60, "common_count": 140}}, "0.25": {"Nearest": {"max_delay": 0.15131459989397134, "cost": 228.21, "target_value": 208.36709989397136, "running_time": 4.004001617431641, "local_count": 200, "common_count": 0}, "M-Greedy": {"max_delay": 0.137642440676862, "cost": 176.21, "target_value": 181.694940676862, "running_time": 8290.971755981445, "n_selected_site": 10, "local_count": 60, "common_count": 140}, "M-Greedy-V2(Tx+Tp+Tq)": {"max_delay": 0.137642440676862, "cost": 176.27, "target_value": 181.70994067686198, "running_time": 13346.813440322876, "n_selected_site": 9, "local_count": 40, "common_count": 160}, "Ours": {"max_delay": 0.1333825895195358, "cost": 167.44, "target_value": 175.24258951953578, "running_time": 100463.28043937683, "local_count": 98, "common_count": 102}}, "0.5": {"Nearest": {"max_delay": 0.15750183027180675, "cost": 215.76, "target_value": 265.38183027180673, "running_time": 3.002643585205078, "local_count": 200, "common_count": 0}, "M-Greedy": {"max_delay": 0.14068166022115464, "cost": 169.88, "target_value": 225.62166022115463, "running_time": 7938.970327377319, "n_selected_site": 10, "local_count": 60, "common_count": 140}, "M-Greedy-V2(Tx+Tp+Tq)": {"max_delay": 0.14068166022115464, "cost": 169.82, "target_value": 225.59166022115463, "running_time": 9366.049766540527, "n_selected_site": 6, "local_count": 40, "common_count": 160}, "Ours": {"max_delay": 0.13513739017181148, "cost": 161.39, "target_value": 215.83239017181148, "running_time": 91395.20049095154, "local_count": 103, "common_count": 97}}, "0.75": {"Nearest": {"max_delay": 0.15750183027180675, "cost": 210.59, "target_value": 315.44433027180673, "running_time": 3.0028820037841797, "local_count": 200, "common_count": 0}, "M-Greedy": {"max_delay": 0.14068166022115464, "cost": 169.88, "target_value": 268.0916602211546, "running_time": 7402.726888656616, "n_selected_site": 10, "local_count": 60, "common_count": 140}, "M-Greedy-V2(Tx+Tp+Tq)": {"max_delay": 0.14068166022115464, "cost": 169.82, "target_value": 268.04666022115464, "running_time": 8752.731800079346, "n_selected_site": 6, "local_count": 40, "common_count": 160}, "Ours": {"max_delay": 0.14068166022115464, "cost": 158.52, "target_value": 259.5716602211546, "running_time": 80903.1081199646, "local_count": 128, "common_count": 72}}}}}